Workbook

Sheet 00_README
A1: BARMM HEALTH SYSTEMS DIAGNOSTICS — CONSOLIDATED RAW DATA AND METADATA
A4: WHAT IS FACT, WHAT IS DERIVED
A5: Black text, no fill | B5: Value transcribed verbatim from the source document. This is the report as printed.
A6: Green fill | B6: LIVE FORMULA. Recomputed in this workbook from the raw inputs in the same row or sheet. Changing an input recalculates the result.
A7: Orange fill | B7: Locator block — document, label, section, subsection and printed page for the table that follows.
A8: Red-orange fill | B8: Variance, QA flag or unresolved item. Requires resolution before the figure is used for allocation.
A10: HOW TO READ THE SHEETS
A11: 01_Source_Register | B11: The five documents, their Google Doc IDs and links, coverage, evidence base and status as declared in each report's REPORT PARTICULARS block.
A12: 02_Section_Index | B12: Every numbered section and subsection of all five reports with the printed page number carried by that report's own contents list.
A13: 03_Table_Index | B13: Every table, exhibit and annex across the five reports: label, printed title, section number, subsection number, printed page, dimensions, source note, and the domain sheet where its data sits.
A14: 04_Report_Particulars | B14: Each report's own REPORT PARTICULARS block: who prepared it, under what programme, its declared coverage, its declared evidence base and package, and its declared status.
A15: 05_Assumptions | B15: The planning parameters the live formulas depend on — the 1:20,000 catchment standard, the rounding convention for implied units, the bed-rate denominator and the population base year. Edit the yellow cells and every dependent sheet recalculates.
A16: 10_Municipal_Master (live) | B16: The four LGU-level annex master tables harmonised into one register of 84 local government units plus Cotabato City, with live recomputation of population per rural health unit, the 1:20,000 implied requirement and shortfall, barangay coverage and beds per 1,000.
A17: 11 to 16 (live) | B17: Thematic recomputation sheets: jurisdiction roll-ups, PhilHealth accreditations, the Konsulta return, inpatient capacity, cold chain, the 1:20,000 standard, and the first-contact coverage gradient. Each carries the figure as printed alongside the live recomputation and the variance.
A18: D01 to D14 | B18: Every remaining table reproduced verbatim, grouped by subject domain, each under its locator block.
A19: 90_QA_Flags | B19: Numbering defects, duplicated labels, missing tables, denominator conflicts and cross-document divergences found during extraction.
A20: 91_Metadata_Dictionary | B20: Field definitions, units, bases and source layers.
A22: STANDING LIMITATIONS CARRIED FROM THE SOURCES
A23: Status | B23: All five reports are declared PROVISIONAL by their own particulars blocks. They establish cleaned service-location baselines, not validated registers of distinct licensed facilities.
A24: Registers | B24: Facility identity, classification, ownership, licensing and accreditation remain subject to reconciliation with MOH-BARMM, DOH-HFSRB and PhilHealth records.
A25: Denominators | B25: Barangay denominators are not consistent across documents. Lanao del Sur's annex preserves the 1,159-node 2020 model geography while current administrative coverage is 1,164 barangays; a five-barangay crosswalk is outstanding.
A26: Page numbers | B26: Page numbers are those printed in each document's own contents list at the time of export. They will move if the documents are repaginated. Section, subsection and table labels are the stable locators and are carried in every row.
A27: Do not use for | B27: Allocation, procurement or costing decisions until the QA flags on sheet 90 are closed.

Sheet 01_Source_Register
A1: Code | B1: Report title | C1: Google Doc file name | D1: Google Doc ID | E1: Link | F1: Scope / unit of analysis | G1: Coverage as declared | H1: Prepared by | I1: Prepared under | J1: Evidence base as declared | K1: Status as declared | L1: Export characters | M1: Export lines | N1: Sections captured | O1: Tables captured | P1: Export basis
A2: BARMM | B2: BARMM Regional Health Systems Diagnostic | C2: BARMM_Regional_Health_Systems_Diagnostic_2026 | D2: 1dzIeIl6jTtxzQXwrF24ZUHT6uOuRUBZV8E55xVY0pFU | E2: https://docs.google.com/document/d/1dzIeIl6jTtxzQXwrF24ZUHT6uOuRUBZV8E55xVY0pFU/edit | F2: Region-wide consolidation of four jurisdiction volumes | G2: 84 local government units, 1,735 current barangays and 3,137,511 residents in four jurisdictions. This is 69.0 per cent of the current PSA BARMM planning population. Basilan, Tawi-Tawi and Cotabato City are outside the workshop cycle; Sulu is outside the cycle and current BARMM. | H2: Lawrence John Paulo L. Trinidad · Consultant, International Organization for Migration (IOM) | I2: Building Resilience through Inclusive Governance and Healthcare Transformation in BARMM (BRIGHT-BARMM), a five-year initiative, 2025–2030 | J2: PSA 2024 Census and current PSGC; 2022 NDHS historical baseline; 2025 NDHS current regional key indicators; municipal scorecards; facility register; dated PhilHealth/Konsulta returns requiring current YAKAP verification; MOH-BARMM FHSIS assessment; WHO, World Bank and workshop records. | K2: Provisional. This consolidation carries forward the provisional status of all four volumes. No figure in it is validated beyond the validation each volume states its own figures require, and no figure in it should be used for allocation or procurement before the ninety-day programmes at Annex B are complete. | L2: 167357 | M2: 1004 | N2: 59 | O2: 27 | P2: 2026-08-11 (Asia/Manila) — Google Docs text export via Google Drive connector
A3: LDS | B3: Lanao del Sur Provincial Health Systems Diagnostic | C3: Lanao_del_Sur_Provincial_Health_Systems_Diagnostic_2026 | D3: 1iZhI2yG39xlDHiQUGLeSOtYpXfam9joZxB5eLtAqRU0 | E3: https://docs.google.com/document/d/1iZhI2yG39xlDHiQUGLeSOtYpXfam9joZxB5eLtAqRU0/edit | F3: Province of Lanao del Sur (40 LGUs incl. Marawi City) | G3: Seventeen (17) local government units of Lanao del Sur participating in the Evidence-Based Decision-Making (EBDM) workshop cycle | H3: Lawrence John Paulo L. Trinidad · Consultant, International Organization for Migration (IOM) | I3: Building Resilience through Inclusive Governance and Healthcare Transformation in BARMM (BRIGHT-BARMM) | J3: Municipal and provincial EBDM worksheet submissions (BARMM 20260629 package), audited into 442 raw rows, 407 cleaned service-location records and 174 records with named or typed facility evidence. Facility identity, classification, accreditation and cold-chain assets remain subject to reconciliation with MOH-BARMM/DOH, PhilHealth and local records. | K3: Provisional. The revision establishes a cleaned service-location baseline, not a validated count of distinct facilities. Registry reconciliation and field verification remain required before allocation or procurement. | L3: 172890 | M3: 1270 | N3: 57 | O3: 32 | P3: 2026-08-11 (Asia/Manila) — Google Docs text export via Google Drive connector
A4: MDN | B4: Maguindanao del Norte Provincial Health Systems Diagnostic | C4: Maguindanao_del_Norte_Provincial_Health_Systems_Diagnostic_2026 | D4: 1JLHwqdyuaFspWyMZVIoNMDLXeGYt1dX5ot2H6V5AST4 | E4: https://docs.google.com/document/d/1JLHwqdyuaFspWyMZVIoNMDLXeGYt1dX5ot2H6V5AST4/edit | F4: Province of Maguindanao del Norte (12 municipalities); Cotabato City shown separately | G4: Twelve (12) constituent municipalities of Maguindanao del Norte — the full complement of the province — participating in the Evidence-Based Decision-Making (EBDM) workshop cycle, together with the City of Cotabato, which participated as an adjunct reporting entity and is not a component local government unit of the province. | H4: Lawrence John Paulo L. Trinidad · Consultant, International Organization for Migration (IOM) | I4: Building Resilience through Inclusive Governance and Healthcare Transformation in BARMM (BRIGHT-BARMM) | J4: Municipal EBDM worksheet submissions (BARMM 20260629 package), audited into 300 raw rows, 230 rows attributable to the twelve constituent municipalities and 207 cleaned service-location records after removal of echo and padding rows. Forty-seven further rows belong to the City of Cotabato and twenty-three to Datu Paglas, a Maguindanao del Sur municipality misfiled in the provincial workbook. Read against the national facility registry (224 records in the twelve municipalities), the DOH LGU Health Scorecard municipal dataset, the MOH-BARMM FHSIS assessment and PhilHealth returns. | K4: Provisional. The report establishes a reconciled service-location baseline and a first municipal master table for a province created in 2022 and not yet carried as a separate reporting unit in most national datasets. Registry reconciliation, denominator validation and field verification remain required before allocation or procurement. | L4: 176250 | M4: 1226 | N4: 53 | O4: 33 | P4: 2026-08-11 (Asia/Manila) — Google Docs text export via Google Drive connector
A5: MDS | B5: Maguindanao del Sur Provincial Health Systems Diagnostic | C5: Maguindanao_del_Sur_Provincial_Health_Systems_Diagnostic_2026 | D5: 1hd1i9nx9ABMeMfDunmPezHI4grylzYzKH7RTHT2HG7Q | E5: https://docs.google.com/document/d/1hd1i9nx9ABMeMfDunmPezHI4grylzYzKH7RTHT2HG7Q/edit | F5: Province of Maguindanao del Sur (24 municipalities) | G5: The twenty-four (24) constituent municipalities of Maguindanao del Sur enumerated in Republic Act No. 11550, §3(b); 287 barangays; 813,243 residents at the 2024 Census | H5: Lawrence John Paulo L. Trinidad · Consultant, International Organization for Migration (IOM) | I5: Building Resilience through Inclusive Governance and Healthcare Transformation in BARMM (BRIGHT-BARMM) | J5: Official statistics for all 24 municipalities (PSA 2024 Census; DOH LGU Health Scorecard; the 222-record DOH/HFSRB facility register; PhilHealth returns of July 2024; the MOH-BARMM FHSIS assessment) tested against the EBDM workshop record filed by 21 of 24 local government units. Facility identity, classification, accreditation, workforce and revenue fields remain subject to reconciliation with MOH-BARMM/DOH, PhilHealth and local records. | K5: Provisional. This edition establishes a municipality-level baseline on official sources. It does not adopt the provincial dashboard circulated in the 20260624/20260629 package, which represents two of twenty-four municipalities and is treated in §2.5 as a reconciliation item to be corrected before use as evidence. | L5: 164015 | M5: 1133 | N5: 58 | O5: 27 | P5: 2026-08-11 (Asia/Manila) — Google Docs text export via Google Drive connector
A6: SGA | B6: Special Geographic Area Health Systems Diagnostic | C6: Special_Geographic_Area_Health_Systems_Diagnostic_2026 | D6: 1sc7EG9QPVDd5x_zTKnJbfOmBXOYgAdCbretmVNW1PE0 | E6: https://docs.google.com/document/d/1sc7EG9QPVDd5x_zTKnJbfOmBXOYgAdCbretmVNW1PE0/edit | F6: Special Geographic Area, PSGC 1999900000 (8 municipalities) | G6: The Special Geographic Area (PSGC 1999900000): eight municipalities, 63 barangays, 214,703 residents at the 2024 Census of Population. All eight municipalities are inside the evidence base. There is no absent cohort. | H6: Evidence-Based Decision-Making workstream, BRIGHT-BARMM, International Organization for Migration. | I6: The Executive Workshop on Evidence-Based Decision Making for Local Health Leaders (BRIGHT BARMM). | J6: Municipal EBDM worksheet submissions (BARMM 20260629 package), audited into 105 raw rows and 66 cleaned service-location records; the project-held DOH facility register (68 Special Geographic Area registrations); the MOH-BARMM FHSIS unit assessment (two of eight municipalities); the draft 2024 BARMM LGU Health Scorecard; PhilHealth's July 2024 returns to IOM; and the World Bank BARMM household survey, North Cotabato stratum. Facility identity, classification, ownership, licensing and accreditation remain subject to reconciliation with MOH-BARMM, DOH-HFSRB and PhilHealth records. | K6: Provisional. The report establishes a cleaned service-location baseline reconciled to the 2024 Census, not a validated register of distinct licensed facilities. Registry reconciliation, licensure verification and field validation remain required before allocation or procurement. | L6: 176673 | M6: 1228 | N6: 53 | O6: 29 | P6: 2026-08-11 (Asia/Manila) — Google Docs text export via Google Drive connector

Sheet 02_Section_Index
A1: Report | B1: Level | C1: Section no. | D1: Section / subsection title | E1: Printed page (document contents list) | F1: Parent section no. | G1: Parent section title | H1: Entry as printed
A2: BARMM | B2: Section | C2: 1 | D2: Executive Summary | E2: 4 | H2: 1 Executive Summary 4
A3: BARMM | B3: Subsection | D3: The central assessment | E3: 4 | F3: 1 | G3: Executive Summary | H3: The central assessment 4
A4: BARMM | B4: Subsection | D4: Eight findings | E4: 4 | F4: 1 | G4: Executive Summary | H4: Eight findings 4
A5: BARMM | B5: Subsection | D5: Decisions required of the Ministry | E5: 6 | F5: 1 | G5: Executive Summary | H5: Decisions required of the Ministry 6
A6: BARMM | B6: Section | C6: 2 | D6: Scope, Evidence and Method | E6: 9 | H6: 2 Scope, Evidence and Method 9
A7: BARMM | B7: Subsection | D7: What this consolidation is, and what it is not | E7: 9 | F7: 2 | G7: Scope, Evidence and Method | H7: What this consolidation is, and what it is not 9
A8: BARMM | B8: Subsection | D8: The evidence layers, consolidated | E8: 9 | F8: 2 | G8: Scope, Evidence and Method | H8: The evidence layers, consolidated 9
A9: BARMM | B9: Subsection | D9: The reconciliation rules carried forward | E9: 10 | F9: 2 | G9: Scope, Evidence and Method | H9: The reconciliation rules carried forward 10
A10: BARMM | B10: Subsection | D10: Relation to the superseded regional draft of 6 August 2026 | E10: 10 | F10: 2 | G10: Scope, Evidence and Method | H10: Relation to the superseded regional draft of 6 August 2026 10
A11: BARMM | B11: Section | C11: 3 | D11: Four Jurisdictions, Four Constraints | E11: 11 | H11: 3 Four Jurisdictions, Four Constraints 11
A12: BARMM | B12: Section | C12: 4 | D12: Stage One — The Illness | E12: 13 | H12: 4 Stage One — The Illness 13
A13: BARMM | B13: Subsection | D13: What the record does not yet support on mortality | E13: 13 | F13: 4 | G13: Stage One — The Illness | H13: What the record does not yet support on mortality 13
A14: BARMM | B14: Subsection | D14: The non-communicable disease loop | E14: 13 | F14: 4 | G14: Stage One — The Illness | H14: The non-communicable disease loop 13
A15: BARMM | B15: Subsection | D15: Tuberculosis: one detection ratio, three provinces | E15: 14 | F15: 4 | G15: Stage One — The Illness | H15: Tuberculosis: one detection ratio, three provinces 14
A16: BARMM | B16: Subsection | D16: The measles outbreak as arbitration | E16: 14 | F16: 4 | G16: Stage One — The Illness | H16: The measles outbreak as arbitration 14
A17: BARMM | B17: Section | C17: 5 | D17: Stage Two — First Contact | E17: 16 | H17: 5 Stage Two — First Contact 16
A18: BARMM | B18: Subsection | D18: The coverage gradient | E18: 16 | F18: 5 | G18: Stage Two — First Contact | H18: The coverage gradient 16
A19: BARMM | B19: Subsection | D19: The 1:20,000 standard is not a facility standard | E19: 16 | F19: 5 | G19: Stage Two — First Contact | H19: The 1:20,000 standard is not a facility standard 16
A20: BARMM | B20: Subsection | D20: The cold chain is not yet assessable from the record | E20: 17 | F20: 5 | G20: Stage Two — First Contact | H20: The cold chain is not yet assessable from the record 17
A21: BARMM | B21: Subsection | D21: Isolation is not yet measured in three of four jurisdictions | E21: 17 | F21: 5 | G21: Stage Two — First Contact | H21: Isolation is not yet measured in three of four jurisdictions 17
A22: BARMM | B22: Section | C22: 6 | D22: Stage Three — Payment | E22: 18 | H22: 6 Stage Three — Payment 18
A23: BARMM | B23: Subsection | D23: The perimeter | E23: 18 | F23: 6 | G23: Stage Three — Payment | H23: The perimeter 18
A24: BARMM | B24: Subsection | D24: The throughput not yet computable | E24: 18 | F24: 6 | G24: Stage Three — Payment | H24: The throughput not yet computable 18
A25: BARMM | B25: Subsection | D25: The area absent from the current line item | E25: 19 | F25: 6 | G25: Stage Three — Payment | H25: The area absent from the current line item 19
A26: BARMM | B26: Subsection | D26: What the household pays | E26: 19 | F26: 6 | G26: Stage Three — Payment | H26: What the household pays 19
A27: BARMM | B27: Section | C27: 7 | D27: Stage Four — Referral | E27: 21 | H27: 7 Stage Four — Referral 21
A28: BARMM | B28: Subsection | D28: The inpatient stock | E28: 21 | F28: 7 | G28: Stage Four — Referral | H28: The inpatient stock 21
A29: BARMM | B29: Subsection | D29: Three different ownership exposures | E29: 21 | F29: 7 | G29: Stage Four — Referral | H29: Three different ownership exposures 21
A30: BARMM | B30: Subsection | D30: The referral measurement gap | E30: 22 | F30: 7 | G30: Stage Four — Referral | H30: The referral measurement gap 22
A31: BARMM | B31: Subsection | D31: The service-delivery network document not yet located | E31: 22 | F31: 7 | G31: Stage Four — Referral | H31: The service-delivery network document not yet located 22
A32: BARMM | B32: Section | C32: 8 | D32: Stage Five — Follow-Up and the Record | E32: 24 | H32: 8 Stage Five — Follow-Up and the Record 24
A33: BARMM | B33: Subsection | D33: The FHSIS apparatus | E33: 24 | F33: 8 | G33: Stage Five — Follow-Up and the Record | H33: The FHSIS apparatus 24
A34: BARMM | B34: Subsection | D34: The instrument requires repair | E34: 24 | F34: 8 | G34: Stage Five — Follow-Up and the Record | H34: The instrument requires repair 24
A35: BARMM | B35: Subsection | D35: Civil registration and the invisible denominator | E35: 25 | F35: 8 | G35: Stage Five — Follow-Up and the Record | H35: Civil registration and the invisible denominator 25
A36: BARMM | B36: Section | C36: 9 | D36: The Reconciliation | E36: 26 | H36: 9 The Reconciliation 26
A37: BARMM | B37: Subsection | D37: What the divergence means for regional allocation | E37: 26 | F37: 9 | G37: The Reconciliation | H37: What the divergence means for regional allocation 26
A38: BARMM | B38: Section | C38: 10 | D38: The Evidence Pipeline | E38: 28 | H38: 10 The Evidence Pipeline 28
A39: BARMM | B39: Section | C39: A | D39: catalogue of data-build issues | E39: 28 | H39: A catalogue of data-build issues 28
A40: BARMM | B40: Subsection | D40: The composite score | E40: 28 | F40: A | G40: catalogue of data-build issues | H40: The composite score 28
A41: BARMM | B41: Subsection | D41: What a corrected build requires | E41: 29 | F41: A | G41: catalogue of data-build issues | H41: What a corrected build requires 29
A42: BARMM | B42: Section | C42: 11 | D42: Governance and Legal Framework | E42: 30 | H42: 11 Governance and Legal Framework 30
A43: BARMM | B43: Subsection | D43: Three corrections of record | E43: 31 | F43: 11 | G43: Governance and Legal Framework | H43: Three corrections of record 31
A44: BARMM | B44: Subsection | D44: Two questions for referral | E44: 31 | F44: 11 | G44: Governance and Legal Framework | H44: Two questions for referral 31
A45: BARMM | B45: Subsection | D45: Two powers not exercised | E45: 31 | F45: 11 | G45: Governance and Legal Framework | H45: Two powers not exercised 31
A46: BARMM | B46: Section | C46: 12 | D46: Priorities: sequencing the Ministry’s own decisions | E46: 32 | H46: 12 Priorities: sequencing the Ministry’s own decisions 32
A47: BARMM | B47: Section | C47: 13 | D47: Two-Year Investment Logic, 2026–2028 | E47: 33 | H47: 13 Two-Year Investment Logic, 2026–2028 33
A48: BARMM | B48: Subsection | D48: Regional volumetrics | E48: 33 | F48: 13 | G48: Two-Year Investment Logic, 2026–2028 | H48: Regional volumetrics 33
A49: BARMM | B49: Subsection | D49: The programme | E49: 33 | F49: 13 | G49: Two-Year Investment Logic, 2026–2028 | H49: The programme 33
A50: BARMM | B50: Subsection | D50: Allocation basis, and why no envelope is costed | E50: 34 | F50: 13 | G50: Two-Year Investment Logic, 2026–2028 | H50: Allocation basis, and why no envelope is costed 34
A51: BARMM | B51: Section | C51: 14 | D51: Monitoring Framework | E51: 35 | H51: 14 Monitoring Framework 35
A52: BARMM | B52: Section | C52: 15 | D52: Methodology, Evidence Tiers and Limitations | E52: 36 | H52: 15 Methodology, Evidence Tiers and Limitations 36
A53: BARMM | B53: Section | C53: — | D53: References | E53: 37 | H53: — References 37
A54: BARMM | B54: Section | C54: A | D54: Annex A — Jurisdiction master table (landscape) | E54: 38 | H54: A Annex A — Jurisdiction master table (landscape) 38
A55: BARMM | B55: Section | C55: B | D55: Annex B — Consolidated ninety-day programme (landscape) | E55: 39 | H55: B Annex B — Consolidated ninety-day programme (landscape) 39
A56: BARMM | B56: Section | C56: C | D56: Annex C — Regional evidence gap register | E56: 41 | H56: C Annex C — Regional evidence gap register 41
A57: BARMM | B57: Section | C57: D | D57: Annex D — Divergences between the four volumes (landscape) | E57: 42 | H57: D Annex D — Divergences between the four volumes (landscape) 42
A58: LDS | B58: Section | C58: 1 | D58: Executive Summary | E58: 4 | H58: 1 Executive Summary 4
A59: LDS | B59: Subsection | D59: The central assessment | E59: 4 | F59: 1 | G59: Executive Summary | H59: The central assessment 4
A60: LDS | B60: Subsection | D60: Six findings | E60: 5 | F60: 1 | G60: Executive Summary | H60: Six findings 5
A61: LDS | B61: Subsection | D61: Decisions required of provincial leadership | E61: 6 | F61: 1 | G61: Executive Summary | H61: Decisions required of provincial leadership 6
A62: LDS | B62: Section | C62: 2 | D62: Program, Scope, Evidence and Method | E62: 8 | H62: 2 Program, Scope, Evidence and Method 8
A63: LDS | B63: Subsection | C63: 2.2 | D63: The five evidence layers | E63: 8 | F63: 2 | G63: Program, Scope, Evidence and Method | H63: 2.2 The five evidence layers 8
A64: LDS | B64: Subsection | C64: 2.3 | D64: The reconciliation rule | E64: 9 | F64: 2 | G64: Program, Scope, Evidence and Method | H64: 2.3 The reconciliation rule 9
A65: LDS | B65: Subsection | C65: 2.4 | D65: From the Executive Workshop on Evidence-based Decision Making (BRIGHT BARMM) | E65: 9 | F65: 2 | G65: Program, Scope, Evidence and Method | H65: 2.4 From the Executive Workshop on Evidence-based Decision Making (BRIGHT BARMM) 9
A66: LDS | B66: Section | C66: 3 | D66: Stage One — The Illness | E66: 11 | H66: 3 Stage One — The Illness 11
A67: LDS | B67: Subsection | C67: 3.1 | D67: The provincial cause profile | E67: 11 | F67: 3 | G67: Stage One — The Illness | H67: 3.1 The provincial cause profile 11
A68: LDS | B68: Subsection | C68: 3.2 | D68: The child-survival signature | E68: 12 | F68: 3 | G68: Stage One — The Illness | H68: 3.2 The child-survival signature 12
A69: LDS | B69: Subsection | C69: 3.3 | D69: What can and cannot be said at municipal level | E69: 13 | F69: 3 | G69: Stage One — The Illness | H69: 3.3 What can and cannot be said at municipal level 13
A70: LDS | B70: Subsection | C70: 3.4 | D70: The 2023–2024 measles outbreak | E70: 15 | F70: 3 | G70: Stage One — The Illness | H70: 3.4 The 2023–2024 measles outbreak 15
A71: LDS | B71: Subsection | C71: 3.5 | D71: The non-communicable disease service gap | E71: 16 | F71: 3 | G71: Stage One — The Illness | H71: 3.5 The non-communicable disease service gap 16
A72: LDS | B72: Section | C72: 4 | D72: Primary-Care Access: physical, effective and registered | E72: 17 | H72: 4 Primary-Care Access: physical, effective and registered 17
A73: LDS | B73: Subsection | C73: 4.0 | D73: Physical and effective access: what the model establishes | E73: 17 | F73: 4 | G73: Primary-Care Access: physical, effective and registered | H73: 4.0 Physical and effective access: what the model establishes 17
A74: LDS | B74: Subsection | C74: 4.1 | D74: The physical-access result is assumption-sensitive | E74: 17 | F74: 4 | G74: Primary-Care Access: physical, effective and registered | H74: 4.1 The physical-access result is assumption-sensitive 17
A75: LDS | B75: Subsection | C75: 4.2 | D75: Where the physical gap is | E75: 18 | F75: 4 | G75: Primary-Care Access: physical, effective and registered | H75: 4.2 Where the physical gap is 18
A76: LDS | B76: Subsection | C76: 4.3 | D76: A consistency test of the modeled result | E76: 20 | F76: 4 | G76: Primary-Care Access: physical, effective and registered | H76: 4.3 A consistency test of the modeled result 20
A77: LDS | B77: Subsection | C77: 4.4 | D77: Effective access, and the population the province cannot yet assess | E77: 22 | F77: 4 | G77: Primary-Care Access: physical, effective and registered | H77: 4.4 Effective access, and the population the province cannot yet assess 22
A78: LDS | B78: Subsection | C78: 4.5 | D78: What the model assumes, and what it cannot see | E78: 22 | F78: 4 | G78: Primary-Care Access: physical, effective and registered | H78: 4.5 What the model assumes, and what it cannot see 22
A79: LDS | B79: Subsection | C79: 4.6 | D79: The facility stock | E79: 23 | F79: 4 | G79: Primary-Care Access: physical, effective and registered | H79: 4.6 The facility stock 23
A80: LDS | B80: Subsection | C80: 4.7 | D80: Catchment adequacy against the 1:20,000 standard | E80: 23 | F80: 4 | G80: Primary-Care Access: physical, effective and registered | H80: 4.7 Catchment adequacy against the 1:20,000 standard 23
A81: LDS | B81: Subsection | C81: 4.8 | D81: Geographic isolation | E81: 25 | F81: 4 | G81: Primary-Care Access: physical, effective and registered | H81: 4.8 Geographic isolation 25
A82: LDS | B82: Subsection | C82: 4.9 | D82: Maternal and newborn services | E82: 26 | F82: 4 | G82: Primary-Care Access: physical, effective and registered | H82: 4.9 Maternal and newborn services 26
A83: LDS | B83: Subsection | C83: 4.10 | D83: Immunization and the 2023–2024 outbreak | E83: 27 | F83: 4 | G83: Primary-Care Access: physical, effective and registered | H83: 4.10 Immunization and the 2023–2024 outbreak 27
A84: LDS | B84: Section | C84: 5 | D84: Stage Three — Payment | E84: 28 | H84: 5 Stage Three — Payment 28
A85: LDS | B85: Subsection | C85: 5.1 | D85: Universal by law, partial in fact | E85: 28 | F85: 5 | G85: Stage Three — Payment | H85: 5.1 Universal by law, partial in fact 28
A86: LDS | B86: Subsection | C86: 5.2 | D86: The accreditation base | E86: 28 | F86: 5 | G86: Stage Three — Payment | H86: 5.2 The accreditation base 28
A87: LDS | B87: Subsection | C87: 5.3 | D87: Registration without utilization | E87: 29 | F87: 5 | G87: Stage Three — Payment | H87: 5.3 Registration without utilization 29
A88: LDS | B88: Subsection | C88: 5.4 | D88: Implications for household financial burden | E88: 30 | F88: 5 | G88: Stage Three — Payment | H88: 5.4 Implications for household financial burden 30
A89: LDS | B89: Section | C89: 6 | D89: Stage Four — Referral | E89: 31 | H89: 6 Stage Four — Referral 31
A90: LDS | B90: Subsection | C90: 6.1 | D90: The hospital stock and its geography | E90: 31 | F90: 6 | G90: Stage Four — Referral | H90: 6.1 The hospital stock and its geography 31
A91: LDS | B91: Subsection | C91: 6.2 | D91: Referral concentration and system resilience | E91: 32 | F91: 6 | G91: Stage Four — Referral | H91: 6.2 Referral concentration and system resilience 32
A92: LDS | B92: Subsection | C92: 6.3 | D92: Referral completion: a priority measurement gap | E92: 33 | F92: 6 | G92: Stage Four — Referral | H92: 6.3 Referral completion: a priority measurement gap 33
A93: LDS | B93: Subsection | C93: 6.4 | D93: The absent catchment map | E93: 33 | F93: 6 | G93: Stage Four — Referral | H93: 6.4 The absent catchment map 33
A94: LDS | B94: Section | C94: 7 | D94: Stage Five — Follow-Up and the Record | E94: 34 | H94: 7 Stage Five — Follow-Up and the Record 34
A95: LDS | B95: Subsection | C95: 7.1 | D95: Continuity after the encounter | E95: 34 | F95: 7 | G95: Stage Five — Follow-Up and the Record | H95: 7.1 Continuity after the encounter 34
A96: LDS | B96: Subsection | C96: 7.2 | D96: The FHSIS apparatus | E96: 34 | F96: 7 | G96: Stage Five — Follow-Up and the Record | H96: 7.2 The FHSIS apparatus 34
A97: LDS | B97: Subsection | C97: 7.3 | D97: Civil registration and the invisible denominator | E97: 35 | F97: 7 | G97: Stage Five — Follow-Up and the Record | H97: 7.3 Civil registration and the invisible denominator 35
A98: LDS | B98: Section | C98: 8 | D98: The Reconciliation | E98: 36 | H98: 8 The Reconciliation 36
A99: LDS | B99: Subsection | D99: What the divergence means for allocation | E99: 36 | F99: 8 | G99: The Reconciliation | H99: What the divergence means for allocation 36
A100: LDS | B100: Section | C100: 9 | D100: Governance and Legal Framework | E100: 38 | H100: 9 Governance and Legal Framework 38
...

Sheet 03_Table_Index
A1: Report | B1: Label | C1: Printed title / caption | D1: Section no. | E1: Section title | F1: Subsection no. | G1: Subsection title | H1: Printed page | I1: Rows (data) | J1: Columns | K1: Domain sheet | L1: Domain | M1: Source note as printed | N1: Export line no.
A2: BARMM | B2: (unlabelled) | C2: # 1 Executive Summary | D2: 1 | E2: Executive Summary | H2: 4 | I2: 0 | J2: 7 | K2: D01 | L2: Executive summary and headline panels | N2: 182
A3: BARMM | B3: (unlabelled) | C3: | 84local government units infour jurisdictions | | 3,137,511 residents, 2024 Census — 55.1% of the 1 July 2024 BARMM-with-Sulu total; 69.0% of current BARMM | | 1,735 current barangays | | 756registered health facilitieson the registry basis | | D3: 1 | E3: Executive Summary | H3: 4 | I3: 0 | J3: 7 | K3: D04 | L3: First contact, facilities and catchment | N3: 188
A4: BARMM | B4: EXHIBIT 1 | C4: Four jurisdictions, four distinct constraints, three shared findings | D4: 1 | E4: Executive Summary | G4: Eight findings | H4: 4 | I4: 5 | J4: 4 | K4: D02 | L4: Evidence base, scope and method | N4: 220
A5: BARMM | B5: TABLE 1 | C5: The four volumes at a glance | D5: 2 | E5: Scope, Evidence and Method | G5: What this consolidation is, and what it is not | H5: 9 | I5: 5 | J5: 6 | K5: D02 | L5: Evidence base, scope and method | N5: 267
A6: BARMM | B6: TABLE 2 | C6: The evidence layers and what each can carry across four jurisdictions | D6: 2 | E6: Scope, Evidence and Method | G6: The evidence layers, consolidated | H6: 9 | I6: 5 | J6: 5 | K6: D02 | L6: Evidence base, scope and method | N6: 284
A7: BARMM | B7: EXHIBIT 2 | C7: The regional dashboard: what each jurisdiction can and cannot measure | D7: 3 | E7: Four Jurisdictions, Four Constraints | H7: 11 | I7: 16 | J7: 6 | K7: D02 | L7: Evidence base, scope and method | N7: 319
A8: BARMM | B8: TABLE 3 | C8: What the evidence establishes, and does not establish, about disease burden | D8: 4 | E8: Stage One — The Illness | G8: What the record does not yet support on mortality | H8: 13 | I8: 6 | J8: 3 | K8: D03 | L8: Disease burden and service coverage | N8: 353
A9: BARMM | B9: EXHIBIT 3 | C9: Adults risk-assessed under PhilPEN, by jurisdiction | D9: 4 | E9: Stage One — The Illness | G9: The non-communicable disease loop | H9: 13 | I9: 4 | J9: 5 | K9: D03 | L9: Disease burden and service coverage | N9: 377
A10: BARMM | B10: EXHIBIT 4 | C10: The first-contact coverage gradient: 11 per cent to 100 per cent | D10: 5 | E10: Stage Two — First Contact | G10: The coverage gradient | H10: 16 | I10: 4 | J10: 6 | K10: D04 | L10: First contact, facilities and catchment | N10: 409
A11: BARMM | B11: TABLE 4 | C11: Rural health units against the 1:20,000 planning target | D11: 5 | E11: Stage Two — First Contact | G11: The 1:20,000 standard is not a facility standard | H11: 16 | I11: 5 | J11: 6 | K11: D04 | L11: First contact, facilities and catchment | N11: 425
A12: BARMM | B12: EXHIBIT 5 | C12: Cold chain: 115 functional, 353 not stated, out of 836 records | D12: 5 | E12: Stage Two — First Contact | G12: The cold chain is not yet assessable from the record | H12: 16 | I12: 5 | J12: 6 | K12: D05 | L12: Cold chain and commodities | N12: 444
A13: BARMM | B13: TABLE 5 | C13: PhilHealth-accredited health care institutions, BARMM by province | D13: 6 | E13: Stage Three — Payment | G13: The perimeter | H13: 18 | I13: 12 | J13: 10 | K13: D06 | L13: Payment, PhilHealth and financing | N13: 471
A14: BARMM | B14: TABLE 6 | C14: The PhilHealth Konsulta return, and its three arithmetic failures | D14: 6 | E14: Stage Three — Payment | G14: The throughput not yet computable | H14: 18 | I14: 9 | J14: 6 | K14: D06 | L14: Payment, PhilHealth and financing | N14: 499
A15: BARMM | B15: TABLE 7 | C15: Licensed inpatient capacity across the four jurisdictions | D15: 7 | E15: Stage Four — Referral | G15: The inpatient stock | H15: 21 | I15: 5 | J15: 8 | K15: D07 | L15: Referral and inpatient capacity | N15: 532
A16: BARMM | B16: EXHIBIT 6 | C16: The referral measurement gap: zero observations across 57 reporting units | D16: 7 | E16: Stage Four — Referral | G16: The referral measurement gap | H16: 21 | I16: 5 | J16: 5 | K16: D07 | L16: Referral and inpatient capacity | N16: 565
A17: BARMM | B17: TABLE 8 | C17: The condition of routine reporting: 68 assessed units | D17: 8 | E17: Stage Five — Follow-Up and the Record | G17: The FHSIS apparatus | H17: 24 | I17: 13 | J17: 6 | K17: D08 | L17: Routine reporting, FHSIS and civil registration | N17: 588
A18: BARMM | B18: EXHIBIT 7 | C18: Five divergences between the administrative record and independent measurement | D18: 9 | E18: The Reconciliation | H18: 26 | I18: 5 | J18: 4 | K18: D09 | L18: Reconciliation and divergences | N18: 631
A19: BARMM | B19: TABLE 9 | C19: The parser and build issues, by jurisdiction | D19: 10 | E19: The Evidence Pipeline | G19: A catalogue of data-build issues | H19: 28 | I19: 7 | J19: 4 | K19: D02 | L19: Evidence base, scope and method | N19: 660
A20: BARMM | B20: TABLE 10 | C20: Legal obligations engaged by the consolidated findings | D20: 11 | E20: Governance and Legal Framework | H20: 30 | I20: 9 | J20: 4 | K20: D10 | L20: Governance and legal framework | N20: 691
A21: BARMM | B21: EXHIBIT 8 | C21: Sequencing: what the Ministry must settle before anything else can be sized | D21: 12 | E21: Priorities: sequencing the Ministry’s own decisions | H21: 32 | I21: 7 | J21: 5 | K21: D11 | L21: Priorities and sequencing | N21: 736
A22: BARMM | B22: EXHIBIT 9 | C22: Regional volumetrics for the two-year programme | D22: 13 | E22: Two-Year Investment Logic, 2026–2028 | G22: Regional volumetrics | H22: 33 | I22: 13 | J22: 3 | K22: D12 | L22: Investment logic and volumetrics | N22: 761
A23: BARMM | B23: TABLE 11 | C23: The two-year programme: volumetrics, sequencing and financing route | D23: 13 | E23: Two-Year Investment Logic, 2026–2028 | G23: The programme | H23: 33 | I23: 11 | J23: 5 | K23: D12 | L23: Investment logic and volumetrics | N23: 784
A24: BARMM | B24: TABLE 12 | C24: Regional monitoring indicators | D24: 14 | E24: Monitoring Framework | H24: 35 | I24: 14 | J24: 5 | K24: D13 | L24: Monitoring indicators | N24: 815
A25: BARMM | B25: ANNEX A | C25: # A Annex A — Jurisdiction master table | D25: A | E25: Annex A — Jurisdiction master table | H25: 28 | I25: 5 | J25: 16 | K25: D14 | L25: Annexes, master tables and gap registers | N25: 918
A26: BARMM | B26: ANNEX B | C26: Each of the four volumes carries its own validation programme, structured for completion within ninety days of adoption by the responsible health board, and none requires capital expenditure. The table consolidates the twenty-nine tasks in those four programmes into nineteen, and separates what the jurisdictions owe from what the Ministry owes. Ten of the nineteen require Ministry initiation or coordination; those are the rows prefixed M, and the four capital programmes are contingent on them. | D26: B | E26: Annex B — Consolidated ninety-day programme | H26: 39 | I26: 19 | J26: 6 | K26: D14 | L26: Annexes, master tables and gap registers | N26: 934
A27: BARMM | B27: ANNEX C | C27: Sixty items are recorded across the four volumes’ own gap registers. The fourteen below are those that recur in two or more jurisdictions, or that a single jurisdiction identifies as decisive. They are ordered by consequence. Twelve of the fourteen are documents retrievable by written request; two require field collection; none requires a new research design. | D27: C | E27: Annex C — Regional evidence gap register | H27: 41 | I27: 14 | J27: 4 | K27: D14 | L27: Annexes, master tables and gap registers | N27: 964
A28: BARMM | B28: ANNEX D | C28: The four volumes were built sequentially and each corrected findings in its predecessors. Eleven divergences remain unresolved between them. They are recorded here rather than adjudicated, because resolving them requires a source the consolidation does not hold. Item 2 is load-bearing: it determines whether any jurisdiction in the series can state its leading causes of death. | D28: D | E28: Annex D — Divergences between the four volumes | H28: 42 | I28: 11 | J28: 5 | K28: D14 | L28: Annexes, master tables and gap registers | N28: 989
A29: LDS | B29: (unlabelled) | C29: # 1 Executive Summary | D29: 1 | E29: Executive Summary | H29: 4 | I29: 0 | J29: 7 | K29: D01 | L29: Executive summary and headline panels | N29: 190
A30: LDS | B30: (unlabelled) | C30: | 11licensed hospitals | | D30: 1 | E30: Executive Summary | H30: 4 | I30: 0 | J30: 7 | K30: D07 | L30: Referral and inpatient capacity | N30: 202
A31: LDS | B31: EXHIBIT 1 | C31: The five stages, and what fails at each one | D31: 1 | E31: Executive Summary | G31: Six findings | H31: 4 | I31: 5 | J31: 4 | K31: D01 | L31: Executive summary and headline panels | M31: Note. Each claim is evidenced in the section indicated. Adapted from Philippine Statistics Authority (2025c); Philippine Statistics Authority and ICF (2023); Department of Health (n.d.-a, 2020b, 2022); Philippine Health Insurance Corporation (2024); World Bank (2019); and International Organization for Migration (2026a). | N31: 241
A32: LDS | B32: TABLE 2 | C32: Completion of required worksheet outputs across the cohort | D32: 2 | E32: Program, Scope, Evidence and Method | H32: 8 | I32: 4 | J32: 4 | K32: D02 | L32: Evidence base, scope and method | N32: 274
A33: LDS | B33: TABLE 1 | C33: The five evidence layers and what each can carry | D33: 2 | E33: Program, Scope, Evidence and Method | F33: 2.2 | G33: The five evidence layers | H33: 8 | I33: 5 | J33: 5 | K33: D02 | L33: Evidence base, scope and method | N33: 292
A34: LDS | B34: (unlabelled) | C34: The 407 cleaned service-location records filed by fifteen local government units, resolved into three components. Source: EBDM worksheet package, 20260629. | D34: 2 | E34: Program, Scope, Evidence and Method | F34: 2.4 | G34: From the Executive Workshop on Evidence-based Decision Making (BRIGHT BARMM) | H34: 9 | I34: 0 | J34: 2 | K34: D02 | L34: Evidence base, scope and method | N34: 320
A35: LDS | B35: TABLE 2 | C35: Leading causes of morbidity and mortality, Lanao del Sur | D35: 3 | E35: Stage One — The Illness | F35: 3.1 | G35: The provincial cause profile | H35: 11 | I35: 10 | J35: 4 | K35: D03 | L35: Disease burden and service coverage | M35: Note. Adapted from World Bank (2019, Table 41, p. 113), reporting Department of Health–ARMM data. Bold entries are non-communicable or trauma causes. No year is stated for the underlying data; the source notes that collection took place during the conflict period, and the profile should be treated as circa 2016–2018. | N35: 340
A36: LDS | B36: EXHIBIT 2 | C36: Child deaths in BARMM fall after the first month rather than during it | D36: 3 | E36: Stage One — The Illness | F36: 3.2 | G36: The child-survival signature | H36: 12 | I36: 0 | J36: 2 | K36: D03 | L36: Disease burden and service coverage | M36: Note. Deaths per 1,000 live births. Adapted from Philippine Statistics Authority and ICF (2023, Tables 8.1 and 8.3). The figures are historical 2022 regional estimates: BARMM rates use a ten-year reference period, while national comparators use five years. Under-five mortality was 28 per 1,000. In the published tables, 98 children and 188 births are weighted denominators; 180 children and 345 births are the corresponding unweighted cases. The latest 2025 NDHS key indicators do not provide an updated regional child-mortality series. | N36: 372
A37: LDS | B37: EXHIBIT 4 | C37: The measles chain: a survey finding, an outbreak, and thirteen deaths | D37: 3 | E37: Stage One — The Illness | F37: 3.4 | G37: The 2023–2024 measles outbreak | H37: 15 | I37: 8 | J37: 4 | K37: D03 | L37: Disease burden and service coverage | M37: Note. Adapted from Philippine Statistics Authority and ICF (2023, Table 10.4.2); Department of Health (n.d.-a); UNICEF Philippines (2024); and Bangsamoro Information Office (2024). The Provincial Health Officer II of Lanao del Sur is quoted attributing the outbreak to “the decline of our immunization rate here in Lanao del Sur” (Bangsamoro Information Office, 2024). The Regional Darul Ifta’ issued a fatwa declaring the vaccines halal — a documented and replicable demand-side intervention. | N37: 416
A38: LDS | B38: (unlabelled) | C38: Facility counts and travel times answer different questions, and the province needs both. A registration is not a building, a building within reach is not an open service, and an open service is not necessarily ready to treat the patient in front of it. The multimodal accessibility model of 8 August 2026 separates these questions for the first time. Its central result is that physical proximity is not, on the assumptions used, the constraint that binds for most of Lanao del Sur. Section 4.3 sets out a consistency test that qualifies how far that result can be carried. | D38: 4 | E38: Primary-Care Access: physical, effective and registered | F38: 4.0 | G38: Physical and effective access: what the model establishes | H38: 17 | I38: 0 | J38: 5 | K38: D04 | L38: First contact, facilities and catchment | M38: Note. Adapted from the Lanao del Sur multimodal and effective primary-care accessibility model (International Organization for Migration, 2026b). Population uses the GeoRisk/PSA 2020 modeled base of 1,195,518 across 1,159 demand nodes against 184 barangay health station and rural health unit supply points. The supply set requires reconciliation: the project-held facility register carries 128 barangay health stations and 44 rural health units, or 172 supply points, and the derivation of the further 12 used by the model is not documented in the material reviewed. The 2024 equivalent of the physical gap is 132,217 by proportional scaling to 1,368,137; it is not a barangay-level 2024 measurement. | N38: 450
A39: LDS | B39: TABLE A | C39: The modeled gap does not vary with facility supply | D39: 4 | E39: Primary-Care Access: physical, effective and registered | F39: 4.3 | G39: A consistency test of the modeled result | H39: 20 | I39: 3 | J39: 3 | K39: D04 | L39: First contact, facilities and catchment | M39: Note. Computed for this report across all 40 local government units, from the central 30-minute multimodal scenario (International Organization for Migration, 2026b) against the project-held facility register and the DOH GIDA barangay register (Department of Health, 2022). A facility-driven access result would show a positive association with barangays per supply point; the observed association is negative on both measures. The strongest association in the set is with geographic isolation. | N39: 500
A40: LDS | B40: (unlabelled) | C40: Physical reach is a necessary condition, not a sufficient one. The model applies a readiness credit to a supply point only where the workshop record provides a direct municipality-and-barangay match and at least half of the planned readiness dimensions were observed — service inventory, workforce, equipment, cold chain, PhilHealth status and referral turnaround. Fifty-nine supply points have a direct match; fifty-seven meet the credit threshold. | D40: 4 | E40: Primary-Care Access: physical, effective and registered | F40: 4.4 | G40: Effective access, and the population the province cannot yet assess | H40: 22 | I40: 0 | J40: 7 | K40: D07 | L40: Referral and inpatient capacity | M40: Note. Adapted from International Organization for Migration (2026b). Municipality profiles inform prioritization but do not impute facility-level credit. | N40: 529
A41: LDS | B41: (unlabelled) | C41: ## 4.5 What the model assumes, and what it cannot see | D41: 4 | E41: Primary-Care Access: physical, effective and registered | F41: 4.5 | G41: What the model assumes, and what it cannot see | H41: 22 | I41: 0 | J41: 2 | K41: D04 | L41: First contact, facilities and catchment | M41: Note. Adapted from International Organization for Migration (2026b). Model outputs are planning estimates and screening signals. They identify where verification and investment must begin; they do not authorize capital construction. | N41: 543
A42: LDS | B42: (unlabelled) | C42: Section 17 of the Local Government Code devolves primary health care to the municipality, and national facility planning carries an expectation of one barangay health station per barangay. The PHFDP 2020 baseline measured the then-ARMM/BARMM footprint at 650 stations against 2,535 barangays, a ratio of 0.3 and a historical gap of 1,885 stations (Department of Health, 2020b, Table 6). This is a dated planning baseline, not the current 2026 regional denominator. On current PSA geography Lanao del Sur has 1,164 barangays; the project-held register matches 128 stations, subject to reconciliation. | D42: 4 | E42: Primary-Care Access: physical, effective and registered | F42: 4.6 | G42: The facility stock | H42: 23 | I42: 0 | J42: 5 | K42: D04 | L42: First contact, facilities and catchment | N42: 553
A43: LDS | B43: TABLE 4 | C43: First-contact infrastructure by municipality, ranked by population | D43: 4 | E43: Primary-Care Access: physical, effective and registered | F43: 4.7 | G43: Catchment adequacy against the 1:20,000 standard | H43: 23 | I43: 41 | J43: 10 | K43: D04 | L43: First contact, facilities and catchment | N43: 591
A44: LDS | B44: TABLE 5 | C44: The twelve most isolated municipalities | D44: 4 | E44: Primary-Care Access: physical, effective and registered | F44: 4.8 | G44: Geographic isolation | H44: 25 | I44: 12 | J44: 8 | K44: D04 | L44: First contact, facilities and catchment | N44: 646
A45: LDS | B45: TABLE 5 | C45: PhilHealth-accredited health care institutions, BARMM by province | D45: 5 | E45: Stage Three — Payment | F45: 5.2 | G45: The accreditation base | H45: 28 | I45: 13 | J45: 9 | K45: D06 | L45: Payment, PhilHealth and financing | M45: Note. Adapted from Philippine Health Insurance Corporation (2024), accredited health care institutions by province and type as of 31 July 2024. Counts are of accreditations, not distinct facilities — rural health units and Konsulta providers overlap in reality and are counted separately here. Lanao del Sur holds 24.8 percent of all BARMM accreditations and holds the region’s only Level III accredited hospital outside Cotabato City. The Integrated Provincial Health Office independently reports 36 of its 39 health units (92.3 percent) as YAKAP-accredited, 30 (76 percent) with maternity care and 28 (71 percent) with TB-DOTS (International Organization for Migration, 2026a). | N45: 704
A46: LDS | B46: EXHIBIT 8 | C46: PhilHealth in Lanao del Sur: 291,084 registered, 6,250 seen | D46: 5 | E46: Stage Three — Payment | F46: 5.3 | G46: Registration without utilization | H46: 29 | I46: 0 | J46: 5 | K46: D06 | L46: Payment, PhilHealth and financing | N46: 739
A47: LDS | B47: TABLE 6 | C47: The eleven licensed hospitals of Lanao del Sur | D47: 6 | E47: Stage Four — Referral | F47: 6.1 | G47: The hospital stock and its geography | H47: 31 | I47: 12 | J47: 6 | K47: D07 | L47: Referral and inpatient capacity | N47: 775
A48: LDS | B48: TABLE 6A | C48: Licensed bed capacity by facility class and ownership | D48: 6 | E48: Stage Four — Referral | F48: 6.1 | G48: The hospital stock and its geography | H48: 31 | I48: 7 | J48: 6 | K48: D07 | L48: Referral and inpatient capacity | M48: Note. Compiled from the project-held DOH/HFSRB facility register against the 2024 census population of 1,368,137 (Philippine Statistics Authority, 2025c). Three of the 43 birthing-home records carry no bed value and 40 of the 44 rural health units carry none, so the total should be read as a floor rather than as a complete inventory. The reports use the acute inpatient basis of 0.75 per 1,000 where a single figure is required, and state the basis wherever a bed ratio appears. | N48: 795
A49: LDS | B49: TABLE 7 | C49: The FHSIS apparatus at municipal level | D49: 7 | E49: Stage Five — Follow-Up and the Record | F49: 7.2 | G49: The FHSIS apparatus | H49: 34 | I49: 8 | J49: 3 | K49: D08 | L49: Routine reporting, FHSIS and civil registration | M49: Note. Adapted from Ministry of Health–Bangsamoro Autonomous Region in Muslim Mindanao (n.d.) — a unit-and-resourcing survey returned by 24 Lanao del Sur local government units and scored for 27, and a reporting-performance assessment covering 33 rural health units — and from the Integrated Provincial Health Office health-systems map in International Organization for Migration (2026a). Two fields in the assessment, the data-quality score and the staffing score, are identical for all 27 Lanao del Sur units and appear to be constants rather than measurements; they are not used in this report. | N49: 850
A50: LDS | B50: (unlabelled) | C50: Beneath the service statistics lies a measurement constraint that bears on every rate in this document. | D50: 7 | E50: Stage Five — Follow-Up and the Record | F50: 7.3 | G50: Civil registration and the invisible denominator | H50: 35 | I50: 0 | J50: 5 | K50: D08 | L50: Routine reporting, FHSIS and civil registration | N50: 870
A51: LDS | B51: EXHIBIT 10 | C51: Five divergences between the administrative record and independent measurement | D51: 8 | E51: The Reconciliation | H51: 36 | I51: 5 | J51: 4 | K51: D09 | L51: Reconciliation and divergences | M51: Note. Sources as cited in Sections 3 to 7. Sample sizes are stated wherever a survey estimate rests on fewer than 250 unweighted cases (Philippine Statistics Authority & ICF, 2023). | N51: 900
A52: LDS | B52: TABLE 8 | C52: Legal obligations engaged by the findings | D52: 9 | E52: Governance and Legal Framework | H52: 38 | I52: 9 | J52: 4 | K52: D10 | L52: Governance and legal framework | M52: Note. Statutory titles, numbers and dates were verified against the Official Gazette, the Supreme Court E-Library and the published text of the Bangsamoro Parliament. Two verification caveats are carried: the enactment date of the Bangsamoro Local Governance Code (2023) could not be confirmed from a primary source — parliamentary approval on 28 September 2023 and publication in January 2024 are documented — and the effectivity date of the Local Government Code (1991) was not confirmed from the text retrieved. The substantive provisions of the Bangsamoro Local Governance Code summarized here are drawn from the project’s EBDM module materials and should be read against the published instrument before any ordinance is drafted on their basis. | N52: 925
A53: LDS | B53: EXHIBIT 11 | C53: Sequencing: what must be true before the next thing can work | D53: 10 | E53: Priorities: sequencing by stage, not by sector | H53: 40 | I53: 7 | J53: 4 | K53: D11 | L53: Priorities and sequencing | M53: Note. Actions 1, 2 and 7 require no capital and can begin immediately; actions 1 and 2 are the substance of the ninety-day program in Section 11. Actions 3 and 4 are low-cost and high-certainty. Actions 5 and 6 are the capital program and are sized in Section 12. | N53: 952
A54: LDS | B54: TABLE 9 | C54: The validation program | D54: 11 | E54: Provincial Validation Program | H54: 42 | I54: 4 | J54: 5 | K54: D11 | L54: Priorities and sequencing | M54: Note. Capital funding is not required for any of the outlined initiatives. Tasks 1, 2, and 7 comprise analytical steps; Tasks 3, 4, and 5 deal with administrative implementation; and Task 6 mirrors previous programmatic interventions deployed during the workshop series. Initiation of the broader strategic development plan is contingent upon the successful validation of Tasks 1 and 2. | N54: 977
A55: LDS | B55: EXHIBIT 12 | C55: Volumetrics for the two-year program | D55: 12 | E55: Two-Year Investment Logic, 2026–2028 | F55: 12.1 | G55: Volumetrics | H55: 43 | I55: 0 | J55: 5 | K55: D12 | L55: Investment logic and volumetrics | N55: 1005
A56: LDS | B56: (unlabelled) | C56: | 305geographically isolatedbarangays | | D56: 12 | E56: Two-Year Investment Logic, 2026–2028 | F56: 12.1 | G56: Volumetrics | H56: 43 | I56: 0 | J56: 5 | K56: D12 | L56: Investment logic and volumetrics | N56: 1017
A57: LDS | B57: TABLE 10 | C57: Two-year program: volumetrics, sequencing and financing route | D57: 12 | E57: Two-Year Investment Logic, 2026–2028 | F57: 12.2 | G57: The program | H57: 43 | I57: 9 | J57: 6 | K57: D12 | L57: Investment logic and volumetrics | M57: Note. Financing routes are named from the sources the local government units themselves cite in their two-year plans (International Organization for Migration, 2026a) and from the standing fiscal instruments established by Mandanas v. Ochoa (2018) and the Local Government Code (1991). Each plan action should be routed through the Local Investment Plan for Health, the Annual Investment Program and Sanggunian appropriation, with a specific appropriation line and amount attached. Eighty percent of actions carrying both is the benchmark proposed for the next review. | N57: 1033
A58: LDS | B58: ANNEX A | C58: Population values reconcile to the PSA 2024 Census provincial total of 1,368,137. Barangay counts in this annex sum to the 1,159 routeable 2020 model geography and must not be presented as the current administrative total; PSA currently lists 1,164 barangays. Shaded rows identify municipalities with no station matched in the project-held register. Empty cells indicate no reported figure, not zero. | D58: A | E58: Annex A — Municipal master table, 40 local government units | H58: 49 | I58: 41 | J58: 21 | K58: D14 | L58: Annexes, master tables and gap registers | M58: Note. Column sources. Population and district: Philippine Statistics Authority 2024 Census and PSGC. The annex barangay column preserves the 1,159-node 2020 model geography; current administrative coverage uses 1,164 barangays and requires a five-barangay crosswalk. GIDA is the 2022 source classification. Facilities and beds are derived from the project-held DOH/HFSRB register, which appears incomplete and may understate stations. Scorecard indicators are unweighted municipal values unless stated otherwise; fully immunized child and facility delivery are from 2021 and 2018, respectively, and all others from 2022. Tuberculosis detection is a notification-to-national-incidence proxy, not a subnational incidence estimate. Six municipal immunization values above 100 per cent identify denominator defects. | N58: 1145
A59: LDS | B59: ANNEX B | C59: Modeled physical access on the central 30-minute multimodal scenario, the readiness evidence available for each municipality, and the resulting planning tier. Tiers sequence validation and planning; they do not authorize capital construction. Population is the GeoRisk/PSA 2020 modeled base, which is the base on which the model runs; it is not the 2024 census figure used elsewhere in this report. | D59: B | E59: Annex — Municipality access and evidence tiers | H59: 51 | I59: 41 | J59: 6 | K59: D14 | L59: Annexes, master tables and gap registers | M59: Note. Adapted from International Organization for Migration (2026b). Tier 1 — sixteen municipalities at or above ten percent modeled unserved population: field-validate routes and settlements, then interim outreach and transport, then site-specific capital only where a residual gap survives. Tier 2 — eight municipalities where readiness rather than distance is the constraint: repair, staffing, equipment, cold chain, accreditation, medicines, connectivity and referral before new construction. Tier 3 — sixteen municipalities where the first task is to complete readiness, route and identity evidence and correct registry and source gaps. No municipality currently qualifies for a monitor-and-sustain tier. Four municipalities have no local readiness source of any kind — Butig, Calanogas, Lumbatan and Lumbayanague. Bumbaran is the pre-2019 name of Amai Manabilang and is a single municipality. | N59: 1196
A60: LDS | B60: ANNEX C | C60: The following items could not be obtained. Each is recorded with the office from which it should be requested. In a province where no municipality-level health outcome data is available in any public source, the gap register is more appropriately read as a work program for data development. | D60: C | E60: Annex C — Evidence gap register | H60: 53 | I60: 16 | J60: 4 | K60: D14 | L60: Annexes, master tables and gap registers | N60: 1250
A61: MDN | B61: (unlabelled) | C61: # 1 Executive Summary | D61: 1 | E61: Executive Summary | H61: 4 | I61: 0 | J61: 7 | K61: D01 | L61: Executive summary and headline panels | N61: 162
A62: MDN | B62: (unlabelled) | C62: | 741,428residents in the twelvemunicipalities, 2024 Census | | 221barangays | | 178registered barangayhealth stations | | 12rural health units | | D62: 1 | E62: Executive Summary | H62: 4 | I62: 0 | J62: 7 | K62: D04 | L62: First contact, facilities and catchment | N62: 168
A63: MDN | B63: EXHIBIT 1 | C63: The five stages, and what fails at each one | D63: 1 | E63: Executive Summary | G63: Seven findings | H63: 4 | I63: 5 | J63: 4 | K63: D01 | L63: Executive summary and headline panels | M63: Note. Each claim is evidenced in the section indicated. Adapted from Philippine Statistics Authority (2025c); Philippine Statistics Authority and ICF (2023); Department of Health (n.d.-a, 2026); Philippine Health Insurance Corporation (2024); World Bank (2020); Ministry of Health–BARMM (2025); and International Organization for Migration (2026). | N63: 204
A64: MDN | B64: TABLE 1 | C64: Completion of required worksheet outputs across the cohort | D64: 2 | E64: Program, Scope, Evidence and Method | H64: 8 | I64: 4 | J64: 4 | K64: D02 | L64: Evidence base, scope and method | N64: 245
A65: MDN | B65: TABLE 2 | C65: The five evidence layers and what each can carry | D65: 2 | E65: Program, Scope, Evidence and Method | F65: 2.1 | G65: The five evidence layers | H65: 8 | I65: 5 | J65: 5 | K65: D02 | L65: Evidence base, scope and method | N65: 261
A66: MDN | B66: (unlabelled) | C66: ## 2.3 What the workshop record establishes, and what it cannot carry | D66: 2 | E66: Program, Scope, Evidence and Method | F66: 2.3 | G66: What the workshop record establishes, and what it cannot carry | H66: 8 | I66: 0 | J66: 2 | K66: D02 | L66: Evidence base, scope and method | N66: 285
A67: MDN | B67: TABLE 3 | C67: What the evidence establishes, and does not establish, about disease burden | D67: 3 | E67: Stage One — The Illness | F67: 3.1 | G67: What can and cannot be said about cause of death in this province | H67: 11 | I67: 5 | J67: 3 | K67: D03 | L67: Disease burden and service coverage | M67: Note. Compiled for this report. This table is the substitute for the leading-cause table that a provincial diagnostic would ordinarily open with, and its purpose is to prevent that table from being invented. The corresponding evidence requests are itemised in Annex C, items 1 to 4. | N67: 313
A68: MDN | B68: EXHIBIT 2 | C68: Adults risk-assessed under PhilPEN, by municipality | D68: 3 | E68: Stage One — The Illness | F68: 3.2 | G68: The non-communicable disease profile, and the readiness that is not used | H68: 11 | I68: 12 | J68: 12 | K68: D03 | L68: Disease burden and service coverage | M68: Note. Derived from Department of Health (n.d.-a), 2022 indicator year, twelve municipalities of Maguindanao del Norte. The provincial figure quoted in text is the unweighted mean of the twelve municipal values (2.47 per cent); the scorecard supplies no population weights. Municipalities shown in accent record coverage below one per cent. The City of Cotabato, not shown, records 6.45 per cent. The Lanao del Sur comparator is the corresponding provincial figure from the same dataset. The complement is the operative figure: on these returns, roughly ninety-seven and a half per cent of adults in this province have never been screened for the conditions that are its leading reported cause of death. | N68: 336
A69: MDN | B69: EXHIBIT 3 | C69: Maguindanao had the best facility readiness in BARMM and the worst vaccination history | D69: 3 | E69: Stage One — The Illness | F69: 3.3 | G69: The child-survival signature | H69: 11 | I69: 7 | J69: 12 | K69: D03 | L69: Disease burden and service coverage | N69: 366
A70: MDN | B70: EXHIBIT 4 | C70: Tuberculosis notification against expected incidence, by municipality | D70: 3 | E70: Stage One — The Illness | F70: 3.4 | G70: The municipal evidence environment | H70: 11 | I70: 12 | J70: 12 | K70: D03 | L70: Disease burden and service coverage | M70: Note. Derived. Notified cases apply the municipal tuberculosis case notification rate (Department of Health, n.d.-a, 2022 indicator year) to the 2024 census population (Philippine Statistics Authority, 2025c); expected incident cases apply the WHO-estimated Philippine incidence of 625 per 100,000 (World Health Organization, 2025) to the same population. Provincial aggregate: approximately 1,285 notified against approximately 4,634 expected, a detection ratio of 27.7 per cent. Three cautions attach. A national incidence rate applied to a provincial population establishes order of magnitude only, and the WHO estimate carries a 95 per cent uncertainty interval of 344 to 1,020 per 100,000. A 2022 notification rate is applied to a 2024 population. And the municipal spread of 70.3 to 303.6 per 100,000 — a fourfold range, against the eighteenfold range recorded in Lanao del Sur — is narrow enough that it measures case-finding effort rather than disease distribution. The City of Cotabato, not shown, notifies at 714.6 per 100,000, more than twice the highest municipal rate; that is an attribution artefact of city facilities notifying cases resident elsewhere and is a reason not to fold the city into provincial tuberculosis planning. | N70: 391
A71: MDN | B71: (unlabelled) | C71: Section 17(b)(1)(ii) of the Local Government Code of 1991 assigns the maintenance of the barangay health centre to the barangay, and Section 17(b)(2)(iii) assigns primary health care, maternal and child care and communicable and non-communicable disease control to the municipality. The national planning benchmark applied to that assignment is one barangay health station per barangay and one rural health unit per 20,000 population (World Bank, 2020, p. 130). | D71: 4 | E71: Stage Two — First Contact | F71: 4.1 | G71: The denominator: 221 barangays, 178 registered stations | H71: 16 | I71: 0 | J71: 7 | K71: D04 | L71: First contact, facilities and catchment | N71: 433
A72: MDN | B72: EXHIBIT 5 | C72: Forty-six of 221 barangays have no registered health station | D72: 4 | E72: Stage Two — First Contact | F72: 4.1 | G72: The denominator: 221 barangays, 178 registered stations | H72: 16 | I72: 11 | J72: 12 | K72: D04 | L72: First contact, facilities and catchment | M72: Note. Derived. Barangay counts from the Philippine Standard Geographic Code (Philippine Statistics Authority, 2025b); station counts and their barangay assignment from the project-held DOH/NHFR facility extract (Department of Health, 2026). Three same-barangay station pairs within the twelve municipalities were resolved to single barangays before counting — in Parang, Barira and Kabuntalan — including Parang’s “CABUAN” and “KABUAN” records, which are almost certainly one facility recorded twice. Three further pairs sit in the City of Cotabato and are outside the provincial count. Registry incompleteness is disclosed and is material in the other direction as well: the workshop record maps 207 service locations across the same twelve municipalities against 224 registry records, so the true station count is a floor rather than a complete inventory. The City of Cotabato, not shown, records thirty-nine stations across thirty-six of its thirty-seven barangays. | N72: 447
A73: MDN | B73: TABLE 4 | C73: First-contact infrastructure by municipality, ranked by population | D73: 4 | E73: Stage Two — First Contact | F73: 4.1 | G73: The denominator: 221 barangays, 178 registered stations | H73: 16 | I73: 14 | J73: 10 | K73: D04 | L73: First contact, facilities and catchment | M73: Note. Population and barangay counts from Philippine Statistics Authority (2025b, 2025c); the twelve municipal values reconcile exactly to 741,428 and to 221 barangays. Facility counts from the project-held DOH/NHFR extract (Department of Health, 2026). No BHS is the barangay count less the count of distinct barangays carrying at least one registered station. Pop/RHU is derived; because every municipality carries exactly one registered unit it equals the municipal population. Labs counts registered clinical, drug-testing and COVID-19 testing laboratories. Shaded rows are the seven municipalities with three or more barangays carrying no registered station; together they account for 40 of the 46. Beds and Labs are printed as zeros because they are measured zeros, not unreported fields. | N73: 466
A74: MDN | B74: EXHIBIT 6 | C74: Population per rural health unit against the 1:20,000 standard | D74: 4 | E74: Stage Two — First Contact | F74: 4.2 | G74: The rural health unit against the 1:20,000 standard | H74: 16 | I74: 12 | J74: 12 | K74: D04 | L74: First contact, facilities and catchment | M74: Note. Derived. The 2024 census municipal population (Philippine Statistics Authority, 2025c) divided by the count of registered rural health units (Department of Health, 2026). Because every municipality carries exactly one registered unit, the ratio equals the municipal population. Eleven of twelve municipalities exceed the standard, covering 97.3 per cent of the province; Talitay alone falls within it. Seven municipalities exceed the standard by a factor of two or more, and four by a factor of three or more. Two distinct constraints are visible and require two distinct instruments: in Datu Odin Sinsuat, Sultan Kudarat, Parang and Upi the binding constraint is capacity and the instrument is unit augmentation; in Kabuntalan, Northern Kabuntalan and Talitay the binding constraint is distribution and the instrument is station construction. The City of Cotabato, not shown, carries 383,383 residents against one registered unit, which is on its face implausible and is treated in Section 4A. | N74: 498
A75: MDN | B75: EXHIBIT 7 | C75: Where births actually happen: the administrative record against the survey | D75: 4 | E75: Stage Two — First Contact | F75: 4.5 | G75: Childbirth: the twenty-point gap and the eighteen-point municipality | H75: 16 | I75: 4 | J75: 12 | K75: D04 | L75: First contact, facilities and catchment | M75: Note. Administrative figures are the twelve-municipality unweighted mean and the municipal extremes from Department of Health (n.d.-a), 2018 indicator year — the last year in which the LGU Health Scorecard carried this indicator. The survey figure is the BARMM regional estimate from Philippine Statistics Authority and ICF (2023), two years preceding the survey, 345 unweighted births. The Matanog figure is that municipality’s own 2025 FHSIS return as transcribed in its Worksheet 2 submission (International Organization for Migration, 2026). The three do not share a denominator and are not alternative estimates of the same quantity; they are printed together because the decision they inform — whether to design for a facility-delivery majority — turns on which is closer to current reality, and the two most recent measurements both say it is not. | N75: 550
A76: MDN | B76: TABLE 5 | C76: The province with and without the City of Cotabato | D76: 4A | E76: The Cotabato City Correction | H76: 21 | I76: 9 | J76: 4 | K76: D02 | L76: Evidence base, scope and method | M76: Note. Facility, bed and diagnostic counts from the project-held DOH/NHFR extract (Department of Health, 2026); population and barangays from Philippine Statistics Authority (2025b, 2025c); accreditation from Philippine Health Insurance Corporation (2024), which is the one source in this evidence base that reports the city separately from the province throughout. The bed ratio row is the operative one: on the published provincial geography Maguindanao del Norte records 0.78 beds per 1,000 and appears comparable to Maguindanao del Sur; on the geography it actually governs it records 0.49, below Lanao del Sur and above only Basilan. | N76: 576
A77: MDN | B77: EXHIBIT 8 | C77: What Cotabato City is worth to the provincial averages | D77: 4A | E77: The Cotabato City Correction | H77: 21 | I77: 7 | J77: 12 | K77: D02 | L77: Evidence base, scope and method | N77: 595
A78: MDN | B78: TABLE 6 | C78: PhilHealth-accredited health care institutions, BARMM by province | D78: 5 | E78: Stage Three — Payment | F78: 5.2 | G78: The accreditation base | H78: 22 | I78: 13 | J78: 9 | K78: D06 | L78: Payment, PhilHealth and financing | M78: Note. Adapted from Philippine Health Insurance Corporation (2024), accredited health care institutions by province and type as of 31 July 2024. Counts are of accreditations, not distinct facilities — rural health units and Konsulta providers overlap in reality and are counted separately here. The “other packages and laboratories” row consolidates animal-bite treatment centres, hospital TB-DOTS, HIV hubs, outpatient malaria packages, ambulatory surgical clinics, Z-benefit packages, catastrophic isolation units and RT-PCR laboratory accreditations. Every row and column of the source table reconciles exactly to its printed totals. Cotabato City is reported by PhilHealth as a separate column and is not included in the Maguindanao del Norte figure, which is the correct treatment and the one adopted throughout this report. The thirteen accredited rural health units against twelve registered units is a discrepancy of record and is carried here because it is what the source states; it should be resolved before an accreditation rate is published. | N78: 640
A79: MDN | B79: EXHIBIT 9 | C79: PhilHealth in Maguindanao del Norte: 312,635 members, 19 Konsulta providers | D79: 5 | E79: Stage Three — Payment | F79: 5.3 | G79: The conversion rate the province cannot compute | H79: 22 | I79: 1 | J79: 7 | K79: D06 | L79: Payment, PhilHealth and financing | N79: 673
A80: MDN | B80: TABLE 7 | C80: The twelve licensed hospitals and infirmaries of Maguindanao del Norte | D80: 6 | E80: Stage Four — Referral | F80: 6.1 | G80: The hospital stock and who owns it | H80: 25 | I80: 14 | J80: 6 | K80: D07 | L80: Referral and inpatient capacity | M80: Note. From the project-held DOH/NHFR facility extract (Department of Health, 2026). Service capability is null for all three infirmary records in the source and is reported here by facility class. Two caveats attach to the licence column. First, every licence date in the extract has passed except that of the Cotabato Sanitarium; this is more plausibly interpreted as a stale registry snapshot taken before the 2026 renewal cycle than as a province of unlicensed hospitals, and it must be verified against current DOH-HFSRB records before publication in any external document. It is carried here because it is what the register states. Second, the Datu Blah T. Sinsuat District Hospital is registered in the municipality of Upi, not in the municipality for which it is named; the assignment should be confirmed before the facility is placed on any referral map. Birthing homes add a further 46 beds across the twelve municipalities and are excluded from this table. | N80: 715
A81: MDN | B81: EXHIBIT 10 | C81: Fifty-six per cent of the province’s beds sit in a national leprosarium | D81: 6 | E81: Stage Four — Referral | F81: 6.2 | G81: Eight municipalities with no inpatient bed | H81: 25 | I81: 6 | J81: 12 | K81: D07 | L81: Referral and inpatient capacity | M81: Note. Licensed hospital and infirmary bed complement from the project-held DOH/NHFR facility extract (Department of Health, 2026); birthing-home beds are excluded. The Cotabato Sanitarium and General Hospital holds 55.6 per cent of the province’s licensed beds. It is a Department of Health–retained institution established as a leprosarium; it is not a provincial or municipal asset and its admission policy is not set by the province. A further 16.7 per cent sits in two Department of National Defense camp hospitals whose access arrangements for civilians are not documented in any source available to this report. The practical consequence is that of 360 beds nominally available to residents of this province, the beds whose use the Bangsamoro Government can direct number twenty-five. Establishing written access arrangements for the remaining 335 — with the Department of Health, the Department of National Defense and the two district hospitals recorded under national-government sub-classification — costs nothing and is Task 4 of Section 11. | N81: 745
A82: MDN | B82: TABLE 8 | C82: The FHSIS apparatus at municipal level | D82: 7 | E82: Stage Five — Follow-Up and the Record | F82: 7.2 | G82: The FHSIS apparatus: the region’s strongest, and what that means | H82: 28 | I82: 9 | J82: 3 | K82: D08 | L82: Routine reporting, FHSIS and civil registration | M82: Note. Adapted from Ministry of Health–Bangsamoro Autonomous Region in Muslim Mindanao (2025), rural health unit assessment, fieldwork 26 November to 17 December 2025, 68 units across four BARMM areas. Denominators are eleven of twelve municipalities; Sultan Mastura’s submission exists in the raw export but its municipality field records “Sultan Kudarat (Nuling)” while its unit name records “Sultan Mastura,” and it was dropped as a duplicate. Two scored fields — the staffing score and the data-quality score — take an identical value for all 68 units in the region and are constants rather than measurements; they are reported here as the systemic findings they are and are not used in any comparison. Northern Kabuntalan’s blank timeliness and indicator fields are scored as “no report” in the source pivots, which converts a non-response into a zero; its resulting score of 0.30 is a reporting artefact and is not treated as a performance finding. | N82: 801
A83: MDN | B83: (unlabelled) | C83: ## 7.3 Civil registration and the invisible denominator | D83: 7 | E83: Stage Five — Follow-Up and the Record | F83: 7.3 | G83: Civil registration and the invisible denominator | H83: 28 | I83: 0 | J83: 7 | K83: D08 | L83: Routine reporting, FHSIS and civil registration | N83: 820
A84: MDN | B84: EXHIBIT 11 | C84: Five divergences between the administrative record and independent measurement | D84: 8 | E84: The Reconciliation | H84: 30 | I84: 5 | J84: 4 | K84: D09 | L84: Reconciliation and divergences | M84: Note. Sources as cited in Sections 3 to 7. Sample sizes are stated wherever a survey estimate rests on fewer than 250 unweighted cases (Philippine Statistics Authority & ICF, 2023). Figures attributed to the 2019 household survey and the 2017 readiness assessment refer to the undivided province of Maguindanao and are so labelled throughout. | N84: 848
A85: MDN | B85: TABLE 9 | C85: Legal obligations engaged by the findings | D85: 9 | E85: Governance and Legal Framework | H85: 32 | I85: 9 | J85: 4 | K85: D10 | L85: Governance and legal framework | M85: Note. One correction of record is carried here. Sections 114 to 117 of the Bangsamoro Local Governance Code are the local health boards provisions; the phrase “Special Health Fund” does not appear anywhere in Bangsamoro Autonomy Act No. 49. The Special Health Fund is created by Section 20 of Republic Act No. 11223, a national statute. Any statement attributing the fund to the Bangsamoro Code — including in earlier provincial diagnostics in this series — should be corrected. A second correction concerns the catchment standard. The one-per-20,000 ratio in the DOH Manual of Standards for Primary Care Facilities is a physician staffing ratio drawn from the National Objectives for Health 2017–2022. Neither RA 7160 nor RA 11223 contains a facility-count standard, and neither should be cited for one; the facility target used in Section 4.2 is that stated in World Bank (2020, p. 130). | N85: 877
A86: MDN | B86: EXHIBIT 12 | C86: Sequencing: what must be true before the next thing can work | D86: 10 | E86: Priorities: sequencing by stage, not by sector | H86: 34 | I86: 7 | J86: 4 | K86: D11 | L86: Priorities and sequencing | M86: Note. Actions 1, 2, 4 and 7 require no capital and can begin immediately; actions 1, 2 and 5 are the substance of the ninety-day programme in Section 11. Action 3 is low-cost and high-certainty and appears already in the improvement plans of five of the twelve municipalities. Action 6 is the capital programme and is sized in Section 12. The ordering is by dependency, not by importance: action 6 is the largest and most visible, and it is sixth because the register that would site it and the readiness evidence that would specify it do not yet exist. | N86: 908
A87: MDN | B87: TABLE 10 | C87: The ninety-day validation program | D87: 11 | E87: Ninety-Day Provincial Validation Program | H87: 35 | I87: 7 | J87: 5 | K87: D11 | L87: Priorities and sequencing | M87: Note. Capital funding is not required for any of the outlined tasks. Tasks 1, 2, 6 and 7 are analytical; Tasks 4 and 5 are administrative; Task 3 is a field exercise mirroring the enumeration already conducted during the workshop series. Initiation of the capital component of the two-year programme in Section 12 is contingent on the completion of Tasks 1 and 3, which together establish which of the 46 unserved barangays require construction and which require rehabilitation of an existing self-help structure. | N87: 935
A88: MDN | B88: EXHIBIT 13 | C88: Volumetrics for the two-year program | D88: 12 | E88: Two-Year Investment Logic, 2026–2028 | F88: 12.1 | G88: Volumetrics | H88: 36 | I88: 2 | J88: 5 | K88: D12 | L88: Investment logic and volumetrics | N88: 964
A89: MDN | B89: TABLE 11 | C89: Two-year program: volumetrics, sequencing and financing route | D89: 12 | E89: Two-Year Investment Logic, 2026–2028 | F89: 12.2 | G89: The program | H89: 36 | I89: 9 | J89: 6 | K89: D12 | L89: Investment logic and volumetrics | M89: Note. Financing routes are named from the sources the municipalities themselves cite in their two-year plans (International Organization for Migration, 2026) and from the standing fiscal instruments established by Mandanas v. Ochoa (2018), the Local Government Code (1991) and the Bangsamoro Organic Law’s Special Development Fund. Each plan action should be routed through the Local Investment Plan for Health, the Annual Investment Program and Sanggunian appropriation, with a specific appropriation line and amount attached. Eighty per cent of actions carrying both a named appropriation line and an amount is the benchmark proposed for the next review; the current provincial position is that no plan action in the entire evidence base carries a peso figure. | N89: 988
A90: MDN | B90: TABLE 12 | C90: Provincial monitoring indicators | D90: 13 | E90: Monitoring Framework | H90: 38 | I90: 20 | J90: 5 | K90: D13 | L90: Monitoring indicators | M90: Note. Baselines are as established in Sections 3 to 7 of this report and inherit the qualifications stated there. Six of the fifteen indicators have no present measured value. That is the intended design: an indicator whose first result is a baseline is more useful than an indicator whose baseline is an artefact. Targets are proposed for discussion by the Provincial Health Board and are not commitments of the Ministry, the programme or its partners. No target is proposed for any indicator whose measurement depends on a data request that has not yet been granted, other than that the request be granted and the measurement begin. | N90: 1019
A91: MDN | B91: ANNEX A | C91: All figures from official sources. Population and barangay counts reconcile exactly to the PSA 2024 Census provincial total of 1,124,811 less the City of Cotabato’s 383,383, and to 221 barangays. The City of Cotabato is printed below the provincial row and is excluded from every provincial total in this report. Shaded rows are the eight municipalities with no inpatient bed of any class. An em-dash in the Beds and Diag columns is a measured zero; an em-dash in the glyph columns indicates no reported figure. | D91: A | E91: Annex A — Municipal master table, twelve local government units | H91: 41 | I91: 14 | J91: 21 | K91: D14 | L91: Annexes, master tables and gap registers | M91: Note. Column sources. Pop 2024, Brgys — Philippine Statistics Authority (2025b, 2025c); the twelve municipal values reconcile exactly to 741,428 and to 221 barangays. RHU, BHS, No BHS, Hosp, Beds, Diag — project-held DOH/NHFR facility extract (Department of Health, 2026); the register is incomplete, licensing status is null for three-quarters of records, and eleven rural health unit birthing annexes are typed as independent facilities; these counts are a floor. No BHS is the barangay count less the count of distinct barangays carrying at least one registered station. Pop/RHU is derived; because every municipality carries exactly one registered unit, it equals the municipal population. FIC, FBD, TB CNR, PEN, Stunt, Water, LHB, ESU, DRR — Department of Health (n.d.-a); indicator years differ by column: facility-based delivery is the 2018 indicator year, the last in which the scorecard carried it, and all others are the 2022 indicator year. TB det % is derived as the notification rate divided by the WHO-estimated Philippine incidence of 625 per 100,000 (World Health Organization, 2025). LHB, ESU, DRR are binary scorecard flags rendered ● = yes, ○ = no, — = not reported; the PROVINCE row renders them as fractions. EBDM records participation in the 2026 workshop cycle; all twelve municipalities participated, the only complete provincial cohort in the programme. There is no GIDA column. No geographically isolated and disadvantaged area determination for this province could be obtained from the Department of Health or MOH-BARMM; the gap is recorded as item 5 of Annex C and is not estimated. No municipality in this province reports immunization coverage above 100 per cent, which distinguishes it from its neighbours and indicates that its denominators are internally plausible even where its levels are contested. | N91: 1087
A92: MDN | B92: ANNEX B | C92: The readiness evidence available for each municipality and the resulting planning tier. Tiers sequence validation and planning; they do not authorise capital construction. Population is the PSA 2024 Census. The tier assignment rests on three official-source variables — unserved barangays, catchment excess above the 20,000 planning standard, and the absence of inpatient and diagnostic capacity — and on none of the derived scores in the workshop record. | D92: B | E92: Annex B — Municipality evidence tiers and planning sequence | H92: 42 | I92: 13 | J92: 8 | K92: D14 | L92: Annexes, master tables and gap registers | M92: Note. Derived for this report from Philippine Statistics Authority (2025b, 2025c), the project-held DOH/NHFR facility extract (Department of Health, 2026), Ministry of Health–BARMM (2025) and International Organization for Migration (2026). Tier 1 — access and capacity: nine municipalities carrying three or more unserved barangays or a population above 100,000. Field-validate the unserved barangays, then station construction and rural health unit augmentation. Tier 2 — readiness: three municipalities — Barira, Matanog and Sultan Mastura — where the station network is substantially complete but the municipality holds no bed and no laboratory; the constraint is referral and readiness rather than first contact, and the instruments are the service-delivery network document and the cold-chain condition survey. No municipality in this province qualifies for a verification tier on the strength of a completed evidence base, and none qualifies for a monitor-and-sustain tier. Three municipalities carry an incomplete evidence position: Northern Kabuntalan filed only a facility inventory and is absent from the consolidated dashboard; Sultan Mastura is missing from every FHSIS pivot because its record is mis-keyed; and Parang filed a facility inventory resolving to a single municipality-wide record. Their apparent positions in any derived scoring are artefacts of reporting and are not treated as performance findings. | N92: 1115
A93: MDN | B93: ANNEX C | C93: The following items could not be obtained. Each is recorded with the office from which it should be requested. In a province created in 2022 and not yet carried as a separate reporting unit in most national datasets, the gap register is more appropriately read as a work programme for data development than as a list of omissions. | D93: C | E93: Annex C — Evidence gap register | H93: 43 | I93: 16 | J93: 4 | K93: D14 | L93: Annexes, master tables and gap registers | N93: 1142
A94: MDS | B94: (unlabelled) | C94: # 1 Executive Summary | D94: 1 | E94: Executive Summary | H94: 4 | I94: 0 | J94: 4 | K94: D01 | L94: Executive summary and headline panels | N94: 184
A95: MDS | B95: (unlabelled) | C95: | 813,243residents, 2024 Census | 287barangays | 222registered health facilities | 24rural health units — one per municipality | | D95: 1 | E95: Executive Summary | H95: 4 | I95: 0 | J95: 4 | K95: D04 | L95: First contact, facilities and catchment | N95: 190
A96: MDS | B96: EXHIBIT 1 | C96: The five stages, and what needs to be checked at each one | D96: 1 | E96: Executive Summary | G96: Decisions required of provincial leadership | H96: 4 | I96: 5 | J96: 4 | K96: D01 | L96: Executive summary and headline panels | M96: Note. Each claim is evidenced in the section indicated. Compiled from Philippine Statistics Authority (2025a, 2025b); Philippine Statistics Authority and ICF (2023); Department of Health (n.d.); Philippine Health Insurance Corporation (2024); World Bank (2020); Ministry of Health–BARMM (n.d.); and International Organization for Migration (2026). | N96: 242
A97: MDS | B97: TABLE 1 | C97: Participation in the Maguindanao del Sur cycle | D97: 2 | E97: Program, Scope, Evidence and Method | F97: 2.1 | G97: The program | H97: 8 | I97: 3 | J97: 5 | K97: D02 | L97: Evidence base, scope and method | M97: Note. Filing status is taken from the 22 files in the programme's Maguindanao del Sur worksheet folder (21 LGU workbooks and one template). Population and barangay counts are PSA 2024 Census and PSGC. Participation in this province is the second-highest in the programme after Maguindanao del Norte (12 of 12) and far above Lanao del Sur (16 of 40). The three non-filers are not marginal units: Gen. S.K. Pendatun holds the province's largest registered facility network (26) and complete barangay coverage; South Upi holds the province's second-largest population and a 25-bed municipal hospital. | N97: 265
A98: MDS | B98: TABLE 2 | C98: The five evidence layers and what each can carry | D98: 2 | E98: Program, Scope, Evidence and Method | F98: 2.3 | G98: The five evidence layers | H98: 9 | I98: 5 | J98: 5 | K98: D02 | L98: Evidence base, scope and method | N98: 292
A99: MDS | B99: TABLE 3 | C99: Two artefacts, one province | D99: 2 | E99: Program, Scope, Evidence and Method | F99: 2.5 | G99: The provincial evidence product, and why this report does not adopt it | H99: 10 | I99: 6 | J99: 3 | K99: D09 | L99: Reconciliation and divergences | N99: 321
A100: MDS | B100: (unlabelled) | C100: Twenty-one municipalities filed. Read as testimony rather than as arithmetic, that record is the only available source located for conditions at the point of service in this province, and several of its statements are specific, checkable and consistent with the official evidence. | D100: 2 | E100: Program, Scope, Evidence and Method | F100: 2.6 | G100: What the workshop record does establish | H100: 11 | I100: 0 | J100: 2 | K100: D02 | L100: Evidence base, scope and method | N100: 348
...

Sheet 04_Report_Particulars
A1: Report | B1: Field | C1: Value as declared in the report
A2: BARMM | B2: Prepared by | C2: Lawrence John Paulo L. Trinidad · Consultant, International Organization for Migration (IOM)
A3: BARMM | B3: Prepared under | C3: Building Resilience through Inclusive Governance and Healthcare Transformation in BARMM (BRIGHT-BARMM), a five-year initiative, 2025–2030
A4: BARMM | B4: Program partners | C4: KOICA and IOM, in partnership with the Ministry of Health, BARMM
A5: BARMM | B5: Coverage | C5: 84 local government units, 1,735 current barangays and 3,137,511 residents in four jurisdictions. This is 69.0 per cent of the current PSA BARMM planning population. Basilan, Tawi-Tawi and Cotabato City are outside the workshop cycle; Sulu is outside the cycle and current BARMM.
A6: BARMM | B6: Evidence base | C6: PSA 2024 Census and current PSGC; 2022 NDHS historical baseline; 2025 NDHS current regional key indicators; municipal scorecards; facility register; dated PhilHealth/Konsulta returns requiring current YAKAP verification; MOH-BARMM FHSIS assessment; WHO, World Bank and workshop records.
A7: BARMM | B7: Status | C7: Provisional. This consolidation carries forward the provisional status of all four volumes. No figure in it is validated beyond the validation each volume states its own figures require, and no figure in it should be used for allocation or procurement before the ninety-day programmes at Annex B are complete.
A8: LDS | B8: Prepared by | C8: Lawrence John Paulo L. Trinidad · Consultant, International Organization for Migration (IOM)
A9: LDS | B9: Prepared under | C9: Building Resilience through Inclusive Governance and Healthcare Transformation in BARMM (BRIGHT-BARMM)
A10: LDS | B10: Program partners | C10: Korea International Cooperation Agency (KOICA) and the International Organization for Migration (IOM), in partnership with the Ministry of Health, Bangsamoro Autonomous Region in Muslim Mindanao (MOH-BARMM)
A11: LDS | B11: Coverage | C11: Seventeen (17) local government units of Lanao del Sur participating in the Evidence-Based Decision-Making (EBDM) workshop cycle
A12: LDS | B12: Evidence base | C12: Municipal and provincial EBDM worksheet submissions (BARMM 20260629 package), audited into 442 raw rows, 407 cleaned service-location records and 174 records with named or typed facility evidence. Facility identity, classification, accreditation and cold-chain assets remain subject to reconciliation with MOH-BARMM/DOH, PhilHealth and local records.
... A31: SGA | B31: Status | C31: Provisional. The report establishes a cleaned service-location baseline reconciled to the 2024 Census, not a validated register of distinct licensed facilities. Registry reconciliation, licensure verification and field validation remain required before allocation or procurement.

Sheet 05_Assumptions
A1: ASSUMPTIONS AND PLANNING PARAMETERS — EDIT THE YELLOW CELLS AND THE WHOLE WORKBOOK RECALCULATES
A3: Parameter | B3: Value | C3: Unit | D3: Basis | E3: What it drives | F3: Convention and caveat
A4: Catchment standard, population per rural health unit | B4: 20000 | C4: residents per unit | D4: The 1:20,000 planning target applied across all five volumes. | E4: Implied rural health units and the shortfall on 10_Municipal_Master, 11_Jurisdiction_Rollup and 16_RHU_Standard_and_Coverage. | F4: The regional volume is explicit that 1:20,000 is a planning target for catchment, not a licensing standard for facilities. It does not by itself justify construction.
A5: Rounding convention for implied units | B5: ROUND (nearest) | C5: convention | D5: Inferred from the source volumes by reconciliation, not stated in them. | E5: The implied-units column on the same three sheets. | F5: Reconciled against Regional Table 4: nearest-integer rounding reproduces 68 / 37 / 41 / 11 exactly, summing to 157. Rounding up would give 69 / 38 / 41 / 11 and a regional 159. Both are computed side by side; the nearest-integer column is the one that reconciles to the reports.
A6: Bed-rate denominator | B6: 1000 | C6: residents | D6: Standard beds-per-1,000 expression used by the volumes. | E6: Beds per 1,000 on 10_Municipal_Master and 14_Inpatient_Capacity.
A7: Population base year | B7: 2024 | C7: year | D7: Philippine Statistics Authority 2024 Census of Population, reference date 1 July 2024. | E7: Every per-capita measure in the workbook. | F7: Facility and service data are of mixed vintage; per-capita rates therefore mix a 2024 denominator with numerators of 2018 to 2026 vintage.

Sheet 10_Municipal_Master
A1: Report | B1: Province / area | C1: Local government unit | D1: Row type | E1: Source locator | F1: Population 2024 | G1: Barangays (as annexed) | H1: Barangays with a first-contact facility (as annexed) | I1: Barangays without a first-contact facility (as annexed) | J1: Rural health units (as annexed) | K1: Barangay health stations | L1: Hospitals | M1: Licensed beds | N1: FIC % | O1: FBD % | P1: TB CNR | Q1: TB detection % | R1: PhilPEN % | S1: Stunting % | T1: Population per RHU as printed | U1: LIVE Population per RHU | V1: LIVE Variance vs printed | W1: LIVE RHUs implied at the catchment standard (nearest) | X1: LIVE RHU shortfall (nearest) | Y1: LIVE Above the catchment standard | Z1: LIVE Barangays with a facility | AA1: LIVE Barangay coverage share | AB1: LIVE Beds per 1,000 residents | AC1: Basis and caveat | AD1: LIVE RHUs implied (rounded up) | AE1: LIVE RHU shortfall (rounded up)
A2: LDS | B2: Lanao del Sur | C2: Marawi City | D2: LGU | E2: LDS · ANNEX A · §A · p. 49 | F2: 259993 | G2: 101 | I2: 70 | J2: 5 | K2: 26 | L2: 4 | N2: 84.5 | O2: 83.8 | P2: 240.2 | Q2: 38 | R2: 10.1 | S2: 5.9 | T2: 51999 | U2: =IF(AND(ISNUMBER(J2),J2>0,ISNUMBER(F2)),F2/J2,"no RHU recorded") -> 51998.6 | V2: =IF(AND(ISNUMBER(T2),ISNUMBER(U2)),U2-T2,"") -> -0.4 | W2: =IF(ISNUMBER(F2),ROUND(F2/'05_Assumptions'!$B$4,0),"") -> 13 | X2: =IF(AND(ISNUMBER(W2),ISNUMBER(J2)),MAX(0,W2-J2),"") -> 8 | Y2: =IF(NOT(ISNUMBER(J2)),"",IF(J2=0,"no RHU",IF(F2/J2>'05_Assumptions'!$B$4,"Yes","No"))) -> Yes | Z2: =IF(ISNUMBER(H2),H2,IF(AND(ISNUMBER(G2),ISNUMBER(I2)),G2-I2,"")) -> 31 | AA2: =IF(AND(ISNUMBER(G2),G2>0,ISNUMBER(Z2)),Z2/G2,"") -> 0.30693069 | AB2: =IF(AND(ISNUMBER(F2),F2>0,ISNUMBER(M2)),M2/F2*'05_Assumptions'!$B$6,"") | AC2: Barangay column preserves the 1,159-node 2020 model geography; current administrative coverage is 1,164 barangays and a five-barangay crosswalk is outstanding. 'Without a facility' = barangays with no matched registered health station. No bed column is carried in this annex. | AD2: =IF(ISNUMBER(F2),ROUNDUP(F2/'05_Assumptions'!$B$4,0),"") -> 13 | AE2: =IF(AND(ISNUMBER(AD2),ISNUMBER(J2)),MAX(0,AD2-J2),"") -> 8
A3: LDS | B3: Lanao del Sur | C3: Malabang | D3: LGU | E3: LDS · ANNEX A · §A · p. 49 | F3: 58377 | G3: 37 | I3: 36 | J3: 1 | K3: 1 | L3: 1 | N3: 111 | O3: 98.5 | P3: 319.6 | Q3: 50.6 | R3: 7 | S3: 1.5 | T3: 58377 | U3: =IF(AND(ISNUMBER(J3),J3>0,ISNUMBER(F3)),F3/J3,"no RHU recorded") -> 58377 | V3: =IF(AND(ISNUMBER(T3),ISNUMBER(U3)),U3-T3,"") -> 0 | W3: =IF(ISNUMBER(F3),ROUND(F3/'05_Assumptions'!$B$4,0),"") -> 3 | X3: =IF(AND(ISNUMBER(W3),ISNUMBER(J3)),MAX(0,W3-J3),"") -> 2 | Y3: =IF(NOT(ISNUMBER(J3)),"",IF(J3=0,"no RHU",IF(F3/J3>'05_Assumptions'!$B$4,"Yes","No"))) -> Yes | Z3: =IF(ISNUMBER(H3),H3,IF(AND(ISNUMBER(G3),ISNUMBER(I3)),G3-I3,"")) -> 1 | AA3: =IF(AND(ISNUMBER(G3),G3>0,ISNUMBER(Z3)),Z3/G3,"") -> 0.027027027 | AB3: =IF(AND(ISNUMBER(F3),F3>0,ISNUMBER(M3)),M3/F3*'05_Assumptions'!$B$6,"") | AC3: Barangay column preserves the 1,159-node 2020 model geography; current administrative coverage is 1,164 barangays and a five-barangay crosswalk is outstanding. 'Without a facility' = barangays with no matched registered health station. No bed column is carried in this annex. | AD3: =IF(ISNUMBER(F3),ROUNDUP(F3/'05_Assumptions'!$B$4,0),"") -> 3 | AE3: =IF(AND(ISNUMBER(AD3),ISNUMBER(J3)),MAX(0,AD3-J3),"") -> 2
A4: LDS | B4: Lanao del Sur | C4: Wao | D4: LGU | E4: LDS · ANNEX A · §A · p. 49 | F4: 51081 | G4: 26 | I4: 0 | J4: 1 | K4: 26 | L4: 1 | N4: 89.6 | O4: 93.2 | P4: 137.9 | Q4: 21.8 | R4: 0.6 | S4: 2.7 | T4: 51081 | U4: =IF(AND(ISNUMBER(J4),J4>0,ISNUMBER(F4)),F4/J4,"no RHU recorded") -> 51081 | V4: =IF(AND(ISNUMBER(T4),ISNUMBER(U4)),U4-T4,"") -> 0 | W4: =IF(ISNUMBER(F4),ROUND(F4/'05_Assumptions'!$B$4,0),"") -> 3 | X4: =IF(AND(ISNUMBER(W4),ISNUMBER(J4)),MAX(0,W4-J4),"") -> 2 | Y4: =IF(NOT(ISNUMBER(J4)),"",IF(J4=0,"no RHU",IF(F4/J4>'05_Assumptions'!$B$4,"Yes","No"))) -> Yes | Z4: =IF(ISNUMBER(H4),H4,IF(AND(ISNUMBER(G4),ISNUMBER(I4)),G4-I4,"")) -> 26 | AA4: =IF(AND(ISNUMBER(G4),G4>0,ISNUMBER(Z4)),Z4/G4,"") -> 1 | AB4: =IF(AND(ISNUMBER(F4),F4>0,ISNUMBER(M4)),M4/F4*'05_Assumptions'!$B$6,"") | AC4: Barangay column preserves the 1,159-node 2020 model geography; current administrative coverage is 1,164 barangays and a five-barangay crosswalk is outstanding. 'Without a facility' = barangays with no matched registered health station. No bed column is carried in this annex. | AD4: =IF(ISNUMBER(F4),ROUNDUP(F4/'05_Assumptions'!$B$4,0),"") -> 3 | AE4: =IF(AND(ISNUMBER(AD4),ISNUMBER(J4)),MAX(0,AD4-J4),"") -> 2
A5: LDS | B5: Lanao del Sur | C5: Lumba-Bayabao | D5: LGU | E5: LDS · ANNEX A · §A · p. 49 | F5: 50959 | G5: 38 | I5: 36 | J5: 1 | K5: 2 | L5: 0 | N5: 95.8 | O5: 99.9 | P5: 104.5 | Q5: 16.5 | R5: 10.4 | S5: 3.4 | T5: 50959 | U5: =IF(AND(ISNUMBER(J5),J5>0,ISNUMBER(F5)),F5/J5,"no RHU recorded") -> 50959 | V5: =IF(AND(ISNUMBER(T5),ISNUMBER(U5)),U5-T5,"") -> 0 | W5: =IF(ISNUMBER(F5),ROUND(F5/'05_Assumptions'!$B$4,0),"") -> 3 | X5: =IF(AND(ISNUMBER(W5),ISNUMBER(J5)),MAX(0,W5-J5),"") -> 2 | Y5: =IF(NOT(ISNUMBER(J5)),"",IF(J5=0,"no RHU",IF(F5/J5>'05_Assumptions'!$B$4,"Yes","No"))) -> Yes | Z5: =IF(ISNUMBER(H5),H5,IF(AND(ISNUMBER(G5),ISNUMBER(I5)),G5-I5,"")) -> 2 | AA5: =IF(AND(ISNUMBER(G5),G5>0,ISNUMBER(Z5)),Z5/G5,"") -> 0.052631579 | AB5: =IF(AND(ISNUMBER(F5),F5>0,ISNUMBER(M5)),M5/F5*'05_Assumptions'!$B$6,"") | AC5: Barangay column preserves the 1,159-node 2020 model geography; current administrative coverage is 1,164 barangays and a five-barangay crosswalk is outstanding. 'Without a facility' = barangays with no matched registered health station. No bed column is carried in this annex. | AD5: =IF(ISNUMBER(F5),ROUNDUP(F5/'05_Assumptions'!$B$4,0),"") -> 3 | AE5: =IF(AND(ISNUMBER(AD5),ISNUMBER(J5)),MAX(0,AD5-J5),"") -> 2
A6: LDS | B6: Lanao del Sur | C6: Marantao | D6: LGU | E6: LDS · ANNEX A · §A · p. 49 | F6: 46233 | G6: 34 | I6: 29 | J6: 1 | K6: 5 | L6: 1 | N6: 89 | O6: 88.4 | P6: 234.3 | Q6: 37.1 | R6: 3.7 | S6: 2.8 | T6: 46233 | U6: =IF(AND(ISNUMBER(J6),J6>0,ISNUMBER(F6)),F6/J6,"no RHU recorded") -> 46233 | V6: =IF(AND(ISNUMBER(T6),ISNUMBER(U6)),U6-T6,"") -> 0 | W6: =IF(ISNUMBER(F6),ROUND(F6/'05_Assumptions'!$B$4,0),"") -> 2 | X6: =IF(AND(ISNUMBER(W6),ISNUMBER(J6)),MAX(0,W6-J6),"") -> 1 | Y6: =IF(NOT(ISNUMBER(J6)),"",IF(J6=0,"no RHU",IF(F6/J6>'05_Assumptions'!$B$4,"Yes","No"))) -> Yes | Z6: =IF(ISNUMBER(H6),H6,IF(AND(ISNUMBER(G6),ISNUMBER(I6)),G6-I6,"")) -> 5 | AA6: =IF(AND(ISNUMBER(G6),G6>0,ISNUMBER(Z6)),Z6/G6,"") -> 0.14705882 | AB6: =IF(AND(ISNUMBER(F6),F6>0,ISNUMBER(M6)),M6/F6*'05_Assumptions'!$B$6,"") | AC6: Barangay column preserves the 1,159-node 2020 model geography; current administrative coverage is 1,164 barangays and a five-barangay crosswalk is outstanding. 'Without a facility' = barangays with no matched registered health station. No bed column is carried in this annex. | AD6: =IF(ISNUMBER(F6),ROUNDUP(F6/'05_Assumptions'!$B$4,0),"") -> 3 | AE6: =IF(AND(ISNUMBER(AD6),ISNUMBER(J6)),MAX(0,AD6-J6),"") -> 2
A7: LDS | B7: Lanao del Sur | C7: Piagapo | D7: LGU | E7: LDS · ANNEX A · §A · p. 49 | F7: 40558 | G7: 37 | I7: 33 | J7: 1 | K7: 4 | L7: 0 | N7: 89.1 | O7: 65.7 | P7: 131.2 | Q7: 20.8 | R7: 2.2 | S7: 10.5 | T7: 40558 | U7: =IF(AND(ISNUMBER(J7),J7>0,ISNUMBER(F7)),F7/J7,"no RHU recorded") -> 40558 | V7: =IF(AND(ISNUMBER(T7),ISNUMBER(U7)),U7-T7,"") -> 0 | W7: =IF(ISNUMBER(F7),ROUND(F7/'05_Assumptions'!$B$4,0),"") -> 2 | X7: =IF(AND(ISNUMBER(W7),ISNUMBER(J7)),MAX(0,W7-J7),"") -> 1 | Y7: =IF(NOT(ISNUMBER(J7)),"",IF(J7=0,"no RHU",IF(F7/J7>'05_Assumptions'!$B$4,"Yes","No"))) -> Yes | Z7: =IF(ISNUMBER(H7),H7,IF(AND(ISNUMBER(G7),ISNUMBER(I7)),G7-I7,"")) -> 4 | AA7: =IF(AND(ISNUMBER(G7),G7>0,ISNUMBER(Z7)),Z7/G7,"") -> 0.10810811 | AB7: =IF(AND(ISNUMBER(F7),F7>0,ISNUMBER(M7)),M7/F7*'05_Assumptions'!$B$6,"") | AC7: Barangay column preserves the 1,159-node 2020 model geography; current administrative coverage is 1,164 barangays and a five-barangay crosswalk is outstanding. 'Without a facility' = barangays with no matched registered health station. No bed column is carried in this annex. | AD7: =IF(ISNUMBER(F7),ROUNDUP(F7/'05_Assumptions'!$B$4,0),"") -> 3 | AE7: =IF(AND(ISNUMBER(AD7),ISNUMBER(J7)),MAX(0,AD7-J7),"") -> 2
A8: LDS | B8: Lanao del Sur | C8: Balindong | D8: LGU | E8: LDS · ANNEX A · §A · p. 49 | F8: 40047 | G8: 38 | I8: 30 | J8: 1 | K8: 8 | L8: 1 | N8: 35.8 | O8: 85.1 | P8: 111.4 | Q8: 17.6 | R8: 0.2 | S8: 4.1 | T8: 40047 | U8: =IF(AND(ISNUMBER(J8),J8>0,ISNUMBER(F8)),F8/J8,"no RHU recorded") -> 40047 | V8: =IF(AND(ISNUMBER(T8),ISNUMBER(U8)),U8-T8,"") -> 0 | W8: =IF(ISNUMBER(F8),ROUND(F8/'05_Assumptions'!$B$4,0),"") -> 2 | X8: =IF(AND(ISNUMBER(W8),ISNUMBER(J8)),MAX(0,W8-J8),"") -> 1 | Y8: =IF(NOT(ISNUMBER(J8)),"",IF(J8=0,"no RHU",IF(F8/J8>'05_Assumptions'!$B$4,"Yes","No"))) -> Yes | Z8: =IF(ISNUMBER(H8),H8,IF(AND(ISNUMBER(G8),ISNUMBER(I8)),G8-I8,"")) -> 8 | AA8: =IF(AND(ISNUMBER(G8),G8>0,ISNUMBER(Z8)),Z8/G8,"") -> 0.21052632 | AB8: =IF(AND(ISNUMBER(F8),F8>0,ISNUMBER(M8)),M8/F8*'05_Assumptions'!$B$6,"") | AC8: Barangay column preserves the 1,159-node 2020 model geography; current administrative coverage is 1,164 barangays and a five-barangay crosswalk is outstanding. 'Without a facility' = barangays with no matched registered health station. No bed column is carried in this annex. | AD8: =IF(ISNUMBER(F8),ROUNDUP(F8/'05_Assumptions'!$B$4,0),"") -> 3 | AE8: =IF(AND(ISNUMBER(AD8),ISNUMBER(J8)),MAX(0,AD8-J8),"") -> 2
A9: LDS | B9: Lanao del Sur | C9: Maguing | D9: LGU | E9: LDS · ANNEX A · §A · p. 49 | F9: 37292 | G9: 34 | I9: 32 | J9: 1 | K9: 2 | L9: 0 | N9: 26.2 | O9: 83.8 | P9: 100.2 | Q9: 15.9 | R9: 1.3 | S9: 1.4 | T9: 37292 | U9: =IF(AND(ISNUMBER(J9),J9>0,ISNUMBER(F9)),F9/J9,"no RHU recorded") -> 37292 | V9: =IF(AND(ISNUMBER(T9),ISNUMBER(U9)),U9-T9,"") -> 0 | W9: =IF(ISNUMBER(F9),ROUND(F9/'05_Assumptions'!$B$4,0),"") -> 2 | X9: =IF(AND(ISNUMBER(W9),ISNUMBER(J9)),MAX(0,W9-J9),"") -> 1 | Y9: =IF(NOT(ISNUMBER(J9)),"",IF(J9=0,"no RHU",IF(F9/J9>'05_Assumptions'!$B$4,"Yes","No"))) -> Yes | Z9: =IF(ISNUMBER(H9),H9,IF(AND(ISNUMBER(G9),ISNUMBER(I9)),G9-I9,"")) -> 2 | AA9: =IF(AND(ISNUMBER(G9),G9>0,ISNUMBER(Z9)),Z9/G9,"") -> 0.058823529 | AB9: =IF(AND(ISNUMBER(F9),F9>0,ISNUMBER(M9)),M9/F9*'05_Assumptions'!$B$6,"") | AC9: Barangay column preserves the 1,159-node 2020 model geography; current administrative coverage is 1,164 barangays and a five-barangay crosswalk is outstanding. 'Without a facility' = barangays with no matched registered health station. No bed column is carried in this annex. | AD9: =IF(ISNUMBER(F9),ROUNDUP(F9/'05_Assumptions'!$B$4,0),"") -> 2 | AE9: =IF(AND(ISNUMBER(AD9),ISNUMBER(J9)),MAX(0,AD9-J9),"") -> 1
A10: LDS | B10: Lanao del Sur | C10: Tamparan | D10: LGU | E10: LDS · ANNEX A · §A · p. 49 | F10: 37190 | G10: 44 | I10: 44 | J10: 1 | K10: 0 | L10: 2 | N10: 98.4 | O10: 95.2 | P10: 139.2 | Q10: 22 | R10: 0.2 | S10: 0.6 | T10: 37190 | U10: =IF(AND(ISNUMBER(J10),J10>0,ISNUMBER(F10)),F10/J10,"no RHU recorded") -> 37190 | V10: =IF(AND(ISNUMBER(T10),ISNUMBER(U10)),U10-T10,"") -> 0 | W10: =IF(ISNUMBER(F10),ROUND(F10/'05_Assumptions'!$B$4,0),"") -> 2 | X10: =IF(AND(ISNUMBER(W10),ISNUMBER(J10)),MAX(0,W10-J10),"") -> 1 | Y10: =IF(NOT(ISNUMBER(J10)),"",IF(J10=0,"no RHU",IF(F10/J10>'05_Assumptions'!$B$4,"Yes","No"))) -> Yes | Z10: =IF(ISNUMBER(H10),H10,IF(AND(ISNUMBER(G10),ISNUMBER(I10)),G10-I10,"")) -> 0 | AA10: =IF(AND(ISNUMBER(G10),G10>0,ISNUMBER(Z10)),Z10/G10,"") -> 0 | AB10: =IF(AND(ISNUMBER(F10),F10>0,ISNUMBER(M10)),M10/F10*'05_Assumptions'!$B$6,"") | AC10: Barangay column preserves the 1,159-node 2020 model geography; current administrative coverage is 1,164 barangays and a five-barangay crosswalk is outstanding. 'Without a facility' = barangays with no matched registered health station. No bed column is carried in this annex. | AD10: =IF(ISNUMBER(F10),ROUNDUP(F10/'05_Assumptions'!$B$4,0),"") -> 2 | AE10: =IF(AND(ISNUMBER(AD10),ISNUMBER(J10)),MAX(0,AD10-J10),"") -> 1
A11: LDS | B11: Lanao del Sur | C11: Masiu | D11: LGU | E11: LDS · ANNEX A · §A · p. 49 | F11: 36803 | G11: 35 | I11: 32 | J11: 1 | K11: 3 | L11: 0 | N11: 101.4 | P11: 105.3 | Q11: 16.7 | R11: 2.5 | S11: 0.3 | T11: 36803 | U11: =IF(AND(ISNUMBER(J11),J11>0,ISNUMBER(F11)),F11/J11,"no RHU recorded") -> 36803 | V11: =IF(AND(ISNUMBER(T11),ISNUMBER(U11)),U11-T11,"") -> 0 | W11: =IF(ISNUMBER(F11),ROUND(F11/'05_Assumptions'!$B$4,0),"") -> 2 | X11: =IF(AND(ISNUMBER(W11),ISNUMBER(J11)),MAX(0,W11-J11),"") -> 1 | Y11: =IF(NOT(ISNUMBER(J11)),"",IF(J11=0,"no RHU",IF(F11/J11>'05_Assumptions'!$B$4,"Yes","No"))) -> Yes | Z11: =IF(ISNUMBER(H11),H11,IF(AND(ISNUMBER(G11),ISNUMBER(I11)),G11-I11,"")) -> 3 | AA11: =IF(AND(ISNUMBER(G11),G11>0,ISNUMBER(Z11)),Z11/G11,"") -> 0.085714286 | AB11: =IF(AND(ISNUMBER(F11),F11>0,ISNUMBER(M11)),M11/F11*'05_Assumptions'!$B$6,"") | AC11: Barangay column preserves the 1,159-node 2020 model geography; current administrative coverage is 1,164 barangays and a five-barangay crosswalk is outstanding. 'Without a facility' = barangays with no matched registered health station. No bed column is carried in this annex. | AD11: =IF(ISNUMBER(F11),ROUNDUP(F11/'05_Assumptions'!$B$4,0),"") -> 2 | AE11: =IF(AND(ISNUMBER(AD11),ISNUMBER(J11)),MAX(0,AD11-J11),"") -> 1
A12: LDS | B12: Lanao del Sur | C12: Ganassi | D12: LGU | E12: LDS · ANNEX A · §A · p. 49 | F12: 33897 | G12: 32 | I12: 32 | J12: 1 | K12: 0 | L12: 0 | N12: 6.6 | O12: 72 | P12: 72.5 | Q12: 11.5 | R12: 0.8 | S12: 5.1 | T12: 33897 | U12: =IF(AND(ISNUMBER(J12),J12>0,ISNUMBER(F12)),F12/J12,"no RHU recorded") -> 33897 | V12: =IF(AND(ISNUMBER(T12),ISNUMBER(U12)),U12-T12,"") -> 0 | W12: =IF(ISNUMBER(F12),ROUND(F12/'05_Assumptions'!$B$4,0),"") -> 2 | X12: =IF(AND(ISNUMBER(W12),ISNUMBER(J12)),MAX(0,W12-J12),"") -> 1 | Y12: =IF(NOT(ISNUMBER(J12)),"",IF(J12=0,"no RHU",IF(F12/J12>'05_Assumptions'!$B$4,"Yes","No"))) -> Yes | Z12: =IF(ISNUMBER(H12),H12,IF(AND(ISNUMBER(G12),ISNUMBER(I12)),G12-I12,"")) -> 0 | AA12: =IF(AND(ISNUMBER(G12),G12>0,ISNUMBER(Z12)),Z12/G12,"") -> 0 | AB12: =IF(AND(ISNUMBER(F12),F12>0,ISNUMBER(M12)),M12/F12*'05_Assumptions'!$B$6,"") | AC12: Barangay column preserves the 1,159-node 2020 model geography; current administrative coverage is 1,164 barangays and a five-barangay crosswalk is outstanding. 'Without a facility' = barangays with no matched registered health station. No bed column is carried in this annex. | AD12: =IF(ISNUMBER(F12),ROUNDUP(F12/'05_Assumptions'!$B$4,0),"") -> 2 | AE12: =IF(AND(ISNUMBER(AD12),ISNUMBER(J12)),MAX(0,AD12-J12),"") -> 1
A13: LDS | B13: Lanao del Sur | C13: Marogong | D13: LGU | E13: LDS · ANNEX A · §A · p. 49 | F13: 33595 | G13: 24 | I13: 19 | J13: 1 | K13: 5 | L13: 0 | N13: 81 | O13: 91.4 | P13: 222.4 | Q13: 35.2 | R13: 0.4 | S13: 0.9 | T13: 33595 | U13: =IF(AND(ISNUMBER(J13),J13>0,ISNUMBER(F13)),F13/J13,"no RHU recorded") -> 33595 | V13: =IF(AND(ISNUMBER(T13),ISNUMBER(U13)),U13-T13,"") -> 0 | W13: =IF(ISNUMBER(F13),ROUND(F13/'05_Assumptions'!$B$4,0),"") -> 2 | X13: =IF(AND(ISNUMBER(W13),ISNUMBER(J13)),MAX(0,W13-J13),"") -> 1 | Y13: =IF(NOT(ISNUMBER(J13)),"",IF(J13=0,"no RHU",IF(F13/J13>'05_Assumptions'!$B$4,"Yes","No"))) -> Yes | Z13: =IF(ISNUMBER(H13),H13,IF(AND(ISNUMBER(G13),ISNUMBER(I13)),G13-I13,"")) -> 5 | AA13: =IF(AND(ISNUMBER(G13),G13>0,ISNUMBER(Z13)),Z13/G13,"") -> 0.20833333 | AB13: =IF(AND(ISNUMBER(F13),F13>0,ISNUMBER(M13)),M13/F13*'05_Assumptions'!$B$6,"") | AC13: Barangay column preserves the 1,159-node 2020 model geography; current administrative coverage is 1,164 barangays and a five-barangay crosswalk is outstanding. 'Without a facility' = barangays with no matched registered health station. No bed column is carried in this annex. | AD13: =IF(ISNUMBER(F13),ROUNDUP(F13/'05_Assumptions'!$B$4,0),"") -> 2 | AE13: =IF(AND(ISNUMBER(AD13),ISNUMBER(J13)),MAX(0,AD13-J13),"") -> 1
A14: LDS | B14: Lanao del Sur | C14: Poona Bayabao | D14: LGU | E14: LDS · ANNEX A · §A · p. 49 | F14: 33307 | G14: 25 | I14: 23 | J14: 1 | K14: 2 | L14: 0 | N14: 39.9 | O14: 97 | P14: 110.6 | Q14: 17.5 | R14: 24.7 | S14: 1.1 | T14: 33307 | U14: =IF(AND(ISNUMBER(J14),J14>0,ISNUMBER(F14)),F14/J14,"no RHU recorded") -> 33307 | V14: =IF(AND(ISNUMBER(T14),ISNUMBER(U14)),U14-T14,"") -> 0 | W14: =IF(ISNUMBER(F14),ROUND(F14/'05_Assumptions'!$B$4,0),"") -> 2 | X14: =IF(AND(ISNUMBER(W14),ISNUMBER(J14)),MAX(0,W14-J14),"") -> 1 | Y14: =IF(NOT(ISNUMBER(J14)),"",IF(J14=0,"no RHU",IF(F14/J14>'05_Assumptions'!$B$4,"Yes","No"))) -> Yes | Z14: =IF(ISNUMBER(H14),H14,IF(AND(ISNUMBER(G14),ISNUMBER(I14)),G14-I14,"")) -> 2 | AA14: =IF(AND(ISNUMBER(G14),G14>0,ISNUMBER(Z14)),Z14/G14,"") -> 0.08 | AB14: =IF(AND(ISNUMBER(F14),F14>0,ISNUMBER(M14)),M14/F14*'05_Assumptions'!$B$6,"") | AC14: Barangay column preserves the 1,159-node 2020 model geography; current administrative coverage is 1,164 barangays and a five-barangay crosswalk is outstanding. 'Without a facility' = barangays with no matched registered health station. No bed column is carried in this annex. | AD14: =IF(ISNUMBER(F14),ROUNDUP(F14/'05_Assumptions'!$B$4,0),"") -> 2 | AE14: =IF(AND(ISNUMBER(AD14),ISNUMBER(J14)),MAX(0,AD14-J14),"") -> 1
A15: LDS | B15: Lanao del Sur | C15: Balabagan | D15: LGU | E15: LDS · ANNEX A · §A · p. 49 | F15: 31227 | G15: 27 | I15: 24 | J15: 1 | K15: 3 | L15: 0 | N15: 56.6 | O15: 96.1 | P15: 356.9 | Q15: 56.5 | R15: 1.2 | S15: 28.1 | T15: 31227 | U15: =IF(AND(ISNUMBER(J15),J15>0,ISNUMBER(F15)),F15/J15,"no RHU recorded") -> 31227 | V15: =IF(AND(ISNUMBER(T15),ISNUMBER(U15)),U15-T15,"") -> 0 | W15: =IF(ISNUMBER(F15),ROUND(F15/'05_Assumptions'!$B$4,0),"") -> 2 | X15: =IF(AND(ISNUMBER(W15),ISNUMBER(J15)),MAX(0,W15-J15),"") -> 1 | Y15: =IF(NOT(ISNUMBER(J15)),"",IF(J15=0,"no RHU",IF(F15/J15>'05_Assumptions'!$B$4,"Yes","No"))) -> Yes | Z15: =IF(ISNUMBER(H15),H15,IF(AND(ISNUMBER(G15),ISNUMBER(I15)),G15-I15,"")) -> 3 | AA15: =IF(AND(ISNUMBER(G15),G15>0,ISNUMBER(Z15)),Z15/G15,"") -> 0.11111111 | AB15: =IF(AND(ISNUMBER(F15),F15>0,ISNUMBER(M15)),M15/F15*'05_Assumptions'!$B$6,"") | AC15: Barangay column preserves the 1,159-node 2020 model geography; current administrative coverage is 1,164 barangays and a five-barangay crosswalk is outstanding. 'Without a facility' = barangays with no matched registered health station. No bed column is carried in this annex. | AD15: =IF(ISNUMBER(F15),ROUNDUP(F15/'05_Assumptions'!$B$4,0),"") -> 2 | AE15: =IF(AND(ISNUMBER(AD15),ISNUMBER(J15)),MAX(0,AD15-J15),"") -> 1
A16: LDS | B16: Lanao del Sur | C16: Bayang | D16: LGU | E16: LDS · ANNEX A · §A · p. 49 | F16: 30227 | G16: 49 | I16: 46 | J16: 1 | K16: 3 | L16: 0 | N16: 81 | O16: 0 | P16: 36.6 | Q16: 5.8 | R16: 2.2 | S16: 0.5 | T16: 30227 | U16: =IF(AND(ISNUMBER(J16),J16>0,ISNUMBER(F16)),F16/J16,"no RHU recorded") -> 30227 | V16: =IF(AND(ISNUMBER(T16),ISNUMBER(U16)),U16-T16,"") -> 0 | W16: =IF(ISNUMBER(F16),ROUND(F16/'05_Assumptions'!$B$4,0),"") -> 2 | X16: =IF(AND(ISNUMBER(W16),ISNUMBER(J16)),MAX(0,W16-J16),"") -> 1 | Y16: =IF(NOT(ISNUMBER(J16)),"",IF(J16=0,"no RHU",IF(F16/J16>'05_Assumptions'!$B$4,"Yes","No"))) -> Yes | Z16: =IF(ISNUMBER(H16),H16,IF(AND(ISNUMBER(G16),ISNUMBER(I16)),G16-I16,"")) -> 3 | AA16: =IF(AND(ISNUMBER(G16),G16>0,ISNUMBER(Z16)),Z16/G16,"") -> 0.06122449 | AB16: =IF(AND(ISNUMBER(F16),F16>0,ISNUMBER(M16)),M16/F16*'05_Assumptions'!$B$6,"") | AC16: Barangay column preserves the 1,159-node 2020 model geography; current administrative coverage is 1,164 barangays and a five-barangay crosswalk is outstanding. 'Without a facility' = barangays with no matched registered health station. No bed column is carried in this annex. | AD16: =IF(ISNUMBER(F16),ROUNDUP(F16/'05_Assumptions'!$B$4,0),"") -> 2 | AE16: =IF(AND(ISNUMBER(AD16),ISNUMBER(J16)),MAX(0,AD16-J16),"") -> 1
A17: LDS | B17: Lanao del Sur | C17: Madalum | D17: LGU | E17: LDS · ANNEX A · §A · p. 49 | F17: 30044 | G17: 37 | I17: 36 | J17: 1 | K17: 1 | L17: 0 | N17: 74.9 | P17: 72.2 | Q17: 11.4 | R17: 2.6 | S17: 0 | T17: 30044 | U17: =IF(AND(ISNUMBER(J17),J17>0,ISNUMBER(F17)),F17/J17,"no RHU recorded") -> 30044 | V17: =IF(AND(ISNUMBER(T17),ISNUMBER(U17)),U17-T17,"") -> 0 | W17: =IF(ISNUMBER(F17),ROUND(F17/'05_Assumptions'!$B$4,0),"") -> 2 | X17: =IF(AND(ISNUMBER(W17),ISNUMBER(J17)),MAX(0,W17-J17),"") -> 1 | Y17: =IF(NOT(ISNUMBER(J17)),"",IF(J17=0,"no RHU",IF(F17/J17>'05_Assumptions'!$B$4,"Yes","No"))) -> Yes | Z17: =IF(ISNUMBER(H17),H17,IF(AND(ISNUMBER(G17),ISNUMBER(I17)),G17-I17,"")) -> 1 | AA17: =IF(AND(ISNUMBER(G17),G17>0,ISNUMBER(Z17)),Z17/G17,"") -> 0.027027027 | AB17: =IF(AND(ISNUMBER(F17),F17>0,ISNUMBER(M17)),M17/F17*'05_Assumptions'!$B$6,"") | AC17: Barangay column preserves the 1,159-node 2020 model geography; current administrative coverage is 1,164 barangays and a five-barangay crosswalk is outstanding. 'Without a facility' = barangays with no matched registered health station. No bed column is carried in this annex. | AD17: =IF(ISNUMBER(F17),ROUNDUP(F17/'05_Assumptions'!$B$4,0),"") -> 2 | AE17: =IF(AND(ISNUMBER(AD17),ISNUMBER(J17)),MAX(0,AD17-J17),"") -> 1
A18: LDS | B18: Lanao del Sur | C18: Taraka | D18: LGU | E18: LDS · ANNEX A · §A · p. 49 | F18: 29558 | G18: 43 | I18: 41 | J18: 1 | K18: 2 | L18: 0 | N18: 20.9 | O18: 94.1 | P18: 122.6 | Q18: 19.4 | R18: 0.3 | S18: 15.6 | T18: 29558 | U18: =IF(AND(ISNUMBER(J18),J18>0,ISNUMBER(F18)),F18/J18,"no RHU recorded") -> 29558 | V18: =IF(AND(ISNUMBER(T18),ISNUMBER(U18)),U18-T18,"") -> 0 | W18: =IF(ISNUMBER(F18),ROUND(F18/'05_Assumptions'!$B$4,0),"") -> 1 | X18: =IF(AND(ISNUMBER(W18),ISNUMBER(J18)),MAX(0,W18-J18),"") -> 0 | Y18: =IF(NOT(ISNUMBER(J18)),"",IF(J18=0,"no RHU",IF(F18/J18>'05_Assumptions'!$B$4,"Yes","No"))) -> Yes | Z18: =IF(ISNUMBER(H18),H18,IF(AND(ISNUMBER(G18),ISNUMBER(I18)),G18-I18,"")) -> 2 | AA18: =IF(AND(ISNUMBER(G18),G18>0,ISNUMBER(Z18)),Z18/G18,"") -> 0.046511628 | AB18: =IF(AND(ISNUMBER(F18),F18>0,ISNUMBER(M18)),M18/F18*'05_Assumptions'!$B$6,"") | AC18: Barangay column preserves the 1,159-node 2020 model geography; current administrative coverage is 1,164 barangays and a five-barangay crosswalk is outstanding. 'Without a facility' = barangays with no matched registered health station. No bed column is carried in this annex. | AD18: =IF(ISNUMBER(F18),ROUNDUP(F18/'05_Assumptions'!$B$4,0),"") -> 2 | AE18: =IF(AND(ISNUMBER(AD18),ISNUMBER(J18)),MAX(0,AD18-J18),"") -> 1
A19: LDS | B19: Lanao del Sur | C19: Saguiaran | D19: LGU | E19: LDS · ANNEX A · §A · p. 49 | F19: 28807 | G19: 30 | I19: 24 | J19: 1 | K19: 6 | L19: 0 | N19: 70.6 | O19: 100 | P19: 189.1 | Q19: 29.9 | R19: 0 | S19: 1.9 | T19: 28807 | U19: =IF(AND(ISNUMBER(J19),J19>0,ISNUMBER(F19)),F19/J19,"no RHU recorded") -> 28807 | V19: =IF(AND(ISNUMBER(T19),ISNUMBER(U19)),U19-T19,"") -> 0 | W19: =IF(ISNUMBER(F19),ROUND(F19/'05_Assumptions'!$B$4,0),"") -> 1 | X19: =IF(AND(ISNUMBER(W19),ISNUMBER(J19)),MAX(0,W19-J19),"") -> 0 | Y19: =IF(NOT(ISNUMBER(J19)),"",IF(J19=0,"no RHU",IF(F19/J19>'05_Assumptions'!$B$4,"Yes","No"))) -> Yes | Z19: =IF(ISNUMBER(H19),H19,IF(AND(ISNUMBER(G19),ISNUMBER(I19)),G19-I19,"")) -> 6 | AA19: =IF(AND(ISNUMBER(G19),G19>0,ISNUMBER(Z19)),Z19/G19,"") -> 0.2 | AB19: =IF(AND(ISNUMBER(F19),F19>0,ISNUMBER(M19)),M19/F19*'05_Assumptions'!$B$6,"") | AC19: Barangay column preserves the 1,159-node 2020 model geography; current administrative coverage is 1,164 barangays and a five-barangay crosswalk is outstanding. 'Without a facility' = barangays with no matched registered health station. No bed column is carried in this annex. | AD19: =IF(ISNUMBER(F19),ROUNDUP(F19/'05_Assumptions'!$B$4,0),"") -> 2 | AE19: =IF(AND(ISNUMBER(AD19),ISNUMBER(J19)),MAX(0,AD19-J19),"") -> 1
A20: LDS | B20: Lanao del Sur | C20: Bubong | D20: LGU | E20: LDS · ANNEX A · §A · p. 49 | F20: 28733 | G20: 36 | I20: 34 | J20: 1 | K20: 2 | L20: 0 | N20: 102.7 | O20: 94.4 | P20: 129.8 | Q20: 20.5 | R20: 0 | S20: 21.9 | T20: 28733 | U20: =IF(AND(ISNUMBER(J20),J20>0,ISNUMBER(F20)),F20/J20,"no RHU recorded") -> 28733 | V20: =IF(AND(ISNUMBER(T20),ISNUMBER(U20)),U20-T20,"") -> 0 | W20: =IF(ISNUMBER(F20),ROUND(F20/'05_Assumptions'!$B$4,0),"") -> 1 | X20: =IF(AND(ISNUMBER(W20),ISNUMBER(J20)),MAX(0,W20-J20),"") -> 0 | Y20: =IF(NOT(ISNUMBER(J20)),"",IF(J20=0,"no RHU",IF(F20/J20>'05_Assumptions'!$B$4,"Yes","No"))) -> Yes | Z20: =IF(ISNUMBER(H20),H20,IF(AND(ISNUMBER(G20),ISNUMBER(I20)),G20-I20,"")) -> 2 | AA20: =IF(AND(ISNUMBER(G20),G20>0,ISNUMBER(Z20)),Z20/G20,"") -> 0.055555556 | AB20: =IF(AND(ISNUMBER(F20),F20>0,ISNUMBER(M20)),M20/F20*'05_Assumptions'!$B$6,"") | AC20: Barangay column preserves the 1,159-node 2020 model geography; current administrative coverage is 1,164 barangays and a five-barangay crosswalk is outstanding. 'Without a facility' = barangays with no matched registered health station. No bed column is carried in this annex. | AD20: =IF(ISNUMBER(F20),ROUNDUP(F20/'05_Assumptions'!$B$4,0),"") -> 2 | AE20: =IF(AND(ISNUMBER(AD20),ISNUMBER(J20)),MAX(0,AD20-J20),"") -> 1
A21: LDS | B21: Lanao del Sur | C21: Binidayan | D21: LGU | E21: LDS · ANNEX A · §A · p. 49 | F21: 27031 | G21: 26 | I21: 26 | J21: 1 | K21: 0 | L21: 1 | N21: 85.2 | O21: 21.2 | P21: 55.7 | Q21: 8.8 | R21: 2.4 | S21: 30.2 | T21: 27031 | U21: =IF(AND(ISNUMBER(J21),J21>0,ISNUMBER(F21)),F21/J21,"no RHU recorded") -> 27031 | V21: =IF(AND(ISNUMBER(T21),ISNUMBER(U21)),U21-T21,"") -> 0 | W21: =IF(ISNUMBER(F21),ROUND(F21/'05_Assumptions'!$B$4,0),"") -> 1 | X21: =IF(AND(ISNUMBER(W21),ISNUMBER(J21)),MAX(0,W21-J21),"") -> 0 | Y21: =IF(NOT(ISNUMBER(J21)),"",IF(J21=0,"no RHU",IF(F21/J21>'05_Assumptions'!$B$4,"Yes","No"))) -> Yes | Z21: =IF(ISNUMBER(H21),H21,IF(AND(ISNUMBER(G21),ISNUMBER(I21)),G21-I21,"")) -> 0 | AA21: =IF(AND(ISNUMBER(G21),G21>0,ISNUMBER(Z21)),Z21/G21,"") -> 0 | AB21: =IF(AND(ISNUMBER(F21),F21>0,ISNUMBER(M21)),M21/F21*'05_Assumptions'!$B$6,"") | AC21: Barangay column preserves the 1,159-node 2020 model geography; current administrative coverage is 1,164 barangays and a five-barangay crosswalk is outstanding. 'Without a facility' = barangays with no matched registered health station. No bed column is carried in this annex. | AD21: =IF(ISNUMBER(F21),ROUNDUP(F21/'05_Assumptions'!$B$4,0),"") -> 2 | AE21: =IF(AND(ISNUMBER(AD21),ISNUMBER(J21)),MAX(0,AD21-J21),"") -> 1
A22: LDS | B22: Lanao del Sur | C22: Ditsaan-Ramain | D22: LGU | E22: LDS · ANNEX A · §A · p. 49 | F22: 26918 | G22: 35 | I22: 32 | J22: 1 | K22: 3 | L22: 0 | N22: 91.8 | O22: 96.5 | P22: 122.1 | Q22: 19.3 | R22: 0.9 | S22: 2.4 | T22: 26918 | U22: =IF(AND(ISNUMBER(J22),J22>0,ISNUMBER(F22)),F22/J22,"no RHU recorded") -> 26918 | V22: =IF(AND(ISNUMBER(T22),ISNUMBER(U22)),U22-T22,"") -> 0 | W22: =IF(ISNUMBER(F22),ROUND(F22/'05_Assumptions'!$B$4,0),"") -> 1 | X22: =IF(AND(ISNUMBER(W22),ISNUMBER(J22)),MAX(0,W22-J22),"") -> 0 | Y22: =IF(NOT(ISNUMBER(J22)),"",IF(J22=0,"no RHU",IF(F22/J22>'05_Assumptions'!$B$4,"Yes","No"))) -> Yes | Z22: =IF(ISNUMBER(H22),H22,IF(AND(ISNUMBER(G22),ISNUMBER(I22)),G22-I22,"")) -> 3 | AA22: =IF(AND(ISNUMBER(G22),G22>0,ISNUMBER(Z22)),Z22/G22,"") -> 0.085714286 | AB22: =IF(AND(ISNUMBER(F22),F22>0,ISNUMBER(M22)),M22/F22*'05_Assumptions'!$B$6,"") | AC22: Barangay column preserves the 1,159-node 2020 model geography; current administrative coverage is 1,164 barangays and a five-barangay crosswalk is outstanding. 'Without a facility' = barangays with no matched registered health station. No bed column is carried in this annex. | AD22: =IF(ISNUMBER(F22),ROUNDUP(F22/'05_Assumptions'!$B$4,0),"") -> 2 | AE22: =IF(AND(ISNUMBER(AD22),ISNUMBER(J22)),MAX(0,AD22-J22),"") -> 1
A23: LDS | B23: Lanao del Sur | C23: Tugaya | D23: LGU | E23: LDS · ANNEX A · §A · p. 49 | F23: 26283 | G23: 23 | I23: 22 | J23: 1 | K23: 1 | L23: 0 | N23: 71.5 | O23: 31.2 | P23: 77.4 | Q23: 12.3 | R23: 1.4 | S23: 7.7 | T23: 26283 | U23: =IF(AND(ISNUMBER(J23),J23>0,ISNUMBER(F23)),F23/J23,"no RHU recorded") -> 26283 | V23: =IF(AND(ISNUMBER(T23),ISNUMBER(U23)),U23-T23,"") -> 0 | W23: =IF(ISNUMBER(F23),ROUND(F23/'05_Assumptions'!$B$4,0),"") -> 1 | X23: =IF(AND(ISNUMBER(W23),ISNUMBER(J23)),MAX(0,W23-J23),"") -> 0 | Y23: =IF(NOT(ISNUMBER(J23)),"",IF(J23=0,"no RHU",IF(F23/J23>'05_Assumptions'!$B$4,"Yes","No"))) -> Yes | Z23: =IF(ISNUMBER(H23),H23,IF(AND(ISNUMBER(G23),ISNUMBER(I23)),G23-I23,"")) -> 1 | AA23: =IF(AND(ISNUMBER(G23),G23>0,ISNUMBER(Z23)),Z23/G23,"") -> 0.043478261 | AB23: =IF(AND(ISNUMBER(F23),F23>0,ISNUMBER(M23)),M23/F23*'05_Assumptions'!$B$6,"") | AC23: Barangay column preserves the 1,159-node 2020 model geography; current administrative coverage is 1,164 barangays and a five-barangay crosswalk is outstanding. 'Without a facility' = barangays with no matched registered health station. No bed column is carried in this annex. | AD23: =IF(ISNUMBER(F23),ROUNDUP(F23/'05_Assumptions'!$B$4,0),"") -> 2 | AE23: =IF(AND(ISNUMBER(AD23),ISNUMBER(J23)),MAX(0,AD23-J23),"") -> 1
A24: LDS | B24: Lanao del Sur | C24: Butig | D24: LGU | E24: LDS · ANNEX A · §A · p. 49 | F24: 25394 | G24: 16 | I24: 14 | J24: 1 | K24: 2 | L24: 0 | N24: 88.2 | O24: 75.7 | P24: 91 | Q24: 14.4 | R24: 16.2 | S24: 14.6 | T24: 25394 | U24: =IF(AND(ISNUMBER(J24),J24>0,ISNUMBER(F24)),F24/J24,"no RHU recorded") -> 25394 | V24: =IF(AND(ISNUMBER(T24),ISNUMBER(U24)),U24-T24,"") -> 0 | W24: =IF(ISNUMBER(F24),ROUND(F24/'05_Assumptions'!$B$4,0),"") -> 1 | X24: =IF(AND(ISNUMBER(W24),ISNUMBER(J24)),MAX(0,W24-J24),"") -> 0 | Y24: =IF(NOT(ISNUMBER(J24)),"",IF(J24=0,"no RHU",IF(F24/J24>'05_Assumptions'!$B$4,"Yes","No"))) -> Yes | Z24: =IF(ISNUMBER(H24),H24,IF(AND(ISNUMBER(G24),ISNUMBER(I24)),G24-I24,"")) -> 2 | AA24: =IF(AND(ISNUMBER(G24),G24>0,ISNUMBER(Z24)),Z24/G24,"") -> 0.125 | AB24: =IF(AND(ISNUMBER(F24),F24>0,ISNUMBER(M24)),M24/F24*'05_Assumptions'!$B$6,"") | AC24: Barangay column preserves the 1,159-node 2020 model geography; current administrative coverage is 1,164 barangays and a five-barangay crosswalk is outstanding. 'Without a facility' = barangays with no matched registered health station. No bed column is carried in this annex. | AD24: =IF(ISNUMBER(F24),ROUNDUP(F24/'05_Assumptions'!$B$4,0),"") -> 2 | AE24: =IF(AND(ISNUMBER(AD24),ISNUMBER(J24)),MAX(0,AD24-J24),"") -> 1
A25: LDS | B25: Lanao del Sur | C25: Lumbatan | D25: LGU | E25: LDS · ANNEX A · §A · p. 49 | F25: 24988 | G25: 21 | I25: 21 | J25: 1 | K25: 0 | L25: 0 | N25: 58.9 | O25: 78.7 | P25: 142.5 | Q25: 22.5 | R25: 0.4 | S25: 0.4 | T25: 24988 | U25: =IF(AND(ISNUMBER(J25),J25>0,ISNUMBER(F25)),F25/J25,"no RHU recorded") -> 24988 | V25: =IF(AND(ISNUMBER(T25),ISNUMBER(U25)),U25-T25,"") -> 0 | W25: =IF(ISNUMBER(F25),ROUND(F25/'05_Assumptions'!$B$4,0),"") -> 1 | X25: =IF(AND(ISNUMBER(W25),ISNUMBER(J25)),MAX(0,W25-J25),"") -> 0 | Y25: =IF(NOT(ISNUMBER(J25)),"",IF(J25=0,"no RHU",IF(F25/J25>'05_Assumptions'!$B$4,"Yes","No"))) -> Yes | Z25: =IF(ISNUMBER(H25),H25,IF(AND(ISNUMBER(G25),ISNUMBER(I25)),G25-I25,"")) -> 0 | AA25: =IF(AND(ISNUMBER(G25),G25>0,ISNUMBER(Z25)),Z25/G25,"") -> 0 | AB25: =IF(AND(ISNUMBER(F25),F25>0,ISNUMBER(M25)),M25/F25*'05_Assumptions'!$B$6,"") | AC25: Barangay column preserves the 1,159-node 2020 model geography; current administrative coverage is 1,164 barangays and a five-barangay crosswalk is outstanding. 'Without a facility' = barangays with no matched registered health station. No bed column is carried in this annex. | AD25: =IF(ISNUMBER(F25),ROUNDUP(F25/'05_Assumptions'!$B$4,0),"") -> 2 | AE25: =IF(AND(ISNUMBER(AD25),ISNUMBER(J25)),MAX(0,AD25-J25),"") -> 1
A26: LDS | B26: Lanao del Sur | C26: Madamba | D26: LGU | E26: LDS · ANNEX A · §A · p. 49 | F26: 24886 | G26: 24 | I26: 23 | J26: 1 | K26: 1 | L26: 0 | N26: 98.5 | O26: 30.5 | P26: 94 | Q26: 14.9 | R26: 9.8 | S26: 10.7 | T26: 24886 | U26: =IF(AND(ISNUMBER(J26),J26>0,ISNUMBER(F26)),F26/J26,"no RHU recorded") -> 24886 | V26: =IF(AND(ISNUMBER(T26),ISNUMBER(U26)),U26-T26,"") -> 0 | W26: =IF(ISNUMBER(F26),ROUND(F26/'05_Assumptions'!$B$4,0),"") -> 1 | X26: =IF(AND(ISNUMBER(W26),ISNUMBER(J26)),MAX(0,W26-J26),"") -> 0 | Y26: =IF(NOT(ISNUMBER(J26)),"",IF(J26=0,"no RHU",IF(F26/J26>'05_Assumptions'!$B$4,"Yes","No"))) -> Yes | Z26: =IF(ISNUMBER(H26),H26,IF(AND(ISNUMBER(G26),ISNUMBER(I26)),G26-I26,"")) -> 1 | AA26: =IF(AND(ISNUMBER(G26),G26>0,ISNUMBER(Z26)),Z26/G26,"") -> 0.041666667 | AB26: =IF(AND(ISNUMBER(F26),F26>0,ISNUMBER(M26)),M26/F26*'05_Assumptions'!$B$6,"") | AC26: Barangay column preserves the 1,159-node 2020 model geography; current administrative coverage is 1,164 barangays and a five-barangay crosswalk is outstanding. 'Without a facility' = barangays with no matched registered health station. No bed column is carried in this annex. | AD26: =IF(ISNUMBER(F26),ROUNDUP(F26/'05_Assumptions'!$B$4,0),"") -> 2 | AE26: =IF(AND(ISNUMBER(AD26),ISNUMBER(J26)),MAX(0,AD26-J26),"") -> 1
A27: LDS | B27: Lanao del Sur | C27: Bacolod-Kalawi | D27: LGU | E27: LDS · ANNEX A · §A · p. 49 | F27: 24381 | G27: 26 | I27: 21 | J27: 1 | K27: 5 | L27: 0 | N27: 86.9 | O27: 43.2 | P27: 96.9 | Q27: 15.3 | R27: 0.2 | S27: 10.8 | T27: 24381 | U27: =IF(AND(ISNUMBER(J27),J27>0,ISNUMBER(F27)),F27/J27,"no RHU recorded") -> 24381 | V27: =IF(AND(ISNUMBER(T27),ISNUMBER(U27)),U27-T27,"") -> 0 | W27: =IF(ISNUMBER(F27),ROUND(F27/'05_Assumptions'!$B$4,0),"") -> 1 | X27: =IF(AND(ISNUMBER(W27),ISNUMBER(J27)),MAX(0,W27-J27),"") -> 0 | Y27: =IF(NOT(ISNUMBER(J27)),"",IF(J27=0,"no RHU",IF(F27/J27>'05_Assumptions'!$B$4,"Yes","No"))) -> Yes | Z27: =IF(ISNUMBER(H27),H27,IF(AND(ISNUMBER(G27),ISNUMBER(I27)),G27-I27,"")) -> 5 | AA27: =IF(AND(ISNUMBER(G27),G27>0,ISNUMBER(Z27)),Z27/G27,"") -> 0.19230769 | AB27: =IF(AND(ISNUMBER(F27),F27>0,ISNUMBER(M27)),M27/F27*'05_Assumptions'!$B$6,"") | AC27: Barangay column preserves the 1,159-node 2020 model geography; current administrative coverage is 1,164 barangays and a five-barangay crosswalk is outstanding. 'Without a facility' = barangays with no matched registered health station. No bed column is carried in this annex. | AD27: =IF(ISNUMBER(F27),ROUNDUP(F27/'05_Assumptions'!$B$4,0),"") -> 2 | AE27: =IF(AND(ISNUMBER(AD27),ISNUMBER(J27)),MAX(0,AD27-J27),"") -> 1
A28: LDS | B28: Lanao del Sur | C28: Buadiposo-Buntong | D28: LGU | E28: LDS · ANNEX A · §A · p. 49 | F28: 23283 | G28: 33 | I28: 30 | J28: 1 | K28: 3 | L28: 0 | N28: 57.2 | O28: 97.5 | P28: 119.8 | Q28: 19 | R28: 0 | S28: 32.4 | T28: 23283 | U28: =IF(AND(ISNUMBER(J28),J28>0,ISNUMBER(F28)),F28/J28,"no RHU recorded") -> 23283 | V28: =IF(AND(ISNUMBER(T28),ISNUMBER(U28)),U28-T28,"") -> 0 | W28: =IF(ISNUMBER(F28),ROUND(F28/'05_Assumptions'!$B$4,0),"") -> 1 | X28: =IF(AND(ISNUMBER(W28),ISNUMBER(J28)),MAX(0,W28-J28),"") -> 0 | Y28: =IF(NOT(ISNUMBER(J28)),"",IF(J28=0,"no RHU",IF(F28/J28>'05_Assumptions'!$B$4,"Yes","No"))) -> Yes | Z28: =IF(ISNUMBER(H28),H28,IF(AND(ISNUMBER(G28),ISNUMBER(I28)),G28-I28,"")) -> 3 | AA28: =IF(AND(ISNUMBER(G28),G28>0,ISNUMBER(Z28)),Z28/G28,"") -> 0.090909091 | AB28: =IF(AND(ISNUMBER(F28),F28>0,ISNUMBER(M28)),M28/F28*'05_Assumptions'!$B$6,"") | AC28: Barangay column preserves the 1,159-node 2020 model geography; current administrative coverage is 1,164 barangays and a five-barangay crosswalk is outstanding. 'Without a facility' = barangays with no matched registered health station. No bed column is carried in this annex. | AD28: =IF(ISNUMBER(F28),ROUNDUP(F28/'05_Assumptions'!$B$4,0),"") -> 2 | AE28: =IF(AND(ISNUMBER(AD28),ISNUMBER(J28)),MAX(0,AD28-J28),"") -> 1
A29: LDS | B29: Lanao del Sur | C29: Kapatagan | D29: LGU | E29: LDS · ANNEX A · §A · p. 49 | F29: 23228 | G29: 15 | I29: 12 | J29: 1 | K29: 3 | L29: 0 | N29: 66.3 | O29: 77.5 | P29: 311.2 | Q29: 49.3 | R29: 2.9 | S29: 0.2 | T29: 23228 | U29: =IF(AND(ISNUMBER(J29),J29>0,ISNUMBER(F29)),F29/J29,"no RHU recorded") -> 23228 | V29: =IF(AND(ISNUMBER(T29),ISNUMBER(U29)),U29-T29,"") -> 0 | W29: =IF(ISNUMBER(F29),ROUND(F29/'05_Assumptions'!$B$4,0),"") -> 1 | X29: =IF(AND(ISNUMBER(W29),ISNUMBER(J29)),MAX(0,W29-J29),"") -> 0 | Y29: =IF(NOT(ISNUMBER(J29)),"",IF(J29=0,"no RHU",IF(F29/J29>'05_Assumptions'!$B$4,"Yes","No"))) -> Yes | Z29: =IF(ISNUMBER(H29),H29,IF(AND(ISNUMBER(G29),ISNUMBER(I29)),G29-I29,"")) -> 3 | AA29: =IF(AND(ISNUMBER(G29),G29>0,ISNUMBER(Z29)),Z29/G29,"") -> 0.2 | AB29: =IF(AND(ISNUMBER(F29),F29>0,ISNUMBER(M29)),M29/F29*'05_Assumptions'!$B$6,"") | AC29: Barangay column preserves the 1,159-node 2020 model geography; current administrative coverage is 1,164 barangays and a five-barangay crosswalk is outstanding. 'Without a facility' = barangays with no matched registered health station. No bed column is carried in this annex. | AD29: =IF(ISNUMBER(F29),ROUNDUP(F29/'05_Assumptions'!$B$4,0),"") -> 2 | AE29: =IF(AND(ISNUMBER(AD29),ISNUMBER(J29)),MAX(0,AD29-J29),"") -> 1
... A42: LDS | B42: Lanao del Sur | C42: PROVINCE | D42: Provincial / area total as annexed | E42: LDS · ANNEX A · §A · p. 49 | F42: 1368137 | G42: 1159 | I42: 1024 | J42: 44 | K42: 140 | L42: 11 | N42: 80.4 | O42: 82.1 | P42: 162.9 | Q42: 25.7 | R42: 4.3 | S42: 5.3 | T42: 31094 | U42: =IF(AND(ISNUMBER(J42),J42>0,ISNUMBER(F42)),F42/J42,"no RHU recorded") -> 31094.023 | V42: =IF(AND(ISNUMBER(T42),ISNUMBER(U42)),U42-T42,"") -> 0.022727273 | W42: =IF(ISNUMBER(F42),ROUND(F42/'05_Assumptions'!$B$4,0),"") -> 68 | X42: =IF(AND(ISNUMBER(W42),ISNUMBER(J42)),MAX(0,W42-J42),"") -> 24 | Y42: =IF(NOT(ISNUMBER(J42)),"",IF(J42=0,"no RHU",IF(F42/J42>'05_Assumptions'!$B$4,"Yes","No"))) -> Yes | Z42: =IF(ISNUMBER(H42),H42,IF(AND(ISNUMBER(G42),ISNUMBER(I42)),G42-I42,"")) -> 135 | AA42: =IF(AND(ISNUMBER(G42),G42>0,ISNUMBER(Z42)),Z42/G42,"") -> 0.11647972 | AB42: =IF(AND(ISNUMBER(F42),F42>0,ISNUMBER(M42)),M42/F42*'05_Assumptions'!$B$6,"") | AC42: Barangay column preserves the 1,159-node 2020 model geography; current administrative coverage is 1,164 barangays and a five-barangay crosswalk is outstanding. 'Without a facility' = barangays with no matched registered health station. No bed column is carried in this annex. | AD42: =IF(ISNUMBER(F42),ROUNDUP(F42/'05_Assumptions'!$B$4,0),"") -> 69 | AE42: =IF(AND(ISNUMBER(AD42),ISNUMBER(J42)),MAX(0,AD42-J42),"") -> 25
A43: MDN | B43: Maguindanao del Norte | C43: Datu Odin Sinsuat | D43: LGU | E43: MDN · ANNEX A · §A · p. 41 | F43: 152907 | G43: 34 | I43: 1 | J43: 1 | K43: 33 | L43: 2 | M43: 100 | N43: 56.3 | O43: 69.2 | P43: 204.4 | Q43: 32.7 | R43: 0.87 | S43: 1.77 | T43: 152907 | U43: =IF(AND(ISNUMBER(J43),J43>0,ISNUMBER(F43)),F43/J43,"no RHU recorded") -> 152907 | V43: =IF(AND(ISNUMBER(T43),ISNUMBER(U43)),U43-T43,"") -> 0 | W43: =IF(ISNUMBER(F43),ROUND(F43/'05_Assumptions'!$B$4,0),"") -> 8 | X43: =IF(AND(ISNUMBER(W43),ISNUMBER(J43)),MAX(0,W43-J43),"") -> 7 | Y43: =IF(NOT(ISNUMBER(J43)),"",IF(J43=0,"no RHU",IF(F43/J43>'05_Assumptions'!$B$4,"Yes","No"))) -> Yes | Z43: =IF(ISNUMBER(H43),H43,IF(AND(ISNUMBER(G43),ISNUMBER(I43)),G43-I43,"")) -> 33 | AA43: =IF(AND(ISNUMBER(G43),G43>0,ISNUMBER(Z43)),Z43/G43,"") -> 0.97058824 | AB43: =IF(AND(ISNUMBER(F43),F43>0,ISNUMBER(M43)),M43/F43*'05_Assumptions'!$B$6,"") -> 0.6539923 | AC43: 'Without a facility' = barangays with no registered barangay health station. Cotabato City is shown for reference and is not a component LGU of the province. | AD43: =IF(ISNUMBER(F43),ROUNDUP(F43/'05_Assumptions'!$B$4,0),"") -> 8 | AE43: =IF(AND(ISNUMBER(AD43),ISNUMBER(J43)),MAX(0,AD43-J43),"") -> 7
A44: MDN | B44: Maguindanao del Norte | C44: Sultan Kudarat | D44: LGU | E44: MDN · ANNEX A · §A · p. 41 | F44: 124965 | G44: 39 | I44: 9 | J44: 1 | K44: 30 | L44: 1 | M44: 200 | N44: 71.4 | O44: 70.7 | P44: 163.3 | Q44: 26.1 | R44: 4.85 | S44: 1.24 | T44: 124965 | U44: =IF(AND(ISNUMBER(J44),J44>0,ISNUMBER(F44)),F44/J44,"no RHU recorded") -> 124965 | V44: =IF(AND(ISNUMBER(T44),ISNUMBER(U44)),U44-T44,"") -> 0 | W44: =IF(ISNUMBER(F44),ROUND(F44/'05_Assumptions'!$B$4,0),"") -> 6 | X44: =IF(AND(ISNUMBER(W44),ISNUMBER(J44)),MAX(0,W44-J44),"") -> 5 | Y44: =IF(NOT(ISNUMBER(J44)),"",IF(J44=0,"no RHU",IF(F44/J44>'05_Assumptions'!$B$4,"Yes","No"))) -> Yes | Z44: =IF(ISNUMBER(H44),H44,IF(AND(ISNUMBER(G44),ISNUMBER(I44)),G44-I44,"")) -> 30 | AA44: =IF(AND(ISNUMBER(G44),G44>0,ISNUMBER(Z44)),Z44/G44,"") -> 0.76923077 | AB44: =IF(AND(ISNUMBER(F44),F44>0,ISNUMBER(M44)),M44/F44*'05_Assumptions'!$B$6,"") -> 1.6004481 | AC44: 'Without a facility' = barangays with no registered barangay health station. Cotabato City is shown for reference and is not a component LGU of the province. | AD44: =IF(ISNUMBER(F44),ROUNDUP(F44/'05_Assumptions'!$B$4,0),"") -> 7 | AE44: =IF(AND(ISNUMBER(AD44),ISNUMBER(J44)),MAX(0,AD44-J44),"") -> 6
A45: MDN | B45: Maguindanao del Norte | C45: Parang | D45: LGU | E45: MDN · ANNEX A · §A · p. 41 | F45: 123209 | G45: 25 | I45: 2 | J45: 1 | K45: 24 | L45: 2 | M45: 35 | N45: 51.7 | O45: 76.4 | P45: 189.4 | Q45: 30.3 | R45: 2.48 | S45: 5.66 | T45: 123209 | U45: =IF(AND(ISNUMBER(J45),J45>0,ISNUMBER(F45)),F45/J45,"no RHU recorded") -> 123209 | V45: =IF(AND(ISNUMBER(T45),ISNUMBER(U45)),U45-T45,"") -> 0 | W45: =IF(ISNUMBER(F45),ROUND(F45/'05_Assumptions'!$B$4,0),"") -> 6 | X45: =IF(AND(ISNUMBER(W45),ISNUMBER(J45)),MAX(0,W45-J45),"") -> 5 | Y45: =IF(NOT(ISNUMBER(J45)),"",IF(J45=0,"no RHU",IF(F45/J45>'05_Assumptions'!$B$4,"Yes","No"))) -> Yes | Z45: =IF(ISNUMBER(H45),H45,IF(AND(ISNUMBER(G45),ISNUMBER(I45)),G45-I45,"")) -> 23 | AA45: =IF(AND(ISNUMBER(G45),G45>0,ISNUMBER(Z45)),Z45/G45,"") -> 0.92 | AB45: =IF(AND(ISNUMBER(F45),F45>0,ISNUMBER(M45)),M45/F45*'05_Assumptions'!$B$6,"") -> 0.28407016 | AC45: 'Without a facility' = barangays with no registered barangay health station. Cotabato City is shown for reference and is not a component LGU of the province. | AD45: =IF(ISNUMBER(F45),ROUNDUP(F45/'05_Assumptions'!$B$4,0),"") -> 7 | AE45: =IF(AND(ISNUMBER(AD45),ISNUMBER(J45)),MAX(0,AD45-J45),"") -> 6
A46: MDN | B46: Maguindanao del Norte | C46: Upi | D46: LGU | E46: MDN · ANNEX A · §A · p. 41 | F46: 65363 | G46: 23 | I46: 6 | J46: 1 | K46: 17 | L46: 1 | M46: 25 | N46: 58.5 | O46: 78.8 | P46: 268 | Q46: 42.9 | R46: 1.15 | S46: 9.36 | T46: 65363 | U46: =IF(AND(ISNUMBER(J46),J46>0,ISNUMBER(F46)),F46/J46,"no RHU recorded") -> 65363 | V46: =IF(AND(ISNUMBER(T46),ISNUMBER(U46)),U46-T46,"") -> 0 | W46: =IF(ISNUMBER(F46),ROUND(F46/'05_Assumptions'!$B$4,0),"") -> 3 | X46: =IF(AND(ISNUMBER(W46),ISNUMBER(J46)),MAX(0,W46-J46),"") -> 2 | Y46: =IF(NOT(ISNUMBER(J46)),"",IF(J46=0,"no RHU",IF(F46/J46>'05_Assumptions'!$B$4,"Yes","No"))) -> Yes | Z46: =IF(ISNUMBER(H46),H46,IF(AND(ISNUMBER(G46),ISNUMBER(I46)),G46-I46,"")) -> 17 | AA46: =IF(AND(ISNUMBER(G46),G46>0,ISNUMBER(Z46)),Z46/G46,"") -> 0.73913043 | AB46: =IF(AND(ISNUMBER(F46),F46>0,ISNUMBER(M46)),M46/F46*'05_Assumptions'!$B$6,"") -> 0.38247938 | AC46: 'Without a facility' = barangays with no registered barangay health station. Cotabato City is shown for reference and is not a component LGU of the province. | AD46: =IF(ISNUMBER(F46),ROUNDUP(F46/'05_Assumptions'!$B$4,0),"") -> 4 | AE46: =IF(AND(ISNUMBER(AD46),ISNUMBER(J46)),MAX(0,AD46-J46),"") -> 3
A47: MDN | B47: Maguindanao del Norte | C47: Buldon | D47: LGU | E47: MDN · ANNEX A · §A · p. 41 | F47: 45676 | G47: 15 | I47: 3 | J47: 1 | K47: 12 | L47: 0 | N47: 42.2 | O47: 35.9 | P47: 95.8 | Q47: 15.3 | R47: 1.24 | S47: 5.94 | T47: 45676 | U47: =IF(AND(ISNUMBER(J47),J47>0,ISNUMBER(F47)),F47/J47,"no RHU recorded") -> 45676 | V47: =IF(AND(ISNUMBER(T47),ISNUMBER(U47)),U47-T47,"") -> 0 | W47: =IF(ISNUMBER(F47),ROUND(F47/'05_Assumptions'!$B$4,0),"") -> 2 | X47: =IF(AND(ISNUMBER(W47),ISNUMBER(J47)),MAX(0,W47-J47),"") -> 1 | Y47: =IF(NOT(ISNUMBER(J47)),"",IF(J47=0,"no RHU",IF(F47/J47>'05_Assumptions'!$B$4,"Yes","No"))) -> Yes | Z47: =IF(ISNUMBER(H47),H47,IF(AND(ISNUMBER(G47),ISNUMBER(I47)),G47-I47,"")) -> 12 | AA47: =IF(AND(ISNUMBER(G47),G47>0,ISNUMBER(Z47)),Z47/G47,"") -> 0.8 | AB47: =IF(AND(ISNUMBER(F47),F47>0,ISNUMBER(M47)),M47/F47*'05_Assumptions'!$B$6,"") | AC47: 'Without a facility' = barangays with no registered barangay health station. Cotabato City is shown for reference and is not a component LGU of the province. | AD47: =IF(ISNUMBER(F47),ROUNDUP(F47/'05_Assumptions'!$B$4,0),"") -> 3 | AE47: =IF(AND(ISNUMBER(AD47),ISNUMBER(J47)),MAX(0,AD47-J47),"") -> 2
A48: MDN | B48: Maguindanao del Norte | C48: Barira | D48: LGU | E48: MDN · ANNEX A · §A · p. 41 | F48: 43301 | G48: 14 | I48: 2 | J48: 1 | K48: 13 | L48: 0 | N48: 56.9 | O48: 34.2 | P48: 109.8 | Q48: 17.6 | R48: 2.8 | S48: 10.25 | T48: 43301 | U48: =IF(AND(ISNUMBER(J48),J48>0,ISNUMBER(F48)),F48/J48,"no RHU recorded") -> 43301 | V48: =IF(AND(ISNUMBER(T48),ISNUMBER(U48)),U48-T48,"") -> 0 | W48: =IF(ISNUMBER(F48),ROUND(F48/'05_Assumptions'!$B$4,0),"") -> 2 | X48: =IF(AND(ISNUMBER(W48),ISNUMBER(J48)),MAX(0,W48-J48),"") -> 1 | Y48: =IF(NOT(ISNUMBER(J48)),"",IF(J48=0,"no RHU",IF(F48/J48>'05_Assumptions'!$B$4,"Yes","No"))) -> Yes | Z48: =IF(ISNUMBER(H48),H48,IF(AND(ISNUMBER(G48),ISNUMBER(I48)),G48-I48,"")) -> 12 | AA48: =IF(AND(ISNUMBER(G48),G48>0,ISNUMBER(Z48)),Z48/G48,"") -> 0.85714286 | AB48: =IF(AND(ISNUMBER(F48),F48>0,ISNUMBER(M48)),M48/F48*'05_Assumptions'!$B$6,"") | AC48: 'Without a facility' = barangays with no registered barangay health station. Cotabato City is shown for reference and is not a component LGU of the province. | AD48: =IF(ISNUMBER(F48),ROUNDUP(F48/'05_Assumptions'!$B$4,0),"") -> 3 | AE48: =IF(AND(ISNUMBER(AD48),ISNUMBER(J48)),MAX(0,AD48-J48),"") -> 2
A49: MDN | B49: Maguindanao del Norte | C49: Matanog | D49: LGU | E49: MDN · ANNEX A · §A · p. 41 | F49: 41146 | G49: 8 | I49: 1 | J49: 1 | K49: 7 | L49: 0 | N49: 50.4 | O49: 63.5 | P49: 147.6 | Q49: 23.6 | R49: 0.79 | S49: 2.84 | T49: 41146 | U49: =IF(AND(ISNUMBER(J49),J49>0,ISNUMBER(F49)),F49/J49,"no RHU recorded") -> 41146 | V49: =IF(AND(ISNUMBER(T49),ISNUMBER(U49)),U49-T49,"") -> 0 | W49: =IF(ISNUMBER(F49),ROUND(F49/'05_Assumptions'!$B$4,0),"") -> 2 | X49: =IF(AND(ISNUMBER(W49),ISNUMBER(J49)),MAX(0,W49-J49),"") -> 1 | Y49: =IF(NOT(ISNUMBER(J49)),"",IF(J49=0,"no RHU",IF(F49/J49>'05_Assumptions'!$B$4,"Yes","No"))) -> Yes | Z49: =IF(ISNUMBER(H49),H49,IF(AND(ISNUMBER(G49),ISNUMBER(I49)),G49-I49,"")) -> 7 | AA49: =IF(AND(ISNUMBER(G49),G49>0,ISNUMBER(Z49)),Z49/G49,"") -> 0.875 | AB49: =IF(AND(ISNUMBER(F49),F49>0,ISNUMBER(M49)),M49/F49*'05_Assumptions'!$B$6,"") | AC49: 'Without a facility' = barangays with no registered barangay health station. Cotabato City is shown for reference and is not a component LGU of the province. | AD49: =IF(ISNUMBER(F49),ROUNDUP(F49/'05_Assumptions'!$B$4,0),"") -> 3 | AE49: =IF(AND(ISNUMBER(AD49),ISNUMBER(J49)),MAX(0,AD49-J49),"") -> 2
A50: MDN | B50: Maguindanao del Norte | C50: Datu Blah T. Sinsuat | D50: LGU | E50: MDN · ANNEX A · §A · p. 41 | F50: 32088 | G50: 13 | I50: 3 | J50: 1 | K50: 10 | L50: 0 | N50: 41.2 | O50: 24 | P50: 70.9 | Q50: 11.3 | R50: 3.39 | S50: 11.34 | T50: 32088 | U50: =IF(AND(ISNUMBER(J50),J50>0,ISNUMBER(F50)),F50/J50,"no RHU recorded") -> 32088 | V50: =IF(AND(ISNUMBER(T50),ISNUMBER(U50)),U50-T50,"") -> 0 | W50: =IF(ISNUMBER(F50),ROUND(F50/'05_Assumptions'!$B$4,0),"") -> 2 | X50: =IF(AND(ISNUMBER(W50),ISNUMBER(J50)),MAX(0,W50-J50),"") -> 1 | Y50: =IF(NOT(ISNUMBER(J50)),"",IF(J50=0,"no RHU",IF(F50/J50>'05_Assumptions'!$B$4,"Yes","No"))) -> Yes | Z50: =IF(ISNUMBER(H50),H50,IF(AND(ISNUMBER(G50),ISNUMBER(I50)),G50-I50,"")) -> 10 | AA50: =IF(AND(ISNUMBER(G50),G50>0,ISNUMBER(Z50)),Z50/G50,"") -> 0.76923077 | AB50: =IF(AND(ISNUMBER(F50),F50>0,ISNUMBER(M50)),M50/F50*'05_Assumptions'!$B$6,"") | AC50: 'Without a facility' = barangays with no registered barangay health station. Cotabato City is shown for reference and is not a component LGU of the province. | AD50: =IF(ISNUMBER(F50),ROUNDUP(F50/'05_Assumptions'!$B$4,0),"") -> 2 | AE50: =IF(AND(ISNUMBER(AD50),ISNUMBER(J50)),MAX(0,AD50-J50),"") -> 1
A51: MDN | B51: Maguindanao del Norte | C51: Kabuntalan | D51: LGU | E51: MDN · ANNEX A · §A · p. 41 | F51: 31863 | G51: 17 | I51: 8 | J51: 1 | K51: 10 | L51: 0 | N51: 85.3 | O51: 69.6 | P51: 122.2 | Q51: 19.6 | R51: 0.43 | S51: 11.56 | T51: 31863 | U51: =IF(AND(ISNUMBER(J51),J51>0,ISNUMBER(F51)),F51/J51,"no RHU recorded") -> 31863 | V51: =IF(AND(ISNUMBER(T51),ISNUMBER(U51)),U51-T51,"") -> 0 | W51: =IF(ISNUMBER(F51),ROUND(F51/'05_Assumptions'!$B$4,0),"") -> 2 | X51: =IF(AND(ISNUMBER(W51),ISNUMBER(J51)),MAX(0,W51-J51),"") -> 1 | Y51: =IF(NOT(ISNUMBER(J51)),"",IF(J51=0,"no RHU",IF(F51/J51>'05_Assumptions'!$B$4,"Yes","No"))) -> Yes | Z51: =IF(ISNUMBER(H51),H51,IF(AND(ISNUMBER(G51),ISNUMBER(I51)),G51-I51,"")) -> 9 | AA51: =IF(AND(ISNUMBER(G51),G51>0,ISNUMBER(Z51)),Z51/G51,"") -> 0.52941176 | AB51: =IF(AND(ISNUMBER(F51),F51>0,ISNUMBER(M51)),M51/F51*'05_Assumptions'!$B$6,"") | AC51: 'Without a facility' = barangays with no registered barangay health station. Cotabato City is shown for reference and is not a component LGU of the province. | AD51: =IF(ISNUMBER(F51),ROUNDUP(F51/'05_Assumptions'!$B$4,0),"") -> 2 | AE51: =IF(AND(ISNUMBER(AD51),ISNUMBER(J51)),MAX(0,AD51-J51),"") -> 1
A52: MDN | B52: Maguindanao del Norte | C52: Sultan Mastura | D52: LGU | E52: MDN · ANNEX A · §A · p. 41 | F52: 30828 | G52: 13 | I52: 0 | J52: 1 | K52: 13 | L52: 0 | N52: 72.6 | O52: 98 | P52: 303.6 | Q52: 48.6 | R52: 9.51 | S52: 18.4 | T52: 30828 | U52: =IF(AND(ISNUMBER(J52),J52>0,ISNUMBER(F52)),F52/J52,"no RHU recorded") -> 30828 | V52: =IF(AND(ISNUMBER(T52),ISNUMBER(U52)),U52-T52,"") -> 0 | W52: =IF(ISNUMBER(F52),ROUND(F52/'05_Assumptions'!$B$4,0),"") -> 2 | X52: =IF(AND(ISNUMBER(W52),ISNUMBER(J52)),MAX(0,W52-J52),"") -> 1 | Y52: =IF(NOT(ISNUMBER(J52)),"",IF(J52=0,"no RHU",IF(F52/J52>'05_Assumptions'!$B$4,"Yes","No"))) -> Yes | Z52: =IF(ISNUMBER(H52),H52,IF(AND(ISNUMBER(G52),ISNUMBER(I52)),G52-I52,"")) -> 13 | AA52: =IF(AND(ISNUMBER(G52),G52>0,ISNUMBER(Z52)),Z52/G52,"") -> 1 | AB52: =IF(AND(ISNUMBER(F52),F52>0,ISNUMBER(M52)),M52/F52*'05_Assumptions'!$B$6,"") | AC52: 'Without a facility' = barangays with no registered barangay health station. Cotabato City is shown for reference and is not a component LGU of the province. | AD52: =IF(ISNUMBER(F52),ROUNDUP(F52/'05_Assumptions'!$B$4,0),"") -> 2 | AE52: =IF(AND(ISNUMBER(AD52),ISNUMBER(J52)),MAX(0,AD52-J52),"") -> 1
A53: MDN | B53: Maguindanao del Norte | C53: Northern Kabuntalan | D53: LGU | E53: MDN · ANNEX A · §A · p. 41 | F53: 30332 | G53: 11 | I53: 6 | J53: 1 | K53: 5 | L53: 0 | N53: 54.1 | O53: 66.6 | P53: 70.3 | Q53: 11.2 | R53: 0.33 | S53: 3.85 | T53: 30332 | U53: =IF(AND(ISNUMBER(J53),J53>0,ISNUMBER(F53)),F53/J53,"no RHU recorded") -> 30332 | V53: =IF(AND(ISNUMBER(T53),ISNUMBER(U53)),U53-T53,"") -> 0 | W53: =IF(ISNUMBER(F53),ROUND(F53/'05_Assumptions'!$B$4,0),"") -> 2 | X53: =IF(AND(ISNUMBER(W53),ISNUMBER(J53)),MAX(0,W53-J53),"") -> 1 | Y53: =IF(NOT(ISNUMBER(J53)),"",IF(J53=0,"no RHU",IF(F53/J53>'05_Assumptions'!$B$4,"Yes","No"))) -> Yes | Z53: =IF(ISNUMBER(H53),H53,IF(AND(ISNUMBER(G53),ISNUMBER(I53)),G53-I53,"")) -> 5 | AA53: =IF(AND(ISNUMBER(G53),G53>0,ISNUMBER(Z53)),Z53/G53,"") -> 0.45454545 | AB53: =IF(AND(ISNUMBER(F53),F53>0,ISNUMBER(M53)),M53/F53*'05_Assumptions'!$B$6,"") | AC53: 'Without a facility' = barangays with no registered barangay health station. Cotabato City is shown for reference and is not a component LGU of the province. | AD53: =IF(ISNUMBER(F53),ROUNDUP(F53/'05_Assumptions'!$B$4,0),"") -> 2 | AE53: =IF(AND(ISNUMBER(AD53),ISNUMBER(J53)),MAX(0,AD53-J53),"") -> 1
A54: MDN | B54: Maguindanao del Norte | C54: Talitay | D54: LGU | E54: MDN · ANNEX A · §A · p. 41 | F54: 19750 | G54: 9 | I54: 5 | J54: 1 | K54: 4 | L54: 0 | N54: 80.7 | O54: 28.2 | P54: 159.2 | Q54: 25.5 | R54: 1.77 | S54: 5.99 | T54: 19750 | U54: =IF(AND(ISNUMBER(J54),J54>0,ISNUMBER(F54)),F54/J54,"no RHU recorded") -> 19750 | V54: =IF(AND(ISNUMBER(T54),ISNUMBER(U54)),U54-T54,"") -> 0 | W54: =IF(ISNUMBER(F54),ROUND(F54/'05_Assumptions'!$B$4,0),"") -> 1 | X54: =IF(AND(ISNUMBER(W54),ISNUMBER(J54)),MAX(0,W54-J54),"") -> 0 | Y54: =IF(NOT(ISNUMBER(J54)),"",IF(J54=0,"no RHU",IF(F54/J54>'05_Assumptions'!$B$4,"Yes","No"))) -> No | Z54: =IF(ISNUMBER(H54),H54,IF(AND(ISNUMBER(G54),ISNUMBER(I54)),G54-I54,"")) -> 4 | AA54: =IF(AND(ISNUMBER(G54),G54>0,ISNUMBER(Z54)),Z54/G54,"") -> 0.44444444 | AB54: =IF(AND(ISNUMBER(F54),F54>0,ISNUMBER(M54)),M54/F54*'05_Assumptions'!$B$6,"") | AC54: 'Without a facility' = barangays with no registered barangay health station. Cotabato City is shown for reference and is not a component LGU of the province. | AD54: =IF(ISNUMBER(F54),ROUNDUP(F54/'05_Assumptions'!$B$4,0),"") -> 1 | AE54: =IF(AND(ISNUMBER(AD54),ISNUMBER(J54)),MAX(0,AD54-J54),"") -> 0
A55: MDN | B55: Maguindanao del Norte | C55: PROVINCE — twelve municipalities | D55: Provincial / area total as annexed | E55: MDN · ANNEX A · §A · p. 41 | F55: 741428 | G55: 221 | I55: 46 | J55: 12 | K55: 178 | L55: 6 | M55: 360 | N55: 60.1 | O55: 59.6 | P55: 158.7 | Q55: 27.7 | R55: 2.47 | S55: 7.35 | T55: 61786 | U55: =IF(AND(ISNUMBER(J55),J55>0,ISNUMBER(F55)),F55/J55,"no RHU recorded") -> 61785.667 | V55: =IF(AND(ISNUMBER(T55),ISNUMBER(U55)),U55-T55,"") -> -0.33333333 | W55: =IF(ISNUMBER(F55),ROUND(F55/'05_Assumptions'!$B$4,0),"") -> 37 | X55: =IF(AND(ISNUMBER(W55),ISNUMBER(J55)),MAX(0,W55-J55),"") -> 25 | Y55: =IF(NOT(ISNUMBER(J55)),"",IF(J55=0,"no RHU",IF(F55/J55>'05_Assumptions'!$B$4,"Yes","No"))) -> Yes | Z55: =IF(ISNUMBER(H55),H55,IF(AND(ISNUMBER(G55),ISNUMBER(I55)),G55-I55,"")) -> 175 | AA55: =IF(AND(ISNUMBER(G55),G55>0,ISNUMBER(Z55)),Z55/G55,"") -> 0.7918552 | AB55: =IF(AND(ISNUMBER(F55),F55>0,ISNUMBER(M55)),M55/F55*'05_Assumptions'!$B$6,"") -> 0.48554951 | AC55: 'Without a facility' = barangays with no registered barangay health station. Cotabato City is shown for reference and is not a component LGU of the province. | AD55: =IF(ISNUMBER(F55),ROUNDUP(F55/'05_Assumptions'!$B$4,0),"") -> 38 | AE55: =IF(AND(ISNUMBER(AD55),ISNUMBER(J55)),MAX(0,AD55-J55),"") -> 26
A56: MDN | B56: Maguindanao del Norte | C56: City of Cotabato (not a component LGU) | D56: Non-component reference (not in provincial total) | E56: MDN · ANNEX A · §A · p. 41 | F56: 383383 | G56: 37 | I56: 1 | J56: 1 | K56: 39 | L56: 6 | M56: 512 | N56: 52.6 | O56: 93.1 | P56: 714.6 | Q56: 114.3 | R56: 6.45 | S56: 5.55 | T56: 383383 | U56: =IF(AND(ISNUMBER(J56),J56>0,ISNUMBER(F56)),F56/J56,"no RHU recorded") -> 383383 | V56: =IF(AND(ISNUMBER(T56),ISNUMBER(U56)),U56-T56,"") -> 0 | W56: =IF(ISNUMBER(F56),ROUND(F56/'05_Assumptions'!$B$4,0),"") -> 19 | X56: =IF(AND(ISNUMBER(W56),ISNUMBER(J56)),MAX(0,W56-J56),"") -> 18 | Y56: =IF(NOT(ISNUMBER(J56)),"",IF(J56=0,"no RHU",IF(F56/J56>'05_Assumptions'!$B$4,"Yes","No"))) -> Yes | Z56: =IF(ISNUMBER(H56),H56,IF(AND(ISNUMBER(G56),ISNUMBER(I56)),G56-I56,"")) -> 36 | AA56: =IF(AND(ISNUMBER(G56),G56>0,ISNUMBER(Z56)),Z56/G56,"") -> 0.97297297 | AB56: =IF(AND(ISNUMBER(F56),F56>0,ISNUMBER(M56)),M56/F56*'05_Assumptions'!$B$6,"") -> 1.3354791 | AC56: 'Without a facility' = barangays with no registered barangay health station. Cotabato City is shown for reference and is not a component LGU of the province. | AD56: =IF(ISNUMBER(F56),ROUNDUP(F56/'05_Assumptions'!$B$4,0),"") -> 20 | AE56: =IF(AND(ISNUMBER(AD56),ISNUMBER(J56)),MAX(0,AD56-J56),"") -> 19
A57: MDS | B57: Maguindanao del Sur | C57: Buluan | D57: LGU | E57: MDS · ANNEX A · § · page not in contents list | F57: 60931 | G57: 7 | I57: 4 | J57: 1 | K57: 2 | L57: 1 | M57: 139 | N57: 63.1 | O57: 74.47 | P57: 236.5 | Q57: 37.8 | R57: 5.12 | T57: 60931 | U57: =IF(AND(ISNUMBER(J57),J57>0,ISNUMBER(F57)),F57/J57,"no RHU recorded") -> 60931 | V57: =IF(AND(ISNUMBER(T57),ISNUMBER(U57)),U57-T57,"") -> 0 | W57: =IF(ISNUMBER(F57),ROUND(F57/'05_Assumptions'!$B$4,0),"") -> 3 | X57: =IF(AND(ISNUMBER(W57),ISNUMBER(J57)),MAX(0,W57-J57),"") -> 2 | Y57: =IF(NOT(ISNUMBER(J57)),"",IF(J57=0,"no RHU",IF(F57/J57>'05_Assumptions'!$B$4,"Yes","No"))) -> Yes | Z57: =IF(ISNUMBER(H57),H57,IF(AND(ISNUMBER(G57),ISNUMBER(I57)),G57-I57,"")) -> 3 | AA57: =IF(AND(ISNUMBER(G57),G57>0,ISNUMBER(Z57)),Z57/G57,"") -> 0.42857143 | AB57: =IF(AND(ISNUMBER(F57),F57>0,ISNUMBER(M57)),M57/F57*'05_Assumptions'!$B$6,"") -> 2.281269 | AC57: 'Without a facility' = barangays carrying no registered facility of any type. Beds are licensed beds of all classes. | AD57: =IF(ISNUMBER(F57),ROUNDUP(F57/'05_Assumptions'!$B$4,0),"") -> 4 | AE57: =IF(AND(ISNUMBER(AD57),ISNUMBER(J57)),MAX(0,AD57-J57),"") -> 3
A58: MDS | B58: Maguindanao del Sur | C58: South Upi | D58: LGU | E58: MDS · ANNEX A · § · page not in contents list | F58: 50018 | G58: 11 | I58: 0 | J58: 1 | K58: 10 | L58: 1 | M58: 27 | N58: 79.95 | O58: 63 | P58: 134.57 | Q58: 21.5 | R58: 1.79 | T58: 50018 | U58: =IF(AND(ISNUMBER(J58),J58>0,ISNUMBER(F58)),F58/J58,"no RHU recorded") -> 50018 | V58: =IF(AND(ISNUMBER(T58),ISNUMBER(U58)),U58-T58,"") -> 0 | W58: =IF(ISNUMBER(F58),ROUND(F58/'05_Assumptions'!$B$4,0),"") -> 3 | X58: =IF(AND(ISNUMBER(W58),ISNUMBER(J58)),MAX(0,W58-J58),"") -> 2 | Y58: =IF(NOT(ISNUMBER(J58)),"",IF(J58=0,"no RHU",IF(F58/J58>'05_Assumptions'!$B$4,"Yes","No"))) -> Yes | Z58: =IF(ISNUMBER(H58),H58,IF(AND(ISNUMBER(G58),ISNUMBER(I58)),G58-I58,"")) -> 11 | AA58: =IF(AND(ISNUMBER(G58),G58>0,ISNUMBER(Z58)),Z58/G58,"") -> 1 | AB58: =IF(AND(ISNUMBER(F58),F58>0,ISNUMBER(M58)),M58/F58*'05_Assumptions'!$B$6,"") -> 0.53980567 | AC58: 'Without a facility' = barangays carrying no registered facility of any type. Beds are licensed beds of all classes. | AD58: =IF(ISNUMBER(F58),ROUNDUP(F58/'05_Assumptions'!$B$4,0),"") -> 3 | AE58: =IF(AND(ISNUMBER(AD58),ISNUMBER(J58)),MAX(0,AD58-J58),"") -> 2
A59: MDS | B59: Maguindanao del Sur | C59: Pagalungan | D59: LGU | E59: MDS · ANNEX A · § · page not in contents list | F59: 49326 | G59: 12 | I59: 9 | J59: 1 | K59: 3 | L59: 0 | M59: 6 | N59: 44.17 | O59: 43.04 | P59: 80.96 | Q59: 13 | R59: 10.05 | T59: 49326 | U59: =IF(AND(ISNUMBER(J59),J59>0,ISNUMBER(F59)),F59/J59,"no RHU recorded") -> 49326 | V59: =IF(AND(ISNUMBER(T59),ISNUMBER(U59)),U59-T59,"") -> 0 | W59: =IF(ISNUMBER(F59),ROUND(F59/'05_Assumptions'!$B$4,0),"") -> 2 | X59: =IF(AND(ISNUMBER(W59),ISNUMBER(J59)),MAX(0,W59-J59),"") -> 1 | Y59: =IF(NOT(ISNUMBER(J59)),"",IF(J59=0,"no RHU",IF(F59/J59>'05_Assumptions'!$B$4,"Yes","No"))) -> Yes | Z59: =IF(ISNUMBER(H59),H59,IF(AND(ISNUMBER(G59),ISNUMBER(I59)),G59-I59,"")) -> 3 | AA59: =IF(AND(ISNUMBER(G59),G59>0,ISNUMBER(Z59)),Z59/G59,"") -> 0.25 | AB59: =IF(AND(ISNUMBER(F59),F59>0,ISNUMBER(M59)),M59/F59*'05_Assumptions'!$B$6,"") -> 0.1216397 | AC59: 'Without a facility' = barangays carrying no registered facility of any type. Beds are licensed beds of all classes. | AD59: =IF(ISNUMBER(F59),ROUNDUP(F59/'05_Assumptions'!$B$4,0),"") -> 3 | AE59: =IF(AND(ISNUMBER(AD59),ISNUMBER(J59)),MAX(0,AD59-J59),"") -> 2
A60: MDS | B60: Maguindanao del Sur | C60: Pagagawan | D60: LGU | E60: MDS · ANNEX A · § · page not in contents list | F60: 42181 | G60: 11 | I60: 5 | J60: 1 | K60: 5 | L60: 0 | M60: 2 | N60: 48.57 | O60: 30.17 | P60: 118.88 | Q60: 19 | R60: 0.88 | T60: 42181 | U60: =IF(AND(ISNUMBER(J60),J60>0,ISNUMBER(F60)),F60/J60,"no RHU recorded") -> 42181 | V60: =IF(AND(ISNUMBER(T60),ISNUMBER(U60)),U60-T60,"") -> 0 | W60: =IF(ISNUMBER(F60),ROUND(F60/'05_Assumptions'!$B$4,0),"") -> 2 | X60: =IF(AND(ISNUMBER(W60),ISNUMBER(J60)),MAX(0,W60-J60),"") -> 1 | Y60: =IF(NOT(ISNUMBER(J60)),"",IF(J60=0,"no RHU",IF(F60/J60>'05_Assumptions'!$B$4,"Yes","No"))) -> Yes | Z60: =IF(ISNUMBER(H60),H60,IF(AND(ISNUMBER(G60),ISNUMBER(I60)),G60-I60,"")) -> 6 | AA60: =IF(AND(ISNUMBER(G60),G60>0,ISNUMBER(Z60)),Z60/G60,"") -> 0.54545455 | AB60: =IF(AND(ISNUMBER(F60),F60>0,ISNUMBER(M60)),M60/F60*'05_Assumptions'!$B$6,"") -> 0.047414713 | AC60: 'Without a facility' = barangays carrying no registered facility of any type. Beds are licensed beds of all classes. | AD60: =IF(ISNUMBER(F60),ROUNDUP(F60/'05_Assumptions'!$B$4,0),"") -> 3 | AE60: =IF(AND(ISNUMBER(AD60),ISNUMBER(J60)),MAX(0,AD60-J60),"") -> 2
A61: MDS | B61: Maguindanao del Sur | C61: Talayan | D61: LGU | E61: MDS · ANNEX A · § · page not in contents list | F61: 39182 | G61: 15 | I61: 5 | J61: 1 | K61: 9 | L61: 0 | M61: 4 | N61: 62.2 | O61: 91.58 | P61: 171.58 | Q61: 27.5 | R61: 2.81 | T61: 39182 | U61: =IF(AND(ISNUMBER(J61),J61>0,ISNUMBER(F61)),F61/J61,"no RHU recorded") -> 39182 | V61: =IF(AND(ISNUMBER(T61),ISNUMBER(U61)),U61-T61,"") -> 0 | W61: =IF(ISNUMBER(F61),ROUND(F61/'05_Assumptions'!$B$4,0),"") -> 2 | X61: =IF(AND(ISNUMBER(W61),ISNUMBER(J61)),MAX(0,W61-J61),"") -> 1 | Y61: =IF(NOT(ISNUMBER(J61)),"",IF(J61=0,"no RHU",IF(F61/J61>'05_Assumptions'!$B$4,"Yes","No"))) -> Yes | Z61: =IF(ISNUMBER(H61),H61,IF(AND(ISNUMBER(G61),ISNUMBER(I61)),G61-I61,"")) -> 10 | AA61: =IF(AND(ISNUMBER(G61),G61>0,ISNUMBER(Z61)),Z61/G61,"") -> 0.66666667 | AB61: =IF(AND(ISNUMBER(F61),F61>0,ISNUMBER(M61)),M61/F61*'05_Assumptions'!$B$6,"") -> 0.10208769 | AC61: 'Without a facility' = barangays carrying no registered facility of any type. Beds are licensed beds of all classes. | AD61: =IF(ISNUMBER(F61),ROUNDUP(F61/'05_Assumptions'!$B$4,0),"") -> 2 | AE61: =IF(AND(ISNUMBER(AD61),ISNUMBER(J61)),MAX(0,AD61-J61),"") -> 1
A62: MDS | B62: Maguindanao del Sur | C62: Datu Paglas | D62: LGU | E62: MDS · ANNEX A · § · page not in contents list | F62: 38446 | G62: 23 | I62: 13 | J62: 1 | K62: 9 | L62: 1 | M62: 33 | N62: 89.07 | O62: 94.7 | P62: 169.62 | Q62: 27.1 | R62: 10.08 | T62: 38446 | U62: =IF(AND(ISNUMBER(J62),J62>0,ISNUMBER(F62)),F62/J62,"no RHU recorded") -> 38446 | V62: =IF(AND(ISNUMBER(T62),ISNUMBER(U62)),U62-T62,"") -> 0 | W62: =IF(ISNUMBER(F62),ROUND(F62/'05_Assumptions'!$B$4,0),"") -> 2 | X62: =IF(AND(ISNUMBER(W62),ISNUMBER(J62)),MAX(0,W62-J62),"") -> 1 | Y62: =IF(NOT(ISNUMBER(J62)),"",IF(J62=0,"no RHU",IF(F62/J62>'05_Assumptions'!$B$4,"Yes","No"))) -> Yes | Z62: =IF(ISNUMBER(H62),H62,IF(AND(ISNUMBER(G62),ISNUMBER(I62)),G62-I62,"")) -> 10 | AA62: =IF(AND(ISNUMBER(G62),G62>0,ISNUMBER(Z62)),Z62/G62,"") -> 0.43478261 | AB62: =IF(AND(ISNUMBER(F62),F62>0,ISNUMBER(M62)),M62/F62*'05_Assumptions'!$B$6,"") -> 0.85834677 | AC62: 'Without a facility' = barangays carrying no registered facility of any type. Beds are licensed beds of all classes. | AD62: =IF(ISNUMBER(F62),ROUNDUP(F62/'05_Assumptions'!$B$4,0),"") -> 2 | AE62: =IF(AND(ISNUMBER(AD62),ISNUMBER(J62)),MAX(0,AD62-J62),"") -> 1
A63: MDS | B63: Maguindanao del Sur | C63: Shariff Aguak | D63: LGU | E63: MDS · ANNEX A · § · page not in contents list | F63: 37437 | G63: 13 | I63: 6 | J63: 1 | K63: 6 | L63: 1 | M63: 74 | N63: 62.36 | O63: 83.06 | P63: 218.57 | Q63: 35 | R63: 2.39 | T63: 37437 | U63: =IF(AND(ISNUMBER(J63),J63>0,ISNUMBER(F63)),F63/J63,"no RHU recorded") -> 37437 | V63: =IF(AND(ISNUMBER(T63),ISNUMBER(U63)),U63-T63,"") -> 0 | W63: =IF(ISNUMBER(F63),ROUND(F63/'05_Assumptions'!$B$4,0),"") -> 2 | X63: =IF(AND(ISNUMBER(W63),ISNUMBER(J63)),MAX(0,W63-J63),"") -> 1 | Y63: =IF(NOT(ISNUMBER(J63)),"",IF(J63=0,"no RHU",IF(F63/J63>'05_Assumptions'!$B$4,"Yes","No"))) -> Yes | Z63: =IF(ISNUMBER(H63),H63,IF(AND(ISNUMBER(G63),ISNUMBER(I63)),G63-I63,"")) -> 7 | AA63: =IF(AND(ISNUMBER(G63),G63>0,ISNUMBER(Z63)),Z63/G63,"") -> 0.53846154 | AB63: =IF(AND(ISNUMBER(F63),F63>0,ISNUMBER(M63)),M63/F63*'05_Assumptions'!$B$6,"") -> 1.9766541 | AC63: 'Without a facility' = barangays carrying no registered facility of any type. Beds are licensed beds of all classes. | AD63: =IF(ISNUMBER(F63),ROUNDUP(F63/'05_Assumptions'!$B$4,0),"") -> 2 | AE63: =IF(AND(ISNUMBER(AD63),ISNUMBER(J63)),MAX(0,AD63-J63),"") -> 1
A64: MDS | B64: Maguindanao del Sur | C64: Datu Abdullah Sangki | D64: LGU | E64: MDS · ANNEX A · § · page not in contents list | F64: 35274 | G64: 10 | I64: 5 | J64: 1 | K64: 3 | L64: 0 | M64: 7 | N64: 52.03 | O64: 72.41 | P64: 176.88 | Q64: 28.3 | R64: 0.47 | T64: 35274 | U64: =IF(AND(ISNUMBER(J64),J64>0,ISNUMBER(F64)),F64/J64,"no RHU recorded") -> 35274 | V64: =IF(AND(ISNUMBER(T64),ISNUMBER(U64)),U64-T64,"") -> 0 | W64: =IF(ISNUMBER(F64),ROUND(F64/'05_Assumptions'!$B$4,0),"") -> 2 | X64: =IF(AND(ISNUMBER(W64),ISNUMBER(J64)),MAX(0,W64-J64),"") -> 1 | Y64: =IF(NOT(ISNUMBER(J64)),"",IF(J64=0,"no RHU",IF(F64/J64>'05_Assumptions'!$B$4,"Yes","No"))) -> Yes | Z64: =IF(ISNUMBER(H64),H64,IF(AND(ISNUMBER(G64),ISNUMBER(I64)),G64-I64,"")) -> 5 | AA64: =IF(AND(ISNUMBER(G64),G64>0,ISNUMBER(Z64)),Z64/G64,"") -> 0.5 | AB64: =IF(AND(ISNUMBER(F64),F64>0,ISNUMBER(M64)),M64/F64*'05_Assumptions'!$B$6,"") -> 0.19844645 | AC64: 'Without a facility' = barangays carrying no registered facility of any type. Beds are licensed beds of all classes. | AD64: =IF(ISNUMBER(F64),ROUNDUP(F64/'05_Assumptions'!$B$4,0),"") -> 2 | AE64: =IF(AND(ISNUMBER(AD64),ISNUMBER(J64)),MAX(0,AD64-J64),"") -> 1
A65: MDS | B65: Maguindanao del Sur | C65: Datu Anggal Midtimbang | D65: LGU | E65: MDS · ANNEX A · § · page not in contents list | F65: 35243 | G65: 7 | I65: 1 | J65: 1 | K65: 5 | L65: 0 | M65: 39 | N65: 63.68 | O65: 63.38 | P65: 111.43 | Q65: 17.8 | R65: 0.61 | T65: 35243 | U65: =IF(AND(ISNUMBER(J65),J65>0,ISNUMBER(F65)),F65/J65,"no RHU recorded") -> 35243 | V65: =IF(AND(ISNUMBER(T65),ISNUMBER(U65)),U65-T65,"") -> 0 | W65: =IF(ISNUMBER(F65),ROUND(F65/'05_Assumptions'!$B$4,0),"") -> 2 | X65: =IF(AND(ISNUMBER(W65),ISNUMBER(J65)),MAX(0,W65-J65),"") -> 1 | Y65: =IF(NOT(ISNUMBER(J65)),"",IF(J65=0,"no RHU",IF(F65/J65>'05_Assumptions'!$B$4,"Yes","No"))) -> Yes | Z65: =IF(ISNUMBER(H65),H65,IF(AND(ISNUMBER(G65),ISNUMBER(I65)),G65-I65,"")) -> 6 | AA65: =IF(AND(ISNUMBER(G65),G65>0,ISNUMBER(Z65)),Z65/G65,"") -> 0.85714286 | AB65: =IF(AND(ISNUMBER(F65),F65>0,ISNUMBER(M65)),M65/F65*'05_Assumptions'!$B$6,"") -> 1.1066027 | AC65: 'Without a facility' = barangays carrying no registered facility of any type. Beds are licensed beds of all classes. | AD65: =IF(ISNUMBER(F65),ROUNDUP(F65/'05_Assumptions'!$B$4,0),"") -> 2 | AE65: =IF(AND(ISNUMBER(AD65),ISNUMBER(J65)),MAX(0,AD65-J65),"") -> 1
A66: MDS | B66: Maguindanao del Sur | C66: Gen. S.K. Pendatun | D66: LGU | E66: MDS · ANNEX A · § · page not in contents list | F66: 33710 | G66: 19 | I66: 0 | J66: 1 | K66: 18 | L66: 0 | M66: 21 | N66: 62.71 | O66: 82.52 | P66: 210.42 | Q66: 33.7 | R66: 4.27 | T66: 33710 | U66: =IF(AND(ISNUMBER(J66),J66>0,ISNUMBER(F66)),F66/J66,"no RHU recorded") -> 33710 | V66: =IF(AND(ISNUMBER(T66),ISNUMBER(U66)),U66-T66,"") -> 0 | W66: =IF(ISNUMBER(F66),ROUND(F66/'05_Assumptions'!$B$4,0),"") -> 2 | X66: =IF(AND(ISNUMBER(W66),ISNUMBER(J66)),MAX(0,W66-J66),"") -> 1 | Y66: =IF(NOT(ISNUMBER(J66)),"",IF(J66=0,"no RHU",IF(F66/J66>'05_Assumptions'!$B$4,"Yes","No"))) -> Yes | Z66: =IF(ISNUMBER(H66),H66,IF(AND(ISNUMBER(G66),ISNUMBER(I66)),G66-I66,"")) -> 19 | AA66: =IF(AND(ISNUMBER(G66),G66>0,ISNUMBER(Z66)),Z66/G66,"") -> 1 | AB66: =IF(AND(ISNUMBER(F66),F66>0,ISNUMBER(M66)),M66/F66*'05_Assumptions'!$B$6,"") -> 0.62296055 | AC66: 'Without a facility' = barangays carrying no registered facility of any type. Beds are licensed beds of all classes. | AD66: =IF(ISNUMBER(F66),ROUNDUP(F66/'05_Assumptions'!$B$4,0),"") -> 2 | AE66: =IF(AND(ISNUMBER(AD66),ISNUMBER(J66)),MAX(0,AD66-J66),"") -> 1
A67: MDS | B67: Maguindanao del Sur | C67: Datu Saudi-Ampatuan | D67: LGU | E67: MDS · ANNEX A · § · page not in contents list | F67: 33374 | G67: 8 | I67: 0 | J67: 1 | K67: 6 | L67: 0 | M67: 27 | N67: 37.41 | O67: 74.93 | P67: 191.8 | Q67: 30.7 | R67: 11.16 | T67: 33374 | U67: =IF(AND(ISNUMBER(J67),J67>0,ISNUMBER(F67)),F67/J67,"no RHU recorded") -> 33374 | V67: =IF(AND(ISNUMBER(T67),ISNUMBER(U67)),U67-T67,"") -> 0 | W67: =IF(ISNUMBER(F67),ROUND(F67/'05_Assumptions'!$B$4,0),"") -> 2 | X67: =IF(AND(ISNUMBER(W67),ISNUMBER(J67)),MAX(0,W67-J67),"") -> 1 | Y67: =IF(NOT(ISNUMBER(J67)),"",IF(J67=0,"no RHU",IF(F67/J67>'05_Assumptions'!$B$4,"Yes","No"))) -> Yes | Z67: =IF(ISNUMBER(H67),H67,IF(AND(ISNUMBER(G67),ISNUMBER(I67)),G67-I67,"")) -> 8 | AA67: =IF(AND(ISNUMBER(G67),G67>0,ISNUMBER(Z67)),Z67/G67,"") -> 1 | AB67: =IF(AND(ISNUMBER(F67),F67>0,ISNUMBER(M67)),M67/F67*'05_Assumptions'!$B$6,"") -> 0.809013 | AC67: 'Without a facility' = barangays carrying no registered facility of any type. Beds are licensed beds of all classes. | AD67: =IF(ISNUMBER(F67),ROUNDUP(F67/'05_Assumptions'!$B$4,0),"") -> 2 | AE67: =IF(AND(ISNUMBER(AD67),ISNUMBER(J67)),MAX(0,AD67-J67),"") -> 1
A68: MDS | B68: Maguindanao del Sur | C68: Mamasapano | D68: LGU | E68: MDS · ANNEX A · § · page not in contents list | F68: 32831 | G68: 14 | I68: 7 | J68: 1 | K68: 6 | L68: 0 | M68: 2 | N68: 45.16 | O68: 33.38 | P68: 102.19 | Q68: 16.4 | R68: 4 | T68: 32831 | U68: =IF(AND(ISNUMBER(J68),J68>0,ISNUMBER(F68)),F68/J68,"no RHU recorded") -> 32831 | V68: =IF(AND(ISNUMBER(T68),ISNUMBER(U68)),U68-T68,"") -> 0 | W68: =IF(ISNUMBER(F68),ROUND(F68/'05_Assumptions'!$B$4,0),"") -> 2 | X68: =IF(AND(ISNUMBER(W68),ISNUMBER(J68)),MAX(0,W68-J68),"") -> 1 | Y68: =IF(NOT(ISNUMBER(J68)),"",IF(J68=0,"no RHU",IF(F68/J68>'05_Assumptions'!$B$4,"Yes","No"))) -> Yes | Z68: =IF(ISNUMBER(H68),H68,IF(AND(ISNUMBER(G68),ISNUMBER(I68)),G68-I68,"")) -> 7 | AA68: =IF(AND(ISNUMBER(G68),G68>0,ISNUMBER(Z68)),Z68/G68,"") -> 0.5 | AB68: =IF(AND(ISNUMBER(F68),F68>0,ISNUMBER(M68)),M68/F68*'05_Assumptions'!$B$6,"") -> 0.060918035 | AC68: 'Without a facility' = barangays carrying no registered facility of any type. Beds are licensed beds of all classes. | AD68: =IF(ISNUMBER(F68),ROUNDUP(F68/'05_Assumptions'!$B$4,0),"") -> 2 | AE68: =IF(AND(ISNUMBER(AD68),ISNUMBER(J68)),MAX(0,AD68-J68),"") -> 1
... A81: MDS | B81: Maguindanao del Sur | C81: PROVINCE | D81: Provincial / area total as annexed | E81: MDS · ANNEX A · § · page not in contents list | F81: 813243 | G81: 287 | I81: 132 | J81: 24 | K81: 128 | L81: 6 | M81: 784 | N81: 58.1 | O81: 58.83 | P81: 163.29 | Q81: 26.3 | R81: 3.96 | T81: 33885 | U81: =IF(AND(ISNUMBER(J81),J81>0,ISNUMBER(F81)),F81/J81,"no RHU recorded") -> 33885.125 | V81: =IF(AND(ISNUMBER(T81),ISNUMBER(U81)),U81-T81,"") -> 0.125 | W81: =IF(ISNUMBER(F81),ROUND(F81/'05_Assumptions'!$B$4,0),"") -> 41 | X81: =IF(AND(ISNUMBER(W81),ISNUMBER(J81)),MAX(0,W81-J81),"") -> 17 | Y81: =IF(NOT(ISNUMBER(J81)),"",IF(J81=0,"no RHU",IF(F81/J81>'05_Assumptions'!$B$4,"Yes","No"))) -> Yes | Z81: =IF(ISNUMBER(H81),H81,IF(AND(ISNUMBER(G81),ISNUMBER(I81)),G81-I81,"")) -> 155 | AA81: =IF(AND(ISNUMBER(G81),G81>0,ISNUMBER(Z81)),Z81/G81,"") -> 0.54006969 | AB81: =IF(AND(ISNUMBER(F81),F81>0,ISNUMBER(M81)),M81/F81*'05_Assumptions'!$B$6,"") -> 0.9640415 | AC81: 'Without a facility' = barangays carrying no registered facility of any type. Beds are licensed beds of all classes. | AD81: =IF(ISNUMBER(F81),ROUNDUP(F81/'05_Assumptions'!$B$4,0),"") -> 41 | AE81: =IF(AND(ISNUMBER(AD81),ISNUMBER(J81)),MAX(0,AD81-J81),"") -> 17
A82: SGA | B82: Special Geographic Area | C82: Malidegao | D82: LGU | E82: SGA · ANNEX A · § · page not in contents list | F82: 36427 | G82: 7 | H82: 7 | J82: 2 | K82: 7 | M82: 2 | U82: =IF(AND(ISNUMBER(J82),J82>0,ISNUMBER(F82)),F82/J82,"no RHU recorded") -> 18213.5 | V82: =IF(AND(ISNUMBER(T82),ISNUMBER(U82)),U82-T82,"") | W82: =IF(ISNUMBER(F82),ROUND(F82/'05_Assumptions'!$B$4,0),"") -> 2 | X82: =IF(AND(ISNUMBER(W82),ISNUMBER(J82)),MAX(0,W82-J82),"") -> 0 | Y82: =IF(NOT(ISNUMBER(J82)),"",IF(J82=0,"no RHU",IF(F82/J82>'05_Assumptions'!$B$4,"Yes","No"))) -> No | Z82: =IF(ISNUMBER(H82),H82,IF(AND(ISNUMBER(G82),ISNUMBER(I82)),G82-I82,"")) -> 7 | AA82: =IF(AND(ISNUMBER(G82),G82>0,ISNUMBER(Z82)),Z82/G82,"") -> 1 | AB82: =IF(AND(ISNUMBER(F82),F82>0,ISNUMBER(M82)),M82/F82*'05_Assumptions'!$B$6,"") -> 0.054904329 | AC82: Rural health units are on the REGISTER basis (RHU reg.); the operating basis is lower (6 area-wide against 9 registered). 'With a facility' is the municipalities' own enumeration of service points, which reaches 63 of 63 barangays; the national register reaches 57. | AD82: =IF(ISNUMBER(F82),ROUNDUP(F82/'05_Assumptions'!$B$4,0),"") -> 2 | AE82: =IF(AND(ISNUMBER(AD82),ISNUMBER(J82)),MAX(0,AD82-J82),"") -> 0
A83: SGA | B83: Special Geographic Area | C83: Tugunan | D83: LGU | E83: SGA · ANNEX A · § · page not in contents list | F83: 33721 | G83: 9 | H83: 9 | J83: 1 | K83: 8 | M83: 2 | U83: =IF(AND(ISNUMBER(J83),J83>0,ISNUMBER(F83)),F83/J83,"no RHU recorded") -> 33721 | V83: =IF(AND(ISNUMBER(T83),ISNUMBER(U83)),U83-T83,"") | W83: =IF(ISNUMBER(F83),ROUND(F83/'05_Assumptions'!$B$4,0),"") -> 2 | X83: =IF(AND(ISNUMBER(W83),ISNUMBER(J83)),MAX(0,W83-J83),"") -> 1 | Y83: =IF(NOT(ISNUMBER(J83)),"",IF(J83=0,"no RHU",IF(F83/J83>'05_Assumptions'!$B$4,"Yes","No"))) -> Yes | Z83: =IF(ISNUMBER(H83),H83,IF(AND(ISNUMBER(G83),ISNUMBER(I83)),G83-I83,"")) -> 9 | AA83: =IF(AND(ISNUMBER(G83),G83>0,ISNUMBER(Z83)),Z83/G83,"") -> 1 | AB83: =IF(AND(ISNUMBER(F83),F83>0,ISNUMBER(M83)),M83/F83*'05_Assumptions'!$B$6,"") -> 0.059310222 | AC83: Rural health units are on the REGISTER basis (RHU reg.); the operating basis is lower (6 area-wide against 9 registered). 'With a facility' is the municipalities' own enumeration of service points, which reaches 63 of 63 barangays; the national register reaches 57. | AD83: =IF(ISNUMBER(F83),ROUNDUP(F83/'05_Assumptions'!$B$4,0),"") -> 2 | AE83: =IF(AND(ISNUMBER(AD83),ISNUMBER(J83)),MAX(0,AD83-J83),"") -> 1
A84: SGA | B84: Special Geographic Area | C84: Kapalawan | D84: LGU | E84: SGA · ANNEX A · § · page not in contents list | F84: 29191 | G84: 7 | H84: 7 | J84: 1 | K84: 7 | M84: 0 | U84: =IF(AND(ISNUMBER(J84),J84>0,ISNUMBER(F84)),F84/J84,"no RHU recorded") -> 29191 | V84: =IF(AND(ISNUMBER(T84),ISNUMBER(U84)),U84-T84,"") | W84: =IF(ISNUMBER(F84),ROUND(F84/'05_Assumptions'!$B$4,0),"") -> 1 | X84: =IF(AND(ISNUMBER(W84),ISNUMBER(J84)),MAX(0,W84-J84),"") -> 0 | Y84: =IF(NOT(ISNUMBER(J84)),"",IF(J84=0,"no RHU",IF(F84/J84>'05_Assumptions'!$B$4,"Yes","No"))) -> Yes | Z84: =IF(ISNUMBER(H84),H84,IF(AND(ISNUMBER(G84),ISNUMBER(I84)),G84-I84,"")) -> 7 | AA84: =IF(AND(ISNUMBER(G84),G84>0,ISNUMBER(Z84)),Z84/G84,"") -> 1 | AB84: =IF(AND(ISNUMBER(F84),F84>0,ISNUMBER(M84)),M84/F84*'05_Assumptions'!$B$6,"") -> 0 | AC84: Rural health units are on the REGISTER basis (RHU reg.); the operating basis is lower (6 area-wide against 9 registered). 'With a facility' is the municipalities' own enumeration of service points, which reaches 63 of 63 barangays; the national register reaches 57. | AD84: =IF(ISNUMBER(F84),ROUNDUP(F84/'05_Assumptions'!$B$4,0),"") -> 2 | AE84: =IF(AND(ISNUMBER(AD84),ISNUMBER(J84)),MAX(0,AD84-J84),"") -> 1
A85: SGA | B85: Special Geographic Area | C85: Ligawasan | D85: LGU | E85: SGA · ANNEX A · § · page not in contents list | F85: 28322 | G85: 7 | H85: 7 | J85: 1 | K85: 5 | M85: 0 | U85: =IF(AND(ISNUMBER(J85),J85>0,ISNUMBER(F85)),F85/J85,"no RHU recorded") -> 28322 | V85: =IF(AND(ISNUMBER(T85),ISNUMBER(U85)),U85-T85,"") | W85: =IF(ISNUMBER(F85),ROUND(F85/'05_Assumptions'!$B$4,0),"") -> 1 | X85: =IF(AND(ISNUMBER(W85),ISNUMBER(J85)),MAX(0,W85-J85),"") -> 0 | Y85: =IF(NOT(ISNUMBER(J85)),"",IF(J85=0,"no RHU",IF(F85/J85>'05_Assumptions'!$B$4,"Yes","No"))) -> Yes | Z85: =IF(ISNUMBER(H85),H85,IF(AND(ISNUMBER(G85),ISNUMBER(I85)),G85-I85,"")) -> 7 | AA85: =IF(AND(ISNUMBER(G85),G85>0,ISNUMBER(Z85)),Z85/G85,"") -> 1 | AB85: =IF(AND(ISNUMBER(F85),F85>0,ISNUMBER(M85)),M85/F85*'05_Assumptions'!$B$6,"") -> 0 | AC85: Rural health units are on the REGISTER basis (RHU reg.); the operating basis is lower (6 area-wide against 9 registered). 'With a facility' is the municipalities' own enumeration of service points, which reaches 63 of 63 barangays; the national register reaches 57. | AD85: =IF(ISNUMBER(F85),ROUNDUP(F85/'05_Assumptions'!$B$4,0),"") -> 2 | AE85: =IF(AND(ISNUMBER(AD85),ISNUMBER(J85)),MAX(0,AD85-J85),"") -> 1
A86: SGA | B86: Special Geographic Area | C86: Kadayangan | D86: LGU | E86: SGA · ANNEX A · § · page not in contents list | F86: 26099 | G86: 7 | H86: 7 | J86: 1 | K86: 7 | M86: 0 | U86: =IF(AND(ISNUMBER(J86),J86>0,ISNUMBER(F86)),F86/J86,"no RHU recorded") -> 26099 | V86: =IF(AND(ISNUMBER(T86),ISNUMBER(U86)),U86-T86,"") | W86: =IF(ISNUMBER(F86),ROUND(F86/'05_Assumptions'!$B$4,0),"") -> 1 | X86: =IF(AND(ISNUMBER(W86),ISNUMBER(J86)),MAX(0,W86-J86),"") -> 0 | Y86: =IF(NOT(ISNUMBER(J86)),"",IF(J86=0,"no RHU",IF(F86/J86>'05_Assumptions'!$B$4,"Yes","No"))) -> Yes | Z86: =IF(ISNUMBER(H86),H86,IF(AND(ISNUMBER(G86),ISNUMBER(I86)),G86-I86,"")) -> 7 | AA86: =IF(AND(ISNUMBER(G86),G86>0,ISNUMBER(Z86)),Z86/G86,"") -> 1 | AB86: =IF(AND(ISNUMBER(F86),F86>0,ISNUMBER(M86)),M86/F86*'05_Assumptions'!$B$6,"") -> 0 | AC86: Rural health units are on the REGISTER basis (RHU reg.); the operating basis is lower (6 area-wide against 9 registered). 'With a facility' is the municipalities' own enumeration of service points, which reaches 63 of 63 barangays; the national register reaches 57. | AD86: =IF(ISNUMBER(F86),ROUNDUP(F86/'05_Assumptions'!$B$4,0),"") -> 2 | AE86: =IF(AND(ISNUMBER(AD86),ISNUMBER(J86)),MAX(0,AD86-J86),"") -> 1
A87: SGA | B87: Special Geographic Area | C87: Nabalawag | D87: LGU | E87: SGA · ANNEX A · § · page not in contents list | F87: 25500 | G87: 7 | H87: 7 | J87: 1 | K87: 7 | M87: 0 | U87: =IF(AND(ISNUMBER(J87),J87>0,ISNUMBER(F87)),F87/J87,"no RHU recorded") -> 25500 | V87: =IF(AND(ISNUMBER(T87),ISNUMBER(U87)),U87-T87,"") | W87: =IF(ISNUMBER(F87),ROUND(F87/'05_Assumptions'!$B$4,0),"") -> 1 | X87: =IF(AND(ISNUMBER(W87),ISNUMBER(J87)),MAX(0,W87-J87),"") -> 0 | Y87: =IF(NOT(ISNUMBER(J87)),"",IF(J87=0,"no RHU",IF(F87/J87>'05_Assumptions'!$B$4,"Yes","No"))) -> Yes | Z87: =IF(ISNUMBER(H87),H87,IF(AND(ISNUMBER(G87),ISNUMBER(I87)),G87-I87,"")) -> 7 | AA87: =IF(AND(ISNUMBER(G87),G87>0,ISNUMBER(Z87)),Z87/G87,"") -> 1 | AB87: =IF(AND(ISNUMBER(F87),F87>0,ISNUMBER(M87)),M87/F87*'05_Assumptions'!$B$6,"") -> 0 | AC87: Rural health units are on the REGISTER basis (RHU reg.); the operating basis is lower (6 area-wide against 9 registered). 'With a facility' is the municipalities' own enumeration of service points, which reaches 63 of 63 barangays; the national register reaches 57. | AD87: =IF(ISNUMBER(F87),ROUNDUP(F87/'05_Assumptions'!$B$4,0),"") -> 2 | AE87: =IF(AND(ISNUMBER(AD87),ISNUMBER(J87)),MAX(0,AD87-J87),"") -> 1
A88: SGA | B88: Special Geographic Area | C88: Pahamuddin | D88: LGU | E88: SGA · ANNEX A · § · page not in contents list | F88: 19262 | G88: 12 | H88: 12 | J88: 1 | K88: 11 | M88: 0 | U88: =IF(AND(ISNUMBER(J88),J88>0,ISNUMBER(F88)),F88/J88,"no RHU recorded") -> 19262 | V88: =IF(AND(ISNUMBER(T88),ISNUMBER(U88)),U88-T88,"") | W88: =IF(ISNUMBER(F88),ROUND(F88/'05_Assumptions'!$B$4,0),"") -> 1 | X88: =IF(AND(ISNUMBER(W88),ISNUMBER(J88)),MAX(0,W88-J88),"") -> 0 | Y88: =IF(NOT(ISNUMBER(J88)),"",IF(J88=0,"no RHU",IF(F88/J88>'05_Assumptions'!$B$4,"Yes","No"))) -> No | Z88: =IF(ISNUMBER(H88),H88,IF(AND(ISNUMBER(G88),ISNUMBER(I88)),G88-I88,"")) -> 12 | AA88: =IF(AND(ISNUMBER(G88),G88>0,ISNUMBER(Z88)),Z88/G88,"") -> 1 | AB88: =IF(AND(ISNUMBER(F88),F88>0,ISNUMBER(M88)),M88/F88*'05_Assumptions'!$B$6,"") -> 0 | AC88: Rural health units are on the REGISTER basis (RHU reg.); the operating basis is lower (6 area-wide against 9 registered). 'With a facility' is the municipalities' own enumeration of service points, which reaches 63 of 63 barangays; the national register reaches 57. | AD88: =IF(ISNUMBER(F88),ROUNDUP(F88/'05_Assumptions'!$B$4,0),"") -> 1 | AE88: =IF(AND(ISNUMBER(AD88),ISNUMBER(J88)),MAX(0,AD88-J88),"") -> 0
A89: SGA | B89: Special Geographic Area | C89: Old Kaabakan | D89: LGU | E89: SGA · ANNEX A · § · page not in contents list | F89: 16181 | G89: 7 | H89: 7 | J89: 1 | K89: 5 | M89: 0 | U89: =IF(AND(ISNUMBER(J89),J89>0,ISNUMBER(F89)),F89/J89,"no RHU recorded") -> 16181 | V89: =IF(AND(ISNUMBER(T89),ISNUMBER(U89)),U89-T89,"") | W89: =IF(ISNUMBER(F89),ROUND(F89/'05_Assumptions'!$B$4,0),"") -> 1 | X89: =IF(AND(ISNUMBER(W89),ISNUMBER(J89)),MAX(0,W89-J89),"") -> 0 | Y89: =IF(NOT(ISNUMBER(J89)),"",IF(J89=0,"no RHU",IF(F89/J89>'05_Assumptions'!$B$4,"Yes","No"))) -> No | Z89: =IF(ISNUMBER(H89),H89,IF(AND(ISNUMBER(G89),ISNUMBER(I89)),G89-I89,"")) -> 7 | AA89: =IF(AND(ISNUMBER(G89),G89>0,ISNUMBER(Z89)),Z89/G89,"") -> 1 | AB89: =IF(AND(ISNUMBER(F89),F89>0,ISNUMBER(M89)),M89/F89*'05_Assumptions'!$B$6,"") -> 0 | AC89: Rural health units are on the REGISTER basis (RHU reg.); the operating basis is lower (6 area-wide against 9 registered). 'With a facility' is the municipalities' own enumeration of service points, which reaches 63 of 63 barangays; the national register reaches 57. | AD89: =IF(ISNUMBER(F89),ROUNDUP(F89/'05_Assumptions'!$B$4,0),"") -> 1 | AE89: =IF(AND(ISNUMBER(AD89),ISNUMBER(J89)),MAX(0,AD89-J89),"") -> 0
A90: SGA | B90: Special Geographic Area | C90: AREA | D90: Provincial / area total as annexed | E90: SGA · ANNEX A · § · page not in contents list | F90: 214703 | G90: 63 | H90: 63 | J90: 9 | K90: 57 | M90: 4 | U90: =IF(AND(ISNUMBER(J90),J90>0,ISNUMBER(F90)),F90/J90,"no RHU recorded") -> 23855.889 | V90: =IF(AND(ISNUMBER(T90),ISNUMBER(U90)),U90-T90,"") | W90: =IF(ISNUMBER(F90),ROUND(F90/'05_Assumptions'!$B$4,0),"") -> 11 | X90: =IF(AND(ISNUMBER(W90),ISNUMBER(J90)),MAX(0,W90-J90),"") -> 2 | Y90: =IF(NOT(ISNUMBER(J90)),"",IF(J90=0,"no RHU",IF(F90/J90>'05_Assumptions'!$B$4,"Yes","No"))) -> Yes | Z90: =IF(ISNUMBER(H90),H90,IF(AND(ISNUMBER(G90),ISNUMBER(I90)),G90-I90,"")) -> 63 | AA90: =IF(AND(ISNUMBER(G90),G90>0,ISNUMBER(Z90)),Z90/G90,"") -> 1 | AB90: =IF(AND(ISNUMBER(F90),F90>0,ISNUMBER(M90)),M90/F90*'05_Assumptions'!$B$6,"") -> 0.018630387 | AC90: Rural health units are on the REGISTER basis (RHU reg.); the operating basis is lower (6 area-wide against 9 registered). 'With a facility' is the municipalities' own enumeration of service points, which reaches 63 of 63 barangays; the national register reaches 57. | AD90: =IF(ISNUMBER(F90),ROUNDUP(F90/'05_Assumptions'!$B$4,0),"") -> 11 | AE90: =IF(AND(ISNUMBER(AD90),ISNUMBER(J90)),MAX(0,AD90-J90),"") -> 2

Sheet 11_Jurisdiction_Rollup
A1: Jurisdiction | B1: Report code | C1: Basis | D1: Population 2024 as printed | E1: LIVE Sum of LGU rows | F1: LIVE Variance | G1: Barangays as printed | H1: LIVE Sum of LGU rows | I1: LIVE Variance | J1: RHUs as printed | K1: LIVE Sum of LGU rows | L1: LIVE Variance | M1: Hospitals as printed | N1: LIVE Sum of LGU rows | O1: LIVE Variance | P1: LIVE RHUs implied at 1:20,000 on summed population | Q1: RHUs implied as printed (Regional Table 4) | R1: LIVE Shortfall | S1: Shortfall as printed (Regional Table 4) | T1: LIVE Variance | U1: Note
A2: Lanao del Sur | B2: LDS | C2: Sum of LGU rows on 10_Municipal_Master, excluding annexed totals and non-component references | D2: 1368137 | E2: =SUMIFS('10_Municipal_Master'!$F$2:$F$90,'10_Municipal_Master'!$A$2:$A$90,$B2,'10_Municipal_Master'!$D$2:$D$90,"LGU") -> 1368137 | F2: =E2-D2 -> 0 | G2: 1159 | H2: =SUMIFS('10_Municipal_Master'!$G$2:$G$90,'10_Municipal_Master'!$A$2:$A$90,$B2,'10_Municipal_Master'!$D$2:$D$90,"LGU") -> 1164 | I2: =H2-G2 -> 5 | J2: 44 | K2: =SUMIFS('10_Municipal_Master'!$J$2:$J$90,'10_Municipal_Master'!$A$2:$A$90,$B2,'10_Municipal_Master'!$D$2:$D$90,"LGU") -> 44 | L2: =K2-J2 -> 0 | M2: 11 | N2: =SUMIFS('10_Municipal_Master'!$L$2:$L$90,'10_Municipal_Master'!$A$2:$A$90,$B2,'10_Municipal_Master'!$D$2:$D$90,"LGU") -> 11 | O2: =N2-M2 -> 0 | P2: =ROUND(E2/'05_Assumptions'!$B$4,0) -> 68 | Q2: 68 | R2: =MAX(0,P2-K2) -> 24 | S2: 24 | T2: =R2-S2 -> 0 | U2: Barangay figure is the 1,159-node model geography carried by Annex A; the volume also states 1,164 current barangays. Regional Table 4 records 44 units held against 68 implied.
A3: Maguindanao del Norte | B3: MDN | C3: Sum of LGU rows on 10_Municipal_Master, excluding annexed totals and non-component references | D3: 741428 | E3: =SUMIFS('10_Municipal_Master'!$F$2:$F$90,'10_Municipal_Master'!$A$2:$A$90,$B3,'10_Municipal_Master'!$D$2:$D$90,"LGU") -> 741428 | F3: =E3-D3 -> 0 | G3: 221 | H3: =SUMIFS('10_Municipal_Master'!$G$2:$G$90,'10_Municipal_Master'!$A$2:$A$90,$B3,'10_Municipal_Master'!$D$2:$D$90,"LGU") -> 221 | I3: =H3-G3 -> 0 | J3: 12 | K3: =SUMIFS('10_Municipal_Master'!$J$2:$J$90,'10_Municipal_Master'!$A$2:$A$90,$B3,'10_Municipal_Master'!$D$2:$D$90,"LGU") -> 12 | L3: =K3-J3 -> 0 | M3: 4 | N3: =SUMIFS('10_Municipal_Master'!$L$2:$L$90,'10_Municipal_Master'!$A$2:$A$90,$B3,'10_Municipal_Master'!$D$2:$D$90,"LGU") -> 6 | O3: =N3-M3 -> 2 | P3: =ROUND(E3/'05_Assumptions'!$B$4,0) -> 37 | Q3: 37 | R3: =MAX(0,P3-K3) -> 25 | S3: 25 | T3: =R3-S3 -> 0 | U3: Twelve component municipalities only; Cotabato City is excluded from the provincial total by the volume's own correction (§4A). Annex A carries 12 RHUs; the hospital count in Regional Table 7 is 4.
A4: Maguindanao del Sur | B4: MDS | C4: Sum of LGU rows on 10_Municipal_Master, excluding annexed totals and non-component references | D4: 813243 | E4: =SUMIFS('10_Municipal_Master'!$F$2:$F$90,'10_Municipal_Master'!$A$2:$A$90,$B4,'10_Municipal_Master'!$D$2:$D$90,"LGU") -> 813243 | F4: =E4-D4 -> 0 | G4: 287 | H4: =SUMIFS('10_Municipal_Master'!$G$2:$G$90,'10_Municipal_Master'!$A$2:$A$90,$B4,'10_Municipal_Master'!$D$2:$D$90,"LGU") -> 287 | I4: =H4-G4 -> 0 | J4: 24 | K4: =SUMIFS('10_Municipal_Master'!$J$2:$J$90,'10_Municipal_Master'!$A$2:$A$90,$B4,'10_Municipal_Master'!$D$2:$D$90,"LGU") -> 24 | L4: =K4-J4 -> 0 | M4: 6 | N4: =SUMIFS('10_Municipal_Master'!$L$2:$L$90,'10_Municipal_Master'!$A$2:$A$90,$B4,'10_Municipal_Master'!$D$2:$D$90,"LGU") -> 6 | O4: =N4-M4 -> 0 | P4: =ROUND(E4/'05_Assumptions'!$B$4,0) -> 41 | Q4: 41 | R4: =MAX(0,P4-K4) -> 17 | S4: 17 | T4: =R4-S4 -> 0 | U4: Twenty-four municipalities. Annex A hospital column counts hospitals only; six infirmaries are carried separately.
A5: Special Geographic Area | B5: SGA | C5: Sum of LGU rows on 10_Municipal_Master, excluding annexed totals and non-component references | D5: 214703 | E5: =SUMIFS('10_Municipal_Master'!$F$2:$F$90,'10_Municipal_Master'!$A$2:$A$90,$B5,'10_Municipal_Master'!$D$2:$D$90,"LGU") -> 214703 | F5: =E5-D5 -> 0 | G5: 63 | H5: =SUMIFS('10_Municipal_Master'!$G$2:$G$90,'10_Municipal_Master'!$A$2:$A$90,$B5,'10_Municipal_Master'!$D$2:$D$90,"LGU") -> 63 | I5: =H5-G5 -> 0 | J5: 9 | K5: =SUMIFS('10_Municipal_Master'!$J$2:$J$90,'10_Municipal_Master'!$A$2:$A$90,$B5,'10_Municipal_Master'!$D$2:$D$90,"LGU") -> 9 | L5: =K5-J5 -> 0 | M5: 0 | N5: =SUMIFS('10_Municipal_Master'!$L$2:$L$90,'10_Municipal_Master'!$A$2:$A$90,$B5,'10_Municipal_Master'!$D$2:$D$90,"LGU") -> 0 | O5: =N5-M5 -> 0 | P5: =ROUND(E5/'05_Assumptions'!$B$4,0) -> 11 | Q5: 11 | R5: =MAX(0,P5-K5) -> 2 | S5: 2 | T5: =R5-S5 -> 0 | U5: Rural health units on the register basis (9). On the operating basis the area holds 6 and the shortfall is 5. No hospital or infirmary of any class exists in the area.
A6: FOUR JURISDICTIONS | B6: BARMM | C6: Sum of the four jurisdiction rows above | D6: =SUM(D2:D5) -> 3137511 | E6: =SUM(E2:E5) -> 3137511 | F6: =SUM(F2:F5) -> 0 | G6: =SUM(G2:G5) -> 1730 | H6: =SUM(H2:H5) -> 1735 | I6: =SUM(I2:I5) -> 5 | J6: =SUM(J2:J5) -> 89 | K6: =SUM(K2:K5) -> 89 | ... T6: =SUM(T2:T5) -> 0 | U6: Regional Annex A states 84 LGUs, 1,735 barangays, 3,137,511 residents, 89 RHUs held against 157 implied and a shortfall of 68, and 21 hospitals. Compare the live sums in this row against those printed figures.
A8: REGIONAL ANNEX A AS PRINTED (BARMM · ANNEX A · §A · p. 28)
A9: Jurisdiction | B9: LGUs | C9: Barangays | D9: Population | 2024 | E9: Registered | facilities | F9: RHUs held / | implied | G9: Barangays with a | first-contact | facility | H9: Hospitals / | LGUs with one | I9: Acute | beds | J9: Beds per | 1,000 | K9: PhilHealth | accreditations | L9: PhilPEN | % | M9: TB det. | % | N9: FHSIS | (of 50) | O9: EBDM | cohort | P9: Referral | completion
A10: Lanao del Sur | B10: 40 | C10: 1,164 current / 1,159 model | D10: 1368137 | E10: 242 | F10: 44 / 68 | G10: 128 | H10: 11 / 7 | I10: 1022 | J10: 0.75 | K10: 86 | L10: 4.34 | M10: 25.7 | N10: 30.46 | O10: 16 of 40 | P10: 0
A11: Maguindanao del Norte | B11: 12 | C11: 221 | D11: 741428 | E11: 224 | F11: 12 / 37 | G11: 175 | H11: 4 / 3 | I11: 360 | J11: 0.49 | K11: 52 | L11: 2.47 | M11: 27.7 | N11: 34.09 | O11: 12 of 12 | P11: 0
A12: Maguindanao del Sur | B12: 24 | C12: 287 | D12: 813243 | E12: 222 | F12: 24 / 41 | G12: 155 | H12: 6 / 6 | I12: 648 | J12: 0.8 | K12: 91 | L12: 3.96 | M12: 26.3 | N12: 32.16 | O12: 21 of 24 | P12: 0
A13: Special Geographic Area | B13: 8 | C13: 63 | D13: 214703 | E13: 68 | F13: 9 / 11 | G13: 57 | H13: 0 / 0 | I13: 0 | J13: 0 | K13: 0 | L13: n.m. | M13: n.m. | N13: 11.25 | O13: 8 of 8 | P13: 0
A14: FOUR JURISDICTIONS | B14: 84 | C14: 1735 | D14: 3137511 | E14: 756 | F14: 89 / 157 | G14: 515 | H14: 21 / 16 | I14: 2030 | J14: 0.65 | K14: 229 of 347 | L14: — | M14: ≈26–28 | N14: 68 units | O14: 57 of 84 | P14: 0

Sheet 12_PhilHealth_Accreditation
A1: PHILHEALTH-ACCREDITED HEALTH CARE INSTITUTIONS, BARMM BY PROVINCE — AS CARRIED BY EACH OF THE FIVE REPORTS
A2: Source for every block: Philippine Health Insurance Corporation returns to IOM, 31 July 2024. Green cells recompute the row total across the province columns and the column total across accreditation classes, and report the variance against the figure printed in that report.
A4: SOURCE ▸ BARMM · TABLE 5 · §6 · p. 18
A5: TITLE AS PRINTED ▸ PhilHealth-accredited health care institutions, BARMM by province
A6: Accreditation class | B6: LDS | C6: MDN | D6: MDS | E6: SGA | F6: Basilan | G6: Sulu | H6: Tawi-Tawi | I6: Cotabato City | J6: BARMM | K6: LIVE Sum of province columns | L6: LIVE Variance vs printed total
A7: Hospitals | B7: 14 | C7: 7 | D7: 11 | E7: 0 | F7: 7 | G7: 8 | H7: 5 | I7: 6 | J7: 58 | K7: =SUM(B7:I7) -> 58 | L7: =IF(ISNUMBER(J7),K7-J7,"") -> 0
A8: — of which Level III | B8: 1 | C8: 0 | D8: 0 | E8: 0 | F8: 0 | G8: 0 | H8: 0 | I8: 1 | J8: 2 | K8: =SUM(B8:I8) -> 2 | L8: =IF(ISNUMBER(J8),K8-J8,"") -> 0
A9: — of which Level II | B9: 0 | C9: 0 | D9: 1 | E9: 0 | F9: 0 | G9: 0 | H9: 0 | I9: 1 | J9: 2 | K9: =SUM(B9:I9) -> 2 | L9: =IF(ISNUMBER(J9),K9-J9,"") -> 0
A10: — of which Level I | B10: 8 | C10: 5 | D10: 3 | E10: 0 | F10: 5 | G10: 5 | H10: 1 | I10: 3 | J10: 30 | K10: =SUM(B10:I10) -> 30 | L10: =IF(ISNUMBER(J10),K10-J10,"") -> 0
A11: — of which primary care facility | B11: 5 | C11: 2 | D11: 7 | E11: 0 | F11: 2 | G11: 3 | H11: 4 | I11: 1 | J11: 24 | K11: =SUM(B11:I11) -> 24 | L11: =IF(ISNUMBER(J11),K11-J11,"") -> 0
A12: Rural health units | B12: 28 | C12: 13 | D12: 23 | E12: 0 | F12: 7 | G12: 7 | H12: 3 | I12: 1 | J12: 82 | K12: =SUM(B12:I12) -> 82 | L12: =IF(ISNUMBER(J12),K12-J12,"") -> 0
A13: — with TB-DOTS and maternity care | B13: 13 | C13: 11 | D13: 19 | E13: 0 | F13: 5 | G13: 6 | H13: 2 | I13: 1 | J13: 57 | K13: =SUM(B13:I13) -> 57 | L13: =IF(ISNUMBER(J13),K13-J13,"") -> 0
A14: Konsulta package providers | B14: 33 | C14: 19 | D14: 28 | E14: 0 | F14: 20 | G14: 11 | H14: 2 | I14: 2 | J14: 115 | K14: =SUM(B14:I14) -> 115 | L14: =IF(ISNUMBER(J14),K14-J14,"") -> 0
A15: Lying-in clinics | B15: 4 | C15: 9 | D15: 26 | E15: 0 | F15: 5 | G15: 0 | H15: 2 | I15: 5 | J15: 51 | K15: =SUM(B15:I15) -> 51 | L15: =IF(ISNUMBER(J15),K15-J15,"") -> 0
A16: Dialysis and haemodialysis | B16: 3 | C16: 0 | D16: 1 | E16: 0 | F16: 1 | G16: 0 | H16: 0 | I16: 4 | J16: 9 | K16: =SUM(B16:I16) -> 9 | L16: =IF(ISNUMBER(J16),K16-J16,"") -> 0
A17: Other packages and laboratories | B17: 4 | C17: 4 | D17: 2 | E17: 0 | F17: 7 | G17: 5 | H17: 2 | I17: 8 | J17: 32 | K17: =SUM(B17:I17) -> 32 | L17: =IF(ISNUMBER(J17),K17-J17,"") -> 0
A18: TOTAL ACCREDITATIONS | B18: 86 | C18: 52 | D18: 91 | E18: 0 | F18: 47 | G18: 31 | H18: 14 | I18: 26 | J18: 347 | K18: =SUM(B18:I18) -> 347 | L18: =IF(ISNUMBER(J18),K18-J18,"") -> 0
A19: LIVE Column sum of the top-level accreditation classes | B19: =B7+B12+B14+B15+B16+B17 -> 86 | C19: =C7+C12+C14+C15+C16+C17 -> 52 | D19: =D7+D12+D14+D15+D16+D17 -> 91 | E19: =E7+E12+E14+E15+E16+E17 -> 0 | F19: =F7+F12+F14+F15+F16+F17 -> 47 | G19: =G7+G12+G14+G15+G16+G17 -> 31 | H19: =H7+H12+H14+H15+H16+H17 -> 14 | I19: =I7+I12+I14+I15+I16+I17 -> 26 | J19: =J7+J12+J14+J15+J16+J17 -> 347
A20: LIVE Variance against TOTAL ACCREDITATIONS as printed | B20: =IF(ISNUMBER(B18),B19-B18,"") -> 0 | C20: =IF(ISNUMBER(C18),C19-C18,"") -> 0 | D20: =IF(ISNUMBER(D18),D19-D18,"") -> 0 | E20: =IF(ISNUMBER(E18),E19-E18,"") -> 0 | F20: =IF(ISNUMBER(F18),F19-F18,"") -> 0 | G20: =IF(ISNUMBER(G18),G19-G18,"") -> 0 | H20: =IF(ISNUMBER(H18),H19-H18,"") -> 0 | I20: =IF(ISNUMBER(I18),I19-I18,"") -> 0 | J20: =IF(ISNUMBER(J18),J19-J18,"") -> 0
A23: SOURCE ▸ LDS · TABLE 5 · §5 · §5.2 · p. 28
A24: TITLE AS PRINTED ▸ PhilHealth-accredited health care institutions, BARMM by province
A25: Accreditation class | B25: Lanao del Sur | C25: Maguindanao del Norte | D25: Maguindanao del Sur | E25: Basilan | F25: Sulu | G25: Tawi-Tawi | H25: Cotabato City | I25: BARMM | J25: LIVE Sum of province columns | K25: LIVE Variance vs printed total
A26: Hospitals | B26: 14 | C26: 7 | D26: 11 | E26: 7 | F26: 8 | G26: 5 | H26: 6 | I26: 58 | J26: =SUM(B26:H26) -> 58 | K26: =IF(ISNUMBER(I26),J26-I26,"") -> 0
A27: of which Level III | B27: 1 | C27: 0 | D27: 0 | E27: 0 | F27: 0 | G27: 0 | H27: 1 | I27: 2 | J27: =SUM(B27:H27) -> 2 | K27: =IF(ISNUMBER(I27),J27-I27,"") -> 0
A28: of which Level I | B28: 8 | C28: 5 | D28: 3 | E28: 5 | F28: 5 | G28: 1 | H28: 3 | I28: 30 | J28: =SUM(B28:H28) -> 30 | K28: =IF(ISNUMBER(I28),J28-I28,"") -> 0
A29: of which primary care facility | B29: 5 | C29: 2 | D29: 7 | E29: 2 | F29: 3 | G29: 4 | H29: 1 | I29: 24 | J29: =SUM(B29:H29) -> 24 | K29: =IF(ISNUMBER(I29),J29-I29,"") -> 0
A30: Rural health units | B30: 28 | C30: 13 | D30: 23 | E30: 7 | F30: 7 | G30: 3 | H30: 1 | I30: 82 | J30: =SUM(B30:H30) -> 82 | K30: =IF(ISNUMBER(I30),J30-I30,"") -> 0
A31: with TB-DOTS and maternity care | B31: 13 | C31: 11 | D31: 19 | E31: 5 | F31: 6 | G31: 2 | H31: 1 | I31: 57 | J31: =SUM(B31:H31) -> 57 | K31: =IF(ISNUMBER(I31),J31-I31,"") -> 0
A32: with maternity care only | B32: 15 | C32: 2 | D32: 3 | E32: 0 | F32: 0 | G32: 1 | H32: 0 | I32: 21 | J32: =SUM(B32:H32) -> 21 | K32: =IF(ISNUMBER(I32),J32-I32,"") -> 0
A33: Konsulta package providers | B33: 33 | C33: 19 | D33: 28 | E33: 20 | F33: 11 | G33: 2 | H33: 2 | I33: 115 | J33: =SUM(B33:H33) -> 115 | K33: =IF(ISNUMBER(I33),J33-I33,"") -> 0
A34: Lying-in clinics | B34: 4 | C34: 9 | D34: 26 | E34: 5 | F34: 0 | G34: 2 | H34: 5 | I34: 51 | J34: =SUM(B34:H34) -> 51 | K34: =IF(ISNUMBER(I34),J34-I34,"") -> 0
A35: Free-standing dialysis / hemodialysis | B35: 3 | C35: 0 | D35: 1 | E35: 1 | F35: 0 | G35: 0 | H35: 4 | I35: 9 | J35: =SUM(B35:H35) -> 9 | K35: =IF(ISNUMBER(I35),J35-I35,"") -> 0
A36: Other packages (animal bite, HIV hub, hospital TB-DOTS) | B36: 3 | C36: 3 | D36: 2 | E36: 7 | F36: 5 | G36: 2 | H36: 4 | I36: 26 | J36: =SUM(B36:H36) -> 26 | K36: =IF(ISNUMBER(I36),J36-I36,"") -> 0
A37: Ambulatory surgical, Z Benefit, isolation and laboratory accreditations | B37: 1 | C37: 1 | D37: 0 | E37: 0 | F37: 0 | G37: 0 | H37: 4 | I37: 6 | J37: =SUM(B37:H37) -> 6 | K37: =IF(ISNUMBER(I37),J37-I37,"") -> 0
A38: Total accreditations | B38: 86 | C38: 52 | D38: 91 | E38: 47 | F38: 31 | G38: 14 | H38: 26 | I38: 347 | J38: =SUM(B38:H38) -> 347 | K38: =IF(ISNUMBER(I38),J38-I38,"") -> 0
A39: LIVE Column sum of the top-level accreditation classes | B39: =B26+B30+B33+B34+B35+B36+B37 -> 86 | C39: =C26+C30+C33+C34+C35+C36+C37 -> 52 | D39: =D26+D30+D33+D34+D35+D36+D37 -> 91 | E39: =E26+E30+E33+E34+E35+E36+E37 -> 47 | F39: =F26+F30+F33+F34+F35+F36+F37 -> 31 | G39: =G26+G30+G33+G34+G35+G36+G37 -> 14 | H39: =H26+H30+H33+H34+H35+H36+H37 -> 26 | I39: =I26+I30+I33+I34+I35+I36+I37 -> 347
A40: LIVE Variance against TOTAL ACCREDITATIONS as printed | B40: =IF(ISNUMBER(B38),B39-B38,"") -> 0 | C40: =IF(ISNUMBER(C38),C39-C38,"") -> 0 | D40: =IF(ISNUMBER(D38),D39-D38,"") -> 0 | E40: =IF(ISNUMBER(E38),E39-E38,"") -> 0 | F40: =IF(ISNUMBER(F38),F39-F38,"") -> 0 | G40: =IF(ISNUMBER(G38),G39-G38,"") -> 0 | H40: =IF(ISNUMBER(H38),H39-H38,"") -> 0 | I40: =IF(ISNUMBER(I38),I39-I38,"") -> 0
A41: Note. Adapted from Philippine Health Insurance Corporation (2024), accredited health care institutions by province and type as of 31 July 2024. Counts are of accreditations, not distinct facilities — rural health units and Konsulta providers overlap in reality and are counted separately here. Lanao del Sur holds 24.8 percent of all BARMM accreditations and holds the region’s only Level III accredited hospital outside Cotabato City. The Integrated Provincial Health Office independently reports 36 of its 39 health units (92.3 percent) as YAKAP-accredited, 30 (76 percent) with maternity care and 28 (71 percent) with TB-DOTS (International Organization for Migration, 2026a).
A44: SOURCE ▸ MDN · TABLE 6 · §5 · §5.2 · p. 22
A45: TITLE AS PRINTED ▸ PhilHealth-accredited health care institutions, BARMM by province
A46: Accreditation class | B46: Mag. del Norte | C46: Lanao del Sur | D46: Mag. del Sur | E46: Basilan | F46: Sulu | G46: Tawi-Tawi | H46: Cotabato City | I46: BARMM | J46: LIVE Sum of province columns | K46: LIVE Variance vs printed total
A47: Hospitals | B47: 7 | C47: 14 | D47: 11 | E47: 7 | F47: 8 | G47: 5 | H47: 6 | I47: 58 | J47: =SUM(B47:H47) -> 58 | K47: =IF(ISNUMBER(I47),J47-I47,"") -> 0
A48: of which Level III | B48: 0 | C48: 1 | D48: 0 | E48: 0 | F48: 0 | G48: 0 | H48: 1 | I48: 2 | J48: =SUM(B48:H48) -> 2 | K48: =IF(ISNUMBER(I48),J48-I48,"") -> 0
A49: of which Level II | B49: 0 | C49: 0 | D49: 1 | E49: 0 | F49: 0 | G49: 0 | H49: 1 | I49: 2 | J49: =SUM(B49:H49) -> 2 | K49: =IF(ISNUMBER(I49),J49-I49,"") -> 0
A50: of which Level I | B50: 5 | C50: 8 | D50: 3 | E50: 5 | F50: 5 | G50: 1 | H50: 3 | I50: 30 | J50: =SUM(B50:H50) -> 30 | K50: =IF(ISNUMBER(I50),J50-I50,"") -> 0
A51: of which primary care facility | B51: 2 | C51: 5 | D51: 7 | E51: 2 | F51: 3 | G51: 4 | H51: 1 | I51: 24 | J51: =SUM(B51:H51) -> 24 | K51: =IF(ISNUMBER(I51),J51-I51,"") -> 0
A52: Rural health units | B52: 13 | C52: 28 | D52: 23 | E52: 7 | F52: 7 | G52: 3 | H52: 1 | I52: 82 | J52: =SUM(B52:H52) -> 82 | K52: =IF(ISNUMBER(I52),J52-I52,"") -> 0
A53: with TB-DOTS and maternity care | B53: 11 | C53: 13 | D53: 19 | E53: 5 | F53: 6 | G53: 2 | H53: 1 | I53: 57 | J53: =SUM(B53:H53) -> 57 | K53: =IF(ISNUMBER(I53),J53-I53,"") -> 0
A54: with maternity care only | B54: 2 | C54: 15 | D54: 3 | E54: 0 | F54: 0 | G54: 1 | H54: 0 | I54: 21 | J54: =SUM(B54:H54) -> 21 | K54: =IF(ISNUMBER(I54),J54-I54,"") -> 0
A55: Konsulta package providers | B55: 19 | C55: 33 | D55: 28 | E55: 20 | F55: 11 | G55: 2 | H55: 2 | I55: 115 | J55: =SUM(B55:H55) -> 115 | K55: =IF(ISNUMBER(I55),J55-I55,"") -> 0
A56: Lying-in clinics | B56: 9 | C56: 4 | D56: 26 | E56: 5 | F56: 0 | G56: 2 | H56: 5 | I56: 51 | J56: =SUM(B56:H56) -> 51 | K56: =IF(ISNUMBER(I56),J56-I56,"") -> 0
A57: Dialysis and haemodialysis | B57: 0 | C57: 3 | D57: 1 | E57: 1 | F57: 0 | G57: 0 | H57: 4 | I57: 9 | J57: =SUM(B57:H57) -> 9 | K57: =IF(ISNUMBER(I57),J57-I57,"") -> 0
A58: Other packages and laboratories | B58: 4 | C58: 4 | D58: 2 | E58: 7 | F58: 5 | G58: 2 | H58: 8 | I58: 32 | J58: =SUM(B58:H58) -> 32 | K58: =IF(ISNUMBER(I58),J58-I58,"") -> 0
A59: Total accreditations | B59: 52 | C59: 86 | D59: 91 | E59: 47 | F59: 31 | G59: 14 | H59: 26 | I59: 347 | J59: =SUM(B59:H59) -> 347 | K59: =IF(ISNUMBER(I59),J59-I59,"") -> 0
A60: LIVE Column sum of the top-level accreditation classes | B60: =B47+B52+B55+B56+B57+B58 -> 52 | C60: =C47+C52+C55+C56+C57+C58 -> 86 | D60: =D47+D52+D55+D56+D57+D58 -> 91 | E60: =E47+E52+E55+E56+E57+E58 -> 47 | F60: =F47+F52+F55+F56+F57+F58 -> 31 | G60: =G47+G52+G55+G56+G57+G58 -> 14 | H60: =H47+H52+H55+H56+H57+H58 -> 26 | I60: =I47+I52+I55+I56+I57+I58 -> 347
A61: LIVE Variance against TOTAL ACCREDITATIONS as printed | B61: =IF(ISNUMBER(B59),B60-B59,"") -> 0 | C61: =IF(ISNUMBER(C59),C60-C59,"") -> 0 | D61: =IF(ISNUMBER(D59),D60-D59,"") -> 0 | E61: =IF(ISNUMBER(E59),E60-E59,"") -> 0 | F61: =IF(ISNUMBER(F59),F60-F59,"") -> 0 | G61: =IF(ISNUMBER(G59),G60-G59,"") -> 0 | H61: =IF(ISNUMBER(H59),H60-H59,"") -> 0 | I61: =IF(ISNUMBER(I59),I60-I59,"") -> 0
A62: Note. Adapted from Philippine Health Insurance Corporation (2024), accredited health care institutions by province and type as of 31 July 2024. Counts are of accreditations, not distinct facilities — rural health units and Konsulta providers overlap in reality and are counted separately here. The “other packages and laboratories” row consolidates animal-bite treatment centres, hospital TB-DOTS, HIV hubs, outpatient malaria packages, ambulatory surgical clinics, Z-benefit packages, catastrophic isolation units and RT-PCR laboratory accreditations. Every row and column of the source table reconciles exactly to its printed totals. Cotabato City is reported by PhilHealth as a separate column and is not included in the Maguindanao del Norte figure, which is the correct treatment and the one adopted throughout this report. The thirteen accredited rural health units against twelve registered units is a discrepancy of record and is carried here because it is what the source states; it should be resolved before an accreditation rate is published.
A65: SOURCE ▸ MDS · TABLE 7 · §5 · §5.2 · p. 20
A66: TITLE AS PRINTED ▸ PhilHealth-accredited health care institutions, BARMM by province
A67: Accreditation class | B67: Maguindanao del Sur | C67: Lanao del Sur | D67: Maguindanao del Norte | E67: Basilan | F67: Sulu | G67: Tawi-Tawi | H67: Cotabato City | I67: BARMM | J67: LIVE Sum of province columns | K67: LIVE Variance vs printed total
A68: Hospitals | B68: 11 | C68: 14 | D68: 7 | E68: 7 | F68: 8 | G68: 5 | H68: 6 | I68: 58 | J68: =SUM(B68:H68) -> 58 | K68: =IF(ISNUMBER(I68),J68-I68,"") -> 0
A69: — of which Level III | B69: 0 | C69: 1 | D69: 0 | E69: 0 | F69: 0 | G69: 0 | H69: 1 | I69: 2 | J69: =SUM(B69:H69) -> 2 | K69: =IF(ISNUMBER(I69),J69-I69,"") -> 0
A70: — of which Level II | B70: 1 | C70: 0 | D70: 0 | E70: 0 | F70: 0 | G70: 0 | H70: 1 | I70: 2 | J70: =SUM(B70:H70) -> 2 | K70: =IF(ISNUMBER(I70),J70-I70,"") -> 0
A71: — of which Level I | B71: 3 | C71: 8 | D71: 5 | E71: 5 | F71: 5 | G71: 1 | H71: 3 | I71: 30 | J71: =SUM(B71:H71) -> 30 | K71: =IF(ISNUMBER(I71),J71-I71,"") -> 0
A72: — of which primary care facility | B72: 7 | C72: 5 | D72: 2 | E72: 2 | F72: 3 | G72: 4 | H72: 1 | I72: 24 | J72: =SUM(B72:H72) -> 24 | K72: =IF(ISNUMBER(I72),J72-I72,"") -> 0
A73: Rural health units | B73: 23 | C73: 28 | D73: 13 | E73: 7 | F73: 7 | G73: 3 | H73: 1 | I73: 82 | J73: =SUM(B73:H73) -> 82 | K73: =IF(ISNUMBER(I73),J73-I73,"") -> 0
A74: — with TB-DOTS and maternity care | B74: 19 | C74: 13 | D74: 11 | E74: 5 | F74: 6 | G74: 2 | H74: 1 | I74: 57 | J74: =SUM(B74:H74) -> 57 | K74: =IF(ISNUMBER(I74),J74-I74,"") -> 0
A75: Konsulta package providers | B75: 28 | C75: 33 | D75: 19 | E75: 20 | F75: 11 | G75: 2 | H75: 2 | I75: 115 | J75: =SUM(B75:H75) -> 115 | K75: =IF(ISNUMBER(I75),J75-I75,"") -> 0
A76: Lying-in clinics | B76: 26 | C76: 4 | D76: 9 | E76: 5 | F76: 0 | G76: 2 | H76: 5 | I76: 51 | J76: =SUM(B76:H76) -> 51 | K76: =IF(ISNUMBER(I76),J76-I76,"") -> 0
A77: — of which private | B77: 22 | C77: 4 | D77: 5 | E77: 2 | F77: 0 | G77: 0 | H77: 3 | I77: 36 | J77: =SUM(B77:H77) -> 36 | K77: =IF(ISNUMBER(I77),J77-I77,"") -> 0
A78: Haemodialysis and dialysis | B78: 1 | C78: 3 | D78: 0 | E78: 1 | F78: 0 | G78: 0 | H78: 4 | I78: 9 | J78: =SUM(B78:H78) -> 9 | K78: =IF(ISNUMBER(I78),J78-I78,"") -> 0
A79: Other packages (animal bite, HIV hub, hospital TB-DOTS) | B79: 2 | C79: 3 | D79: 3 | E79: 7 | F79: 5 | G79: 2 | H79: 4 | I79: 26 | J79: =SUM(B79:H79) -> 26 | K79: =IF(ISNUMBER(I79),J79-I79,"") -> 0
... A81: Total accreditations | B81: 91 | C81: 86 | D81: 52 | E81: 47 | F81: 31 | G81: 14 | H81: 26 | I81: 347 | J81: =SUM(B81:H81) -> 347 | K81: =IF(ISNUMBER(I81),J81-I81,"") -> 0
A82: LIVE Column sum of the top-level accreditation classes | B82: =B68+B73+B75+B76+B78+B79+B80 -> 91 | C82: =C68+C73+C75+C76+C78+C79+C80 -> 86 | D82: =D68+D73+D75+D76+D78+D79+D80 -> 52 | E82: =E68+E73+E75+E76+E78+E79+E80 -> 47 | F82: =F68+F73+F75+F76+F78+F79+F80 -> 31 | G82: =G68+G73+G75+G76+G78+G79+G80 -> 14 | H82: =H68+H73+H75+H76+H78+H79+H80 -> 26 | I82: =I68+I73+I75+I76+I78+I79+I80 -> 347
A83: LIVE Variance against TOTAL ACCREDITATIONS as printed | B83: =IF(ISNUMBER(B81),B82-B81,"") -> 0 | C83: =IF(ISNUMBER(C81),C82-C81,"") -> 0 | D83: =IF(ISNUMBER(D81),D82-D81,"") -> 0 | E83: =IF(ISNUMBER(E81),E82-E81,"") -> 0 | F83: =IF(ISNUMBER(F81),F82-F81,"") -> 0 | G83: =IF(ISNUMBER(G81),G82-G81,"") -> 0 | H83: =IF(ISNUMBER(H81),H82-H81,"") -> 0 | I83: =IF(ISNUMBER(I81),I82-I81,"") -> 0
A84: Note. Philippine Health Insurance Corporation (2024), accredited health care institutions by province and type as of 31 July 2024. Counts are of accreditations, not distinct facilities — a rural health unit accredited for TB-DOTS, maternity care and Konsulta appears in more than one row. All thirteen row totals and all seven area-column totals reconcile. Maguindanao del Sur holds 26.2 per cent of all BARMM accreditations, the largest single share.
A87: SOURCE ▸ SGA · TABLE 7 · §5 · §5.2 · p. 19
A88: TITLE AS PRINTED ▸ PhilHealth-accredited health care institutions, BARMM by province, 31 July 2024
A89: Accreditation class | B89: Lanao del Sur | C89: Maguindanao del Norte | D89: Maguindanao del Sur | E89: Basilan | F89: Sulu | G89: Tawi-Tawi | H89: Cotabato City | I89: BARMM | J89: LIVE Sum of province columns | K89: LIVE Variance vs printed total
A90: I. Hospital | B90: 14 | C90: 7 | D90: 11 | E90: 7 | F90: 8 | G90: 5 | H90: 6 | I90: 58 | J90: =SUM(B90:H90) -> 58 | K90: =IF(ISNUMBER(I90),J90-I90,"") -> 0
A91: of which Level III | B91: 1 | C91: 0 | D91: 0 | E91: 0 | F91: 0 | G91: 0 | H91: 1 | I91: 2 | J91: =SUM(B91:H91) -> 2 | K91: =IF(ISNUMBER(I91),J91-I91,"") -> 0
A92: of which Level II | B92: 0 | C92: 0 | D92: 1 | E92: 0 | F92: 0 | G92: 0 | H92: 1 | I92: 2 | J92: =SUM(B92:H92) -> 2 | K92: =IF(ISNUMBER(I92),J92-I92,"") -> 0
A93: of which Level I | B93: 8 | C93: 5 | D93: 3 | E93: 5 | F93: 5 | G93: 1 | H93: 3 | I93: 30 | J93: =SUM(B93:H93) -> 30 | K93: =IF(ISNUMBER(I93),J93-I93,"") -> 0
A94: of which primary care facility | B94: 5 | C94: 2 | D94: 7 | E94: 2 | F94: 3 | G94: 4 | H94: 1 | I94: 24 | J94: =SUM(B94:H94) -> 24 | K94: =IF(ISNUMBER(I94),J94-I94,"") -> 0
A95: Ambulatory surgical clinic | B95: 0 | C95: 1 | D95: 0 | E95: 0 | F95: 0 | G95: 0 | H95: 0 | I95: 1 | J95: =SUM(B95:H95) -> 1 | K95: =IF(ISNUMBER(I95),J95-I95,"") -> 0
A96: Z Benefit Package | B96: 0 | C96: 0 | D96: 0 | E96: 0 | F96: 0 | G96: 0 | H96: 2 | I96: 2 | J96: =SUM(B96:H96) -> 2 | K96: =IF(ISNUMBER(I96),J96-I96,"") -> 0
A97: II. Rural health unit | B97: 28 | C97: 13 | D97: 23 | E97: 7 | F97: 7 | G97: 3 | H97: 1 | I97: 82 | J97: =SUM(B97:H97) -> 82 | K97: =IF(ISNUMBER(I97),J97-I97,"") -> 0
A98: TB-DOTS and maternity care | B98: 13 | C98: 11 | D98: 19 | E98: 5 | F98: 6 | G98: 2 | H98: 1 | I98: 57 | J98: =SUM(B98:H98) -> 57 | K98: =IF(ISNUMBER(I98),J98-I98,"") -> 0
A99: TB-DOTS only | B99: 0 | C99: 0 | D99: 1 | E99: 2 | F99: 1 | G99: 0 | H99: 0 | I99: 4 | J99: =SUM(B99:H99) -> 4 | K99: =IF(ISNUMBER(I99),J99-I99,"") -> 0
A100: Maternity care only | B100: 15 | C100: 2 | D100: 3 | E100: 0 | F100: 0 | G100: 1 | H100: 0 | I100: 21 | J100: =SUM(B100:H100) -> 21 | K100: =IF(ISNUMBER(I100),J100-I100,"") -> 0
